Workbook

Sheet 2024 -2025-2026
A1: S.No | B1: Authors | C1: Title | D1: Source title | E1: Volume | F1: Issue | G1: Year | H1: DOI | I1: Link | J1: Document Type in Scopus | K1: Document Type as per Report | L1: Department | M1: Name of the Faculty
A2: 1 | B2: Bruntha P.M.; Neebha T.M.; Dhanasekar S.; Pandian S.I.A.; Abraham S.S.; Kumar S.N.; Anitha J. | C2: Lung Nodule Classification using Shallow CNNs and Deep Transfer Learning CNNs | D2: 2021 7th International Conference on Advanced Computing and Communication Systems, ICACCS 2021 | G2: 2021 | H2: 10.1109/ICACCS51430.2021.9441702 | I2: https://www.scopus.com/inward/record.uri?eid=2-s2.0-85108026954&doi=10.1109%2fICACCS51430.2021.9441702&partnerID=40&md5=128e9b7d1c33e42b3181084abffa12ba | J2: Conference paper | K2: Scopus/WoS Conference/Book Chapter/Others | L2: ECE
A3: 2 | B3: Roberts M.K.; Anguraj P. | C3: A Comparative Review of Recent Advances in Decoding Algorithms for Low-Density Parity-Check (LDPC) Codes and Their Applications | D3: Archives of Computational Methods in Engineering | E3: 28 | G3: 2021 | H3: 10.1007/s11831-020-09466-6 | I3: https://www.scopus.com/inward/record.uri?eid=2-s2.0-85088038531&doi=10.1007%2fs11831-020-09466-6&partnerID=40&md5=59ea8e42f6b608cd24a9689459baaa0b | J3: Article | K3: SCI | L3: ECE
A4: 3 | B4: Saravanan M.; Parthasarathy E. | C4: Investigation of RF/Analog Performance of InAs/InGaAs Channel Based Nanowire TFETS | D4: ICCISc 2021 - 2021 International Conference on Communication, Control and Information Sciences, Proceedings | G4: 2021 | H4: 10.1109/ICCISc52257.2021.9484973 | I4: https://www.scopus.com/inward/record.uri?eid=2-s2.0-85113304126&doi=10.1109%2fICCISc52257.2021.9484973&partnerID=40&md5=bbfe557847a5faff57b86f87a849efa6 | J4: Conference paper | K4: Scopus/WoS Conference/Book Chapter/Others | L4: CSE
A5: 4 | B5: Murugan S.; Anandakumar H. | C5: Privacy Information Leakage Prevention in Cognitive Social Mining Applications: Causes and Prevention Measures | D5: Research Anthology on Privatizing and Securing Data | G5: 2021 | H5: 10.4018/978-1-7998-8954-0.ch103 | I5: https://www.scopus.com/inward/record.uri?eid=2-s2.0-85134940087&doi=10.4018%2f978-1-7998-8954-0.ch103&partnerID=40&md5=f7afe281062e02dfb2497391ae8e0022 | J5: Book chapter | K5: Scopus/WoS Conference/Book Chapter/Others | L5: CSE
A6: 5 | B6: Yang C.-Y.; Sharif M.; Ravana S.D.; Haldorai A. | C6: Big Cloud Innovation for Sustainable Wireless Management | D6: Wireless Personal Communications | E6: 117 | G6: 2021 | H6: 10.1007/s11277-021-08250-4 | I6: https://www.scopus.com/inward/record.uri?eid=2-s2.0-85101047207&doi=10.1007%2fs11277-021-08250-4&partnerID=40&md5=8bf5ba1d0c35a10db8cbde3298fab2d8 | J6: Editorial | K6: Scopus/WoS Conference/Book Chapter/Others | L6: CSE
A7: 6 | B7: Roberts M.K.; Anguraj P.; Krishnan T. | C7: Design and Analysis of Improved Low Power and High-Speed N-Bit Adder | D7: 2021 International Conference on Decision Aid Sciences and Application, DASA 2021 | G7: 2021 | H7: 10.1109/DASA53625.2021.9682405 | I7: https://www.scopus.com/inward/record.uri?eid=2-s2.0-85125797289&doi=10.1109%2fDASA53625.2021.9682405&partnerID=40&md5=dfad45ec5053baecd9a47bfdc2c72c74 | J7: Conference paper | K7: Scopus/WoS Conference/Book Chapter/Others | L7: ECE
A8: 7 | B8: Gnanasekaran S.; Chelladurai S.J.S.; Ramakrishnan T.; Sivananthan S.; Padmanaban G.; Arthanari R.; Balasubramanian V. | C8: Optimizing the characteristics of the laser hardfacing process parameters to maximize the wear resistance of Ni-based hard-faced deposits using the RSM technique | D8: Advances in Materials Science and Engineering | E8: 2021 | G8: 2021 | H8: 10.1155/2021/3665631 | I8: https://www.scopus.com/inward/record.uri?eid=2-s2.0-85123056746&doi=10.1155%2f2021%2f3665631&partnerID=40&md5=3876872d08653fa7744d0087e4159ab9 | J8: Retracted | K8: Scopus/WoS Journals | L8: Mech
A9: 8 | B9: Suresh Kumar R.; Senthil Kumar S.; Murugan K.; Hailegiorgis S.M. | C9: Green Machining Characteristics Study of Al-6063 in CNC Milling Using Taguchi Method and Grey Relational Analysis | D9: Advances in Materials Science and Engineering | E9: 2021 | G9: 2021 | H9: 10.1155/2021/4420250 | I9: https://www.scopus.com/inward/record.uri?eid=2-s2.0-85122407842&doi=10.1155%2f2021%2f4420250&partnerID=40&md5=965b77f400f02a00d94ed5d686f0093a | J9: Retracted | K9: Scopus/WoS Journals | L9: Mech
A10: 9 | B10: UMADEVI M.; RATHINAM R.; POORNIMA S.; SANTHI T.; PATTABHI S. | C10: Electrochemical degradation of reactive red 195 from its aqueous solution using ruo2/iro2/tao2 coated titanium electrodes | D10: Asian Journal of Chemistry | E10: 33 | G10: 2021 | H10: 10.14233/ajchem.2021.23330 | I10: https://www.scopus.com/inward/record.uri?eid=2-s2.0-85111191361&doi=10.14233%2fajchem.2021.23330&partnerID=40&md5=0ab257b70b055ac5c152a9c58b7ab0ea | J10: Article | K10: SCI | L10: S&H
A11: 10 | B11: Pradeep R.; Myilsamy K.; Vijaykumar V.R.; Kumar A.S. | C11: An optimized SIR Modeling for Analyzing the Spreading Rate of Covid-19 Pandemic | D11: 2021 7th International Conference on Advanced Computing and Communication Systems, ICACCS 2021 | G11: 2021 | H11: 10.1109/ICACCS51430.2021.9441791 | I11: https://www.scopus.com/inward/record.uri?eid=2-s2.0-85108027811&doi=10.1109%2fICACCS51430.2021.9441791&partnerID=40&md5=f21430870648a3292b1f57493c117b1b | J11: Conference paper | K11: Scopus/WoS Conference/Book Chapter/Others | L11: ECE
A12: 11 | B12: Nisar K.S.; Jothimani K.; Kaliraj K.; Ravichandran C. | C12: An analysis of controllability results for nonlinear Hilfer neutral fractional derivatives with non-dense domain | D12: Chaos, Solitons and Fractals | E12: 146 | G12: 2021 | H12: 10.1016/j.chaos.2021.110915 | I12: https://www.scopus.com/inward/record.uri?eid=2-s2.0-85103787277&doi=10.1016%2fj.chaos.2021.110915&partnerID=40&md5=1e67594cece01cf64b972ea9f1fbcf53 | J12: Article | K12: Scopus/WoS Journals | L12: S&H
A13: 12 | B13: Mayurappriyan P.S.; Loganathan N.; Shanmugapriya M.; Anbarasu P.; Sakthi P.K.A. | C13: Evolution of Outcome Based Engineering Education in India - A Case Study | D13: 2021 7th International Conference on Advanced Computing and Communication Systems, ICACCS 2021 | G13: 2021 | H13: 10.1109/ICACCS51430.2021.9441676 | I13: https://www.scopus.com/inward/record.uri?eid=2-s2.0-85108028501&doi=10.1109%2fICACCS51430.2021.9441676&partnerID=40&md5=6113f61623d1007dac06e2dee4953d2e | J13: Conference paper | K13: Scopus/WoS Conference/Book Chapter/Others | L13: EEE
A14: 13 | B14: Suresh Kumar R.; Senthil Kumar S.; Murugan K.; Guruprasad B.; Manavalla S.; Madhu S.; Hariprabhu M.; Balamuralitharan S.; Venkatesa Prabhu S. | C14: Optimization of CNC End Milling Process Parameters of Low-Carbon Mold Steel Using Response Surface Methodology and Grey Relational Analysis | D14: Advances in Materials Science and Engineering | E14: 2021 | G14: 2021 | H14: 10.1155/2021/4005728 | I14: https://www.scopus.com/inward/record.uri?eid=2-s2.0-85114091035&doi=10.1155%2f2021%2f4005728&partnerID=40&md5=0de58ff56cb65189fd1843767e8a125f | J14: Retracted | K14: Scopus/WoS Journals | L14: Mech
A15: 14 | B15: Haldorai A.; Murugan S.; Ramu A. | C15: Evolution, challenges, and application of intelligent ICT education: An overview | D15: Computer Applications in Engineering Education | E15: 29 | G15: 2021 | H15: 10.1002/cae.22217 | I15: https://www.scopus.com/inward/record.uri?eid=2-s2.0-85081017759&doi=10.1002%2fcae.22217&partnerID=40&md5=cb112dd0f5559a3e89d62d537ef75b4f | J15: Article | K15: SCI | L15: CSE
A16: 15 | B16: Raja L.; Farithkhan A.; Vijayalakshmi K.; Sripriya T.; Krishnan R.; Devnesh K.N. | C16: Design of Cubic Dielectric Resonator Antenna for Biomedical Application | D16: Proceedings of the 2021 IEEE International Conference on Innovative Computing, Intelligent Communication and Smart Electrical Systems, ICSES 2021 | G16: 2021 | H16: 10.1109/ICSES52305.2021.9633792 | I16: https://www.scopus.com/inward/record.uri?eid=2-s2.0-85123806073&doi=10.1109%2fICSES52305.2021.9633792&partnerID=40&md5=027b25145050c1cae0262ad965f1403d | J16: Conference paper | K16: Scopus/WoS Conference/Book Chapter/Others | L16: ECE
A17: 16 | B17: Natarajan Phd B.; Subramanian B.; Kanagaraj K.; Soundararajan R. | C17: Experimental Study on SS 304 Sheet Metal for Bending Process Optimization using Response Surface Method | D17: SAE Technical Papers | E17: Part 173236 | G17: 2021 | H17: 10.4271/2021-28-0268 | I17: https://www.scopus.com/inward/record.uri?eid=2-s2.0-85118604573&doi=10.4271%2f2021-28-0268&partnerID=40&md5=6b0c2d915f9708d4612279c1220b67c0 | J17: Conference paper | K17: Scopus/WoS Conference/Book Chapter/Others | L17: MECH | M17: Ms. Hemalatha R
A18: 17 | B18: Satishkumar P.; Gokila Krishnan G.; Seenivasan S.; Rajarathnam P. | C18: A study on tribological evaluation of hybrid aluminium metal matrix for thermal application | D18: Materials Today: Proceedings | E18: 81 | G18: 2021 | H18: 10.1016/j.matpr.2021.04.389 | I18: https://www.scopus.com/inward/record.uri?eid=2-s2.0-85184719183&doi=10.1016%2fj.matpr.2021.04.389&partnerID=40&md5=6228a690885a95b9f726266c6ad69d13 | J18: Conference paper | K18: Scopus/WoS Conference/Book Chapter/Others | L18: Mech
A19: 18 | B19: Gupta A.K.; Maity T.; H A.; Chauhan Y.K. | C19: An electromagnetic strategy to improve the performance of PV panel under partial shading | D19: Computers and Electrical Engineering | E19: 90 | G19: 2021 | H19: 10.1016/j.compeleceng.2020.106896 | I19: https://www.scopus.com/inward/record.uri?eid=2-s2.0-85094914685&doi=10.1016%2fj.compeleceng.2020.106896&partnerID=40&md5=c86ac01e0edba782a23cf448efc48ae1 | J19: Article | K19: Scopus/WoS Journals | L19: CSE
A20: 19 | B20: Latha R.; Adharsh Babu S.; Vivek Kumar M. | C20: Design and Analysis of Multi-Device Interleaved Boost Converter Driving an Induction Motor | D20: IOP Conference Series: Earth and Environmental Science | E20: 850 | G20: 2021 | H20: 10.1088/1755-1315/850/1/012036 | I20: https://www.scopus.com/inward/record.uri?eid=2-s2.0-85120472296&doi=10.1088%2f1755-1315%2f850%2f1%2f012036&partnerID=40&md5=df1b41a01acafd202c3e625d827f2a33 | J20: Editorial | K20: Scopus/WoS Conference/Book Chapter/Others | L20: ECE
A21: 20 | B21: Sreemathy J.; Naveen Durai K.; Lakshmi Priya E.; Deebika R.; Suganthi K.; Aisshwarya P.T. | C21: Data Integration and ETL: A Theoretical Perspective | D21: 2021 7th International Conference on Advanced Computing and Communication Systems, ICACCS 2021 | G21: 2021 | H21: 10.1109/ICACCS51430.2021.9441997 | I21: https://www.scopus.com/inward/record.uri?eid=2-s2.0-85108022889&doi=10.1109%2fICACCS51430.2021.9441997&partnerID=40&md5=86750bcaf6437255d9b783f3dd74aeb9 | J21: Conference paper | K21: Scopus/WoS Conference/Book Chapter/Others | L21: CSE
A22: 21 | B22: Ramu A.; Chen M.-Y.; Ravana S.D.; Haldorai A. | C22: Signal processing techniques for sustainable cognitive radio communications | D22: Wireless Networks | E22: 27 | G22: 2021 | H22: 10.1007/s11276-020-02503-z | I22: https://www.scopus.com/inward/record.uri?eid=2-s2.0-85096215135&doi=10.1007%2fs11276-020-02503-z&partnerID=40&md5=039240eee283856c9aee62eb1449a773 | J22: Editorial | K22: Scopus/WoS Conference/Book Chapter/Others | L22: CSE
A23: 22 | B23: Gokila A.; Ayyappan S. | C23: Quantum chemical insight properties of glyphosine(N, N-Bis (phosphonomethyl) glycine) – a combined hf and density functional study | D23: Digest Journal of Nanomaterials and Biostructures | E23: 16 | G23: 2021 | H23: 10.15251/DJNB.2021.162.535 | I23: https://www.scopus.com/inward/record.uri?eid=2-s2.0-85148617107&doi=10.15251%2fDJNB.2021.162.535&partnerID=40&md5=e83bc51305aed888c9a2319080e9a880 | J23: Article | K23: Scopus/WoS Journals | L23: S&H
A24: 23 | B24: AnishFathima B.; Mahaboob M. | C24: Design and Analysis of Energy Efficient Domino Logic Architectures with Single Electron Transistors in Pull Down Network and Keeper Topology | D24: EAI Endorsed Transactions on Energy Web | E24: 8 | G24: 2021 | H24: 10.4108/eai.27-11-2020.167287 | I24: https://www.scopus.com/inward/record.uri?eid=2-s2.0-85106659431&doi=10.4108%2feai.27-11-2020.167287&partnerID=40&md5=ada3e79e117acff68735bc1c54e839ce | J24: Article | K24: Scopus/WoS Journals | L24: ECE
A25: 24 | B25: Ganesh R.S.; Anuradha B.; Karthikeyan S.; Vijayalakshmi P.; Ashok M.; Nagaraj V. | C25: Biometrics based Smart and Secured Electronic Voting Machine | D25: Proceedings - 2nd International Conference on Smart Electronics and Communication, ICOSEC 2021 | G25: 2021 | H25: 10.1109/ICOSEC51865.2021.9591865 | I25: https://www.scopus.com/inward/record.uri?eid=2-s2.0-85123174442&doi=10.1109%2fICOSEC51865.2021.9591865&partnerID=40&md5=3d32a9f94aba4a4e394d5f3f156f1d1a | J25: Conference paper | K25: Scopus/WoS Conference/Book Chapter/Others | L25: ECE
A26: 25 | B26: Thamaraimanalan T.; Mohankumar M.; Dhanasekaran S.; Anandakumar H. | C26: Experimental analysis of intelligent vehicle monitoring system using Internet of Things (IoT) | D26: EAI Endorsed Transactions on Energy Web | E26: 8 | G26: 2021 | H26: 10.4108/eai.16-4-2021.169336 | I26: https://www.scopus.com/inward/record.uri?eid=2-s2.0-85121215064&doi=10.4108%2feai.16-4-2021.169336&partnerID=40&md5=fb22578b3d5a2c697d075fc57a14d096 | J26: Article | K26: Scopus/WoS Journals | L26: CSE
A27: 26 | B27: Kowsalya M.; Elakya A.; Pradeep R. | C27: Solar Operated PLC Based Automated Irrigation System with Fault Preventer | D27: 2021 7th International Conference on Advanced Computing and Communication Systems, ICACCS 2021 | G27: 2021 | H27: 10.1109/ICACCS51430.2021.9441796 | I27: https://www.scopus.com/inward/record.uri?eid=2-s2.0-85108026296&doi=10.1109%2fICACCS51430.2021.9441796&partnerID=40&md5=9cd5e15dcde685735ba9b004d06f9fdf | J27: Conference paper | K27: Scopus/WoS Conference/Book Chapter/Others | L27: ECE
A28: 27 | B28: Jothimani K.; Kaliraj K.; Panda S.K.; Nisar K.S.; Raviohandran C. | C28: RESULTS ON CONTROLLABILITY OF NON-DENSELY CHARACTERIZED NEUTRAL FRACTIONAL DELAY DIFFERENTIAL SYSTEM | D28: Evolution Equations and Control Theory | E28: 10 | G28: 2021 | H28: 10.3934/eect.2020083 | I28: https://www.scopus.com/inward/record.uri?eid=2-s2.0-85096688930&doi=10.3934%2feect.2020083&partnerID=40&md5=fb00be2803ab5f3b63f57576777db55a | J28: Article | K28: Scopus/WoS Journals | L28: S&H
A29: 28 | B29: Rathinam R.; Brindha T.; Petchiammal M.; Ibrahim A.M. | C29: Photo-Electrocatalytic Degradation Of Aqueous Rhodamine B Dye Using Titanium Electrodes Coated With RuO2/lrO2/TaO2 | D29: Indian Journal of Environmental Protection | E29: 41 | G29: 2021 | I29: https://www.scopus.com/inward/record.uri?eid=2-s2.0-85126982129&partnerID=40&md5=8654577449f65af5eca05c63d4f4475e | J29: Article | K29: SCI | L29: S&H
A30: 29 | B30: Kingston Roberts M.; Kumari S.; Anguraj P. | C30: Certain investigations on recent advances in the design of decoding algorithms using low-density parity-check codes and its applications | D30: International Journal of Communication Systems | E30: 34 | G30: 2021 | H30: 10.1002/dac.4765 | I30: https://www.scopus.com/inward/record.uri?eid=2-s2.0-85103065887&doi=10.1002%2fdac.4765&partnerID=40&md5=4127316f06f6dfda196321e516fc7c38 | J30: Article | K30: SCI | L30: ECE
A31: 30 | B31: Sureshbabu Y.; Ashoka Varthanan P. | C31: Experimental investigation on four-stroke catalytic coated spark ignition engine to promote cleaner environment | D31: International Journal of Enterprise Network Management | E31: 12 | G31: 2021 | H31: 10.1504/IJENM.2021.116437 | I31: https://www.scopus.com/inward/record.uri?eid=2-s2.0-85111469571&doi=10.1504%2fIJENM.2021.116437&partnerID=40&md5=bad0f35b031b65e88fb8afb386b7410a | J31: Article | K31: Scopus/WoS Journals | L31: MECH
A32: 31 | B32: Alhomdy S.; Thabit F.; Abdulrazzak F.H.; Haldorai A.; Jagtap S. | C32: The role of cloud computing technology: A savior to fight the lockdown in COVID 19 crisis, the benefits, characteristics and applications | D32: International Journal of Intelligent Networks | E32: 2 | G32: 2021 | H32: 10.1016/j.ijin.2021.08.001 | I32: https://www.scopus.com/inward/record.uri?eid=2-s2.0-85129999273&doi=10.1016%2fj.ijin.2021.08.001&partnerID=40&md5=6931497baf6ccd4f4140d9c81eaba233 | J32: Article | K32: SCI | L32: CSE
A33: 32 | B33: Naveen P.; Sivakumar P. | C33: A deep convolution neural network for facial expression recognition | D33: Journal of Current Science and Technology | E33: 11 | G33: 2021 | H33: 10.14456/jcst.2021.40 | I33: https://www.scopus.com/inward/record.uri?eid=2-s2.0-85117325130&doi=10.14456%2fjcst.2021.40&partnerID=40&md5=b698397f86e160870ce3daeffd99d53d | J33: Article | K33: Scopus/WoS Journals | L33: ECE
A34: 33 | B34: Abirami S.K.; Keerthika J. | C34: Critical Evaluation of the Cloud-Based Design and Manufacturing | D34: Journal of Machine and Computing | E34: 1 | G34: 2021 | H34: 10.53759/7669/jmc202101019 | I34: https://www.scopus.com/inward/record.uri?eid=2-s2.0-85147532106&doi=10.53759%2f7669%2fjmc202101019&partnerID=40&md5=33847dd9cee4efd5862682e804a2b1fc | J34: Article | K34: SCI | L34: CSE
A35: 34 | B35: Sucharitha Y.; Raj P.A.C.; Karthik T.S.; Kapila D.; Mathiazhagan V.; Walia R. | C35: Implementing an effective and secure resource architecture for vlsi block encryption | D35: Journal of Nuclear Energy Science and Power Generation Technology | E35: 10 | G35: 2021 | I35: https://www.scopus.com/inward/record.uri?eid=2-s2.0-85118343937&partnerID=40&md5=98759389645dc4d88a4817aa86a51413 | J35: Article | K35: Scopus/WoS Journals | L35: ECE
A36: 35 | B36: Priyadharshini S.; Shanthi S. | C36: A Survey on Detecting Android Malware Using Machine Learning Technique | D36: 2021 7th International Conference on Advanced Computing and Communication Systems, ICACCS 2021 | G36: 2021 | H36: 10.1109/ICACCS51430.2021.9441712 | I36: https://www.scopus.com/inward/record.uri?eid=2-s2.0-85108027428&doi=10.1109%2fICACCS51430.2021.9441712&partnerID=40&md5=4b14fde7647b20ecaeeb543fd8744972 | J36: Conference paper | K36: Scopus/WoS Conference/Book Chapter/Others | L36: CSE
A37: 36 | B37: Saranya N.; Sakthi Samyuktha M.; Isaac S.; Subhanki B. | C37: Diagnosing Chronic Kidney Disease using KNN Algorithm | D37: 2021 7th International Conference on Advanced Computing and Communication Systems, ICACCS 2021 | G37: 2021 | H37: 10.1109/ICACCS51430.2021.9442039 | I37: https://www.scopus.com/inward/record.uri?eid=2-s2.0-85108022899&doi=10.1109%2fICACCS51430.2021.9442039&partnerID=40&md5=4b795bcf839902d3ce460f4e4e9e2870 | J37: Conference paper | K37: Scopus/WoS Conference/Book Chapter/Others | L37: CSE
A38: 37 | B38: Gayathri N.; Divagaran A.R.; Akhilesh C.D.; Aswiin V.M.; Charan N. | C38: IOT Based Smart Waste Management System | D38: 2021 7th International Conference on Advanced Computing and Communication Systems, ICACCS 2021 | G38: 2021 | H38: 10.1109/ICACCS51430.2021.9441819 | I38: https://www.scopus.com/inward/record.uri?eid=2-s2.0-85108024201&doi=10.1109%2fICACCS51430.2021.9441819&partnerID=40&md5=e1669d0e0fbe2c9de27e70cf7aab69cb | J38: Conference paper | K38: Scopus/WoS Conference/Book Chapter/Others | L38: CSE
A39: 38 | B39: Velmurugan S.; Shanthi G.; Raja L.; Nirmala S. | C39: Fully Automated Single Window Saline Fluid Flow Control and Automatic Container Changing System | D39: 2021 7th International Conference on Advanced Computing and Communication Systems, ICACCS 2021 | G39: 2021 | H39: 10.1109/ICACCS51430.2021.9441723 | I39: https://www.scopus.com/inward/record.uri?eid=2-s2.0-85108026228&doi=10.1109%2fICACCS51430.2021.9441723&partnerID=40&md5=48855fb5d9366e1217bae67876a69504 | J39: Conference paper | K39: Scopus/WoS Conference/Book Chapter/Others | L39: ECE
A40: 39 | B40: Sreemathy J.; Brindha R.; Selva Nagalakshmi M.; Suvekha N.; Karthick Ragul N.; Praveennandha M. | C40: Overview of ETL Tools and Talend-Data Integration | D40: 2021 7th International Conference on Advanced Computing and Communication Systems, ICACCS 2021 | G40: 2021 | H40: 10.1109/ICACCS51430.2021.9441984 | I40: https://www.scopus.com/inward/record.uri?eid=2-s2.0-85108029699&doi=10.1109%2fICACCS51430.2021.9441984&partnerID=40&md5=09193dde92d718a4bbec55419472a897 | J40: Conference paper | K40: Scopus/WoS Conference/Book Chapter/Others | L40: CSE
A41: 40 | B41: Kiruthiga T.; Shanmugasundaram N. | C41: In-network data aggregation techniques for wireless sensor networks: A survey | D41: Lecture Notes on Data Engineering and Communications Technologies | E41: 66 | G41: 2021 | H41: 10.1007/978-981-16-0965-7_68 | I41: https://www.scopus.com/inward/record.uri?eid=2-s2.0-85114627539&doi=10.1007%2f978-981-16-0965-7_68&partnerID=40&md5=7a958018a7ca729f47fa5a45de1f9573 | J41: Article | K41: Scopus/WoS Journals | L41: ECE
A42: 41 | B42: Haldorai A.; Ramu A. | C42: Intelligent computing application for cloud enhancing healthcare services | D42: Lecture Notes on Data Engineering and Communications Technologies | E42: 66 | G42: 2021 | H42: 10.1007/978-981-16-0965-7_22 | I42: https://www.scopus.com/inward/record.uri?eid=2-s2.0-85114651526&doi=10.1007%2f978-981-16-0965-7_22&partnerID=40&md5=8bfd8a18088df242a0739211c4828cca | J42: Article | K42: SCI | L42: CSE | M42: Others
A43: 42 | B43: Suvitha M.; Subha R. | C43: A Survey on Smart Contract Platforms and Features | D43: 2021 7th International Conference on Advanced Computing and Communication Systems, ICACCS 2021 | G43: 2021 | H43: 10.1109/ICACCS51430.2021.9441970 | I43: https://www.scopus.com/inward/record.uri?eid=2-s2.0-85108030686&doi=10.1109%2fICACCS51430.2021.9441970&partnerID=40&md5=6c288f7ccde2ac75da230ef9b68984d8 | J43: Conference paper | K43: Scopus/WoS Conference/Book Chapter/Others | L43: CSE
A44: 43 | B44: Ahmed L.J.; Anish Fathima B.; Mahaboob M.; Gokulavasan B. | C44: Biomedical Image Processing with Improved SPIHT Algorithm and optimized Curvelet Transform Technique | D44: 2021 7th International Conference on Advanced Computing and Communication Systems, ICACCS 2021 | G44: 2021 | H44: 10.1109/ICACCS51430.2021.9441832 | I44: https://www.scopus.com/inward/record.uri?eid=2-s2.0-85108023591&doi=10.1109%2fICACCS51430.2021.9441832&partnerID=40&md5=dcf6b7105d5e405d4557640b36af305d | J44: Conference paper | K44: Scopus/WoS Conference/Book Chapter/Others | L44: ECE
A45: 44 | B45: Nandalal V.; Anand Kumar V. | C45: Internet of Things (IoT) and Real Time Applications | D45: Studies in Systems, Decision and Control | E45: 358 | G45: 2021 | H45: 10.1007/978-3-030-69744-0_12 | I45: https://www.scopus.com/inward/record.uri?eid=2-s2.0-85111133547&doi=10.1007%2f978-3-030-69744-0_12&partnerID=40&md5=e3135f7b1a450aaabf804bd24503f8cb | J45: Book chapter | K45: Scopus/WoS Conference/Book Chapter/Others | L45: ECE | M45: Dr. Michaelraj Kingston R
A46: 45 | B46: Anandaraj A.; Yeshwanth Ram P.; Sri Ram Kumar K.; Revanth M.; Praveen R. | C46: Book Recommendation System with TensorFlow | D46: 2021 7th International Conference on Advanced Computing and Communication Systems, ICACCS 2021 | G46: 2021 | H46: 10.1109/ICACCS51430.2021.9441927 | I46: https://www.scopus.com/inward/record.uri?eid=2-s2.0-85108022700&doi=10.1109%2fICACCS51430.2021.9441927&partnerID=40&md5=5c1be9627b533d33f6fcb8d51eb3c011 | J46: Conference paper | K46: Scopus/WoS Conference/Book Chapter/Others | L46: CSE
A47: 46 | B47: Saravanan M.; Parthasarathy E. | C47: A review of III-V Tunnel Field Effect Transistors for future ultra low power digital/analog applications | D47: Microelectronics Journal | E47: 114 | G47: 2021 | H47: 10.1016/j.mejo.2021.105102 | I47: https://www.scopus.com/inward/record.uri?eid=2-s2.0-85106550029&doi=10.1016%2fj.mejo.2021.105102&partnerID=40&md5=ce2ed05097db584ce5d543298fb7d198 | J47: Article | K47: SCI | L47: ECE
A48: 47 | B48: Rathinam R.; Govindaraj M. | C48: Photoelectrocatalytic oxidation of textile industry wastewater by RuO2/IrO2/TaO2 coated titanium electrodes | D48: Nature Environment and Pollution Technology | E48: 20 | G48: 2021 | H48: 10.46488/NEPT.2021.V20I03.014 | I48: https://www.scopus.com/inward/record.uri?eid=2-s2.0-85115255868&doi=10.46488%2fNEPT.2021.V20I03.014&partnerID=40&md5=cdb6e13339449beee00ada4257224095 | J48: Article | K48: Scopus/WoS Journals | L48: S&H
A49: 48 | B49: Keerthika J.; Sruthi D.; Swathi D.; Swetha S.; Vinupriya R. | C49: Diagnosis of Breast Cancer using Decision Tree Data Mining Technique | D49: 2021 7th International Conference on Advanced Computing and Communication Systems, ICACCS 2021 | G49: 2021 | H49: 10.1109/ICACCS51430.2021.9442043 | I49: https://www.scopus.com/inward/record.uri?eid=2-s2.0-85108029623&doi=10.1109%2fICACCS51430.2021.9442043&partnerID=40&md5=e4e2f22ea46d1af13087b0f159b4cf54 | J49: Conference paper | K49: Scopus/WoS Conference/Book Chapter/Others | L49: CSE
A50: 49 | B50: Shanthi S.; Rajkumar N. | C50: Lung Cancer Prediction Using Stochastic Diffusion Search (SDS) Based Feature Selection and Machine Learning Methods | D50: Neural Processing Letters | E50: 53 | G50: 2021 | H50: 10.1007/s11063-020-10192-0 | I50: https://www.scopus.com/inward/record.uri?eid=2-s2.0-85078585409&doi=10.1007%2fs11063-020-10192-0&partnerID=40&md5=a54743f3276c58f7380bff40c13dd351 | J50: Article | K50: SCI | L50: CSE
A51: 50 | B51: Niranjani V.; Keerthana R.; Mohana Priya B.; Nekalya K.; Padmanabhan A.K. | C51: System application control based on Hand gesture using Deep learning | D51: 2021 7th International Conference on Advanced Computing and Communication Systems, ICACCS 2021 | G51: 2021 | H51: 10.1109/ICACCS51430.2021.9441732 | I51: https://www.scopus.com/inward/record.uri?eid=2-s2.0-85108029517&doi=10.1109%2fICACCS51430.2021.9441732&partnerID=40&md5=1f2eab92fa48a2af12b253472b9f5208 | J51: Conference paper | K51: Scopus/WoS Conference/Book Chapter/Others | L51: CSE
A52: 51 | B52: Haldorai A.; Ramu A. | C52: Canonical Correlation Analysis Based Hyper Basis Feedforward Neural Network Classification for Urban Sustainability | D52: Neural Processing Letters | E52: 53 | G52: 2021 | H52: 10.1007/s11063-020-10327-3 | I52: https://www.scopus.com/inward/record.uri?eid=2-s2.0-85088828851&doi=10.1007%2fs11063-020-10327-3&partnerID=40&md5=0108a82e70608eeccaf37b38d683fa70 | J52: Article | K52: SCI | L52: CSE
A53: 52 | B53: Krishnapraseeda V.; Geetha Devasena M.S.; Venkatesh V.; Kousalya A. | C53: Predictive Analytics on Diabetes Data using Machine Learning Techniques | D53: 2021 7th International Conference on Advanced Computing and Communication Systems, ICACCS 2021 | G53: 2021 | H53: 10.1109/ICACCS51430.2021.9441972 | I53: https://www.scopus.com/inward/record.uri?eid=2-s2.0-85108027730&doi=10.1109%2fICACCS51430.2021.9441972&partnerID=40&md5=b93abf8c48047d3394cfad2f9da47d9e | J53: Conference paper | K53: Scopus/WoS Conference/Book Chapter/Others | L53: S&H
A54: 53 | B54: Kumar P.S.; Boopathy S.; Dhanasekaran S.; Anand K.R.G. | C54: Optimization of Multi-Band Antenna for Wireless Communication Systems using Genetic Algorithm | D54: 2021 International Conference on Advancements in Electrical, Electronics, Communication, Computing and Automation, ICAECA 2021 | G54: 2021 | H54: 10.1109/ICAECA52838.2021.9675686 | I54: https://www.scopus.com/inward/record.uri?eid=2-s2.0-85125013576&doi=10.1109%2fICAECA52838.2021.9675686&partnerID=40&md5=47c3f2285da16578ba5f931e1480c1d6 | J54: Conference paper | K54: Scopus/WoS Conference/Book Chapter/Others | L54: ECE
A55: 54 | B55: Babu E.; Bhuvaneswari J.; Rajakumar K.; Sathish V.; Thanasekaran P. | C55: Non-conventional photoactive transition metal complexes that mediated sensing and inhibition of amyloidogenic aggregates | D55: Coordination Chemistry Reviews | E55: 428 | G55: 2021 | H55: 10.1016/j.ccr.2020.213612 | I55: https://www.scopus.com/inward/record.uri?eid=2-s2.0-85092356599&doi=10.1016%2fj.ccr.2020.213612&partnerID=40&md5=6b4badf55b97d1ce4c02db38fb8ab016 | J55: Review | K55: Scopus/WoS Journals | L55: S&H
A56: 55 | B56: Prasanna C.; Subha R.; Sreemathy J.; Aravindh Ramanathan P.; Jainaveen M. | C56: Data Validation and Migration-A Theoretical Perspective | D56: 2021 7th International Conference on Advanced Computing and Communication Systems, ICACCS 2021 | G56: 2021 | H56: 10.1109/ICACCS51430.2021.9441784 | I56: https://www.scopus.com/inward/record.uri?eid=2-s2.0-85108029195&doi=10.1109%2fICACCS51430.2021.9441784&partnerID=40&md5=cdb2eac9b1841a470038cdfb6b4ade1e | J56: Conference paper | K56: Scopus/WoS Conference/Book Chapter/Others | L56: CSE
A57: 56 | B57: Jahnavi A.; Dushyanth Reddy B.; Kommineni M.; Haldorai A.; Vasantha B. | C57: Election Tweets Prediction Using Enhanced Cart and Random Forest | D57: Lecture Notes in Networks and Systems | E57: 173 LNNS | G57: 2021 | H57: 10.1007/978-981-33-4305-4_61 | I57: https://www.scopus.com/inward/record.uri?eid=2-s2.0-85107384737&doi=10.1007%2f978-981-33-4305-4_61&partnerID=40&md5=4d6f643bbd76ad69c629da29847c3f67 | J57: Conference paper | K57: Scopus/WoS Conference/Book Chapter/Others | L57: CSE
A58: 57 | B58: Venkatesh S.; Sivapirakasam S.P.; Sakthivel M.; Ganeshkumar S.; Mahendhira Prabhu M.; Naveenkumar M. | C58: Experimental and numerical investigation in the series arrangement square cyclone separator | D58: Powder Technology | E58: 383 | G58: 2021 | H58: 10.1016/j.powtec.2021.01.031 | I58: https://www.scopus.com/inward/record.uri?eid=2-s2.0-85099941636&doi=10.1016%2fj.powtec.2021.01.031&partnerID=40&md5=d181e28d24169f56c6403bcf3f2dc4cf | J58: Article | K58: SCI | L58: MECH
A59: 58 | B59: Ganesh R.S.; Mahaboob M.; An J.; Lakshman C.; Poonthamilan S.; Kumar K.K. | C59: Smart System for Hazardous Gases Detection and Alert System using Internet of Things | D59: Proceedings of the 5th International Conference on Electronics, Communication and Aerospace Technology, ICECA 2021 | G59: 2021 | H59: 10.1109/ICECA52323.2021.9676149 | I59: https://www.scopus.com/inward/record.uri?eid=2-s2.0-85125369379&doi=10.1109%2fICECA52323.2021.9676149&partnerID=40&md5=29746284ae1076c5e844fdadfd47f1c4 | J59: Conference paper | K59: Scopus/WoS Conference/Book Chapter/Others | L59: ECE
A60: 59 | B60: Saravanan M.; Parthasarathy E. | C60: Investigation of RF/Analog performance of Lg=16nm Planner In0.80Ga0.20As TFET | D60: 2021 4th International Conference on Electrical, Computer and Communication Technologies, ICECCT 2021 | G60: 2021 | H60: 10.1109/ICECCT52121.2021.9616769 | I60: https://www.scopus.com/inward/record.uri?eid=2-s2.0-85123436950&doi=10.1109%2fICECCT52121.2021.9616769&partnerID=40&md5=5a844aae36efda00d4fa9cac7d8c2164 | J60: Conference paper | K60: Scopus/WoS Conference/Book Chapter/Others | L60: ECE
A61: 60 | B61: Kumar V.A.; Nandalal V.; Kousalya M.; Madhumitha P.; Kamaleshwari R.; Selvi N.K. | C61: Implementation of Smart Home Assistance and Surveillance | D61: 2021 7th International Conference on Advanced Computing and Communication Systems, ICACCS 2021 | G61: 2021 | H61: 10.1109/ICACCS51430.2021.9442055 | I61: https://www.scopus.com/inward/record.uri?eid=2-s2.0-85108029519&doi=10.1109%2fICACCS51430.2021.9442055&partnerID=40&md5=54233c30a5344b000bf601f5cec4f78f | J61: Conference paper | K61: Scopus/WoS Conference/Book Chapter/Others | L61: ECE | M61: Dr. Rajan Babu W
A62: 61 | B62: KUMAR S.D.; KUMAR S.S. | C62: Effect of heat treatment conditions on ballistic behaviour of various zones of friction stir welded magnesium alloy joints | D62: Transactions of Nonferrous Metals Society of China (English Edition) | E62: 31 | G62: 2021 | H62: 10.1016/S1003-6326(20)65484-X | I62: https://www.scopus.com/inward/record.uri?eid=2-s2.0-85100667516&doi=10.1016%2fS1003-6326%2820%2965484-X&partnerID=40&md5=599b4ebecc9da78fc59a3c7a1b5bca4b | J62: Article | K62: Scopus/WoS Journals | L62: MECH
A63: 62 | B63: Naveen P.; Sivakumar P. | C63: Human Emotions Detection using Kernel Nonlinear Collaborative Discriminant Regression Classifier : HHuman Emotions Detection using KNCDRC | D63: Proceedings - 2nd International Conference on Smart Electronics and Communication, ICOSEC 2021 | G63: 2021 | H63: 10.1109/ICOSEC51865.2021.9591878 | I63: https://www.scopus.com/inward/record.uri?eid=2-s2.0-85123222412&doi=10.1109%2fICOSEC51865.2021.9591878&partnerID=40&md5=2b4e0fb76bf42c6320c7c2c9596a9f35 | J63: Conference paper | K63: Scopus/WoS Conference/Book Chapter/Others | L63: ECE
A64: 63 | B64: Saranya N.; Brindha R.; Aishwariya N.; Kokila R.; Matheswaran P.; Poongavi P. | C64: Data Migration using ETL Workflow | D64: 2021 7th International Conference on Advanced Computing and Communication Systems, ICACCS 2021 | G64: 2021 | H64: 10.1109/ICACCS51430.2021.9441840 | I64: https://www.scopus.com/inward/record.uri?eid=2-s2.0-85108029527&doi=10.1109%2fICACCS51430.2021.9441840&partnerID=40&md5=57205b38fe7674c9fd92e3854ca31a6c | J64: Conference paper | K64: Scopus/WoS Conference/Book Chapter/Others | L64: CSE
A65: 64 | B65: Prasath N.; Sreemathy J. | C65: A New Approach for Cloud Data Migration Technique Using Talend ETL Tool | D65: 2021 7th International Conference on Advanced Computing and Communication Systems, ICACCS 2021 | G65: 2021 | H65: 10.1109/ICACCS51430.2021.9441898 | I65: https://www.scopus.com/inward/record.uri?eid=2-s2.0-85108027466&doi=10.1109%2fICACCS51430.2021.9441898&partnerID=40&md5=259711d65c84f73b0fb2d73f3bad02f8 | J65: Conference paper | K65: Scopus/WoS Conference/Book Chapter/Others | L65: CSE | M65: Dr. Maheswari R
A66: 65 | B66: Dhanasekar S.; Bruntha P.M.; Neebha T.M.; Arunkumar N.; Senathipathi N.; Priya C. | C66: An Area Effective OFDM Transceiver System with Multi-Radix FFT/IFFT Algorithm for Wireless Applications | D66: 2021 7th International Conference on Advanced Computing and Communication Systems, ICACCS 2021 | G66: 2021 | H66: 10.1109/ICACCS51430.2021.9441694 | I66: https://www.scopus.com/inward/record.uri?eid=2-s2.0-85108025320&doi=10.1109%2fICACCS51430.2021.9441694&partnerID=40&md5=1495345ad003accb840d7ea3afed865b | J66: Conference paper | K66: Scopus/WoS Conference/Book Chapter/Others | L66: ECE
A67: 66 | B67: Niranjani V.; Akshaya V.S.; Harish V.; Abhishek S. | C67: Block Chaining in Finance and Accounting | D67: 2021 7th International Conference on Advanced Computing and Communication Systems, ICACCS 2021 | G67: 2021 | H67: 10.1109/ICACCS51430.2021.9442064 | I67: https://www.scopus.com/inward/record.uri?eid=2-s2.0-85108027346&doi=10.1109%2fICACCS51430.2021.9442064&partnerID=40&md5=5dd44d4a899913fe54359da97505f1f7 | J67: Conference paper | K67: Scopus/WoS Conference/Book Chapter/Others | L67: CSE
A68: 67 | B68: Jaichandran R.; Jagan S.; Khasim S.; Dhavamani L.; Mathiazhagan V.; Kumar Bagal D. | C68: Crime Visualization using A Novel GIS-Based Framework | D68: 2021 International Conference on Computational Intelligence and Computing Applications, ICCICA 2021 | G68: 2021 | H68: 10.1109/ICCICA52458.2021.9697127 | I68: https://www.scopus.com/inward/record.uri?eid=2-s2.0-85126435573&doi=10.1109%2fICCICA52458.2021.9697127&partnerID=40&md5=c110f5edc67c4ae7fa2ffc5b5b27e07d | J68: Conference paper | K68: Scopus/WoS Conference/Book Chapter/Others | L68: ECE
A69: 68 | B69: Subudhi P.S.; Thilagaraj M.; Sundar Ganesh C.S.; Diwakaran S.; Naveen P.; Gurusamy S.; Pallikonda Rajasekaran M. | C69: Current-Fed Bidirectional DC-DC Converter Topology for Wireless Charging System Electrical Vehicle Applications | D69: Wireless Communications and Mobile Computing | E69: 2021 | G69: 2021 | H69: 10.1155/2021/1144453 | I69: https://www.scopus.com/inward/record.uri?eid=2-s2.0-85122262299&doi=10.1155%2f2021%2f1144453&partnerID=40&md5=c2f8f633c1b8070d025314149e43f16c | J69: Article | K69: Scopus/WoS Journals | L69: ECE
A70: 69 | B70: Dhanasekaran S.; Ramesh J. | C70: Channel estimation using spatial partitioning with coalitional game theory (SPCGT) in wireless communication | D70: Wireless Networks | E70: 27 | G70: 2021 | H70: 10.1007/s11276-020-02528-4 | I70: https://www.scopus.com/inward/record.uri?eid=2-s2.0-85099866956&doi=10.1007%2fs11276-020-02528-4&partnerID=40&md5=8d072aaa1cdd484fa8f09d676fcf081a | J70: Article | K70: SCI | L70: ECE
A71: 70 | B71: Nandalal V.; Anand Kumar V.; Sujitha A.; Sumitha G.; Sureka A.S. | C71: Intelligent Multi-Utility Shoe for Visually Impaired Persons | D71: Proceedings - 2nd International Conference on Smart Electronics and Communication, ICOSEC 2021 | G71: 2021 | H71: 10.1109/ICOSEC51865.2021.9591728 | I71: https://www.scopus.com/inward/record.uri?eid=2-s2.0-85123163024&doi=10.1109%2fICOSEC51865.2021.9591728&partnerID=40&md5=547821bdc3933e9f8e8e3ee9d75134c7 | J71: Conference paper | K71: Scopus/WoS Conference/Book Chapter/Others | L71: ECE
A72: 71 | B72: Babu W.R.; Kumar R.S.; Kumar R.S. | C72: Rigorous investigation of stator current envelope of an induction motor using hilbert spectrum analysis | D72: Materials Today: Proceedings | E72: 45 | G72: 2021 | H72: 10.1016/j.matpr.2020.11.054 | I72: https://www.scopus.com/inward/record.uri?eid=2-s2.0-85107323837&doi=10.1016%2fj.matpr.2020.11.054&partnerID=40&md5=3d3590c52eff64fea10bfb35d5d20336 | J72: Conference paper | K72: Scopus/WoS Conference/Book Chapter/Others | L72: EEE
A73: 72 | B73: Gokilakrishnan G.; Ganeshkumar S.; Anandakumar H.; Vigneshkumar M. | C73: A Critical Review of Production Distribution Planning Models | D73: 2021 7th International Conference on Advanced Computing and Communication Systems, ICACCS 2021 | G73: 2021 | H73: 10.1109/ICACCS51430.2021.9441879 | I73: https://www.scopus.com/inward/record.uri?eid=2-s2.0-85108023824&doi=10.1109%2fICACCS51430.2021.9441879&partnerID=40&md5=e7fb3ec393439db5c73c4ed73c26b020 | J73: Conference paper | K73: Scopus/WoS Conference/Book Chapter/Others | L73: CSE
A74: 73 | B74: Kumar A.; Abhishek K.; Liu X.; Haldorai A. | C74: An Efficient Privacy-Preserving ID Centric Authentication in IoT Based Cloud Servers for Sustainable Smart Cities | D74: Wireless Personal Communications | E74: 117 | G74: 2021 | H74: 10.1007/s11277-020-07979-8 | I74: https://www.scopus.com/inward/record.uri?eid=2-s2.0-85096390389&doi=10.1007%2fs11277-020-07979-8&partnerID=40&md5=40fc3a3569b8a109bc7c6bde9ebde8bc | J74: Article | K74: SCI | L74: CSE
A75: 74 | B75: Ashokkumar S.R.; Premkumar M.; Selvapandian A.; Jeevanantham V.; Anupallavi S. | C75: Design of an EEG-based transceiver with data decomposition for IoHT applications | D75: Proceedings of the 5th International Conference on I-SMAC (IoT in Social, Mobile, Analytics and Cloud), I-SMAC 2021 | G75: 2021 | H75: 10.1109/I-SMAC52330.2021.9641040 | I75: https://www.scopus.com/inward/record.uri?eid=2-s2.0-85124224153&doi=10.1109%2fI-SMAC52330.2021.9641040&partnerID=40&md5=c04a7c0913b3b41fd2342e59f584d765 | J75: Conference paper | K75: Scopus/WoS Conference/Book Chapter/Others | L75: ECE
A76: 75 | B76: Durai K.N.; Subha R.; Haldorai A. | C76: A Novel Method to Detect and Prevent SQLIA Using Ontology to Cloud Web Security | D76: Wireless Personal Communications | E76: 117 | G76: 2021 | H76: 10.1007/s11277-020-07243-z | I76: https://www.scopus.com/inward/record.uri?eid=2-s2.0-85082934164&doi=10.1007%2fs11277-020-07243-z&partnerID=40&md5=790b6f89bc9f7017191810e293e26e0b | J76: Article | K76: SCI | L76: CSE
A77: 76 | B77: Shanthi S. | C77: A Survey on Non-small Cell Lung Cancer Prediction Using Machine Learning Methods | D77: EAI/Springer Innovations in Communication and Computing | G77: 2021 | H77: 10.1007/978-3-030-47560-4_20 | I77: https://www.scopus.com/inward/record.uri?eid=2-s2.0-85092713251&doi=10.1007%2f978-3-030-47560-4_20&partnerID=40&md5=8b7d83a27b2e3d996d94220194ab6b01 | J77: Conference paper | K77: Scopus/WoS Conference/Book Chapter/Others | L77: CSE
A78: 77 | B78: Nandalal V.; Anand Kumar V. | C78: Design and Analysis of (5, 10) Regular LDPC Encoder Using MRP Technique | D78: Wireless Personal Communications | E78: 118 | G78: 2021 | H78: 10.1007/s11277-021-08075-1 | I78: https://www.scopus.com/inward/record.uri?eid=2-s2.0-85099766775&doi=10.1007%2fs11277-021-08075-1&partnerID=40&md5=431659cf6b3a98f4d29515e71976ef45 | J78: Article | K78: SCI | L78: ECE | M78: Dr. Maheswari R
A79: 78 | B79: Saravanan M.; Ajayan J.; Maheswar R.; Parthasarathy E.; Sumathi K. | C79: Machine learning concept-based IoT platforms for smart cities' implementation and requirements | D79: Machine Learning Paradigm for Internet of Things Applications | G79: 2021 | I79: https://www.scopus.com/inward/record.uri?eid=2-s2.0-85136774649&partnerID=40&md5=26d6437a0c2d3b70e74f18482fd5810f | J79: Book chapter | K79: Scopus/WoS Conference/Book Chapter/Others | L79: ECE | M79: Dr. Raja L
A80: 79 | B80: Pradeep R.; Kanimozhi R. | C80: Hardware Efficient Architectural Design for Physical Layer Security in Wireless Communication | D80: Wireless Personal Communications | E80: 120 | G80: 2021 | H80: 10.1007/s11277-021-08536-7 | I80: https://www.scopus.com/inward/record.uri?eid=2-s2.0-85106736993&doi=10.1007%2fs11277-021-08536-7&partnerID=40&md5=50d362170fce448be669de4645aafa55 | J80: Article | K80: SCI | L80: ECE
A81: 80 | B81: Subha R.; Haldorai A.; Ramu A. | C81: An Optimal Approach to Enhance Context Aware Description Administration Service for Cloud Robots in a Deep Learning Environment | D81: Wireless Personal Communications | E81: 117 | G81: 2021 | H81: 10.1007/s11277-021-08073-3 | I81: https://www.scopus.com/inward/record.uri?eid=2-s2.0-85100089401&doi=10.1007%2fs11277-021-08073-3&partnerID=40&md5=63ec22f504a4c36b89c80786410cb9ad | J81: Article | K81: SCI | L81: CSE
A82: 81 | B82: Haldorai A.; Chen M.-Y.; Onn C.C.; Ramu A. | C82: Guest editorial | D82: International Journal of Pervasive Computing and Communications | E82: 17 | G82: 2021 | H82: 10.1108/IJPCC-04-2021-214 | I82: https://www.scopus.com/inward/record.uri?eid=2-s2.0-85103644186&doi=10.1108%2fIJPCC-04-2021-214&partnerID=40&md5=7b2944da46b56aac2a129e4d98106cbb | J82: Editorial | K82: Scopus/WoS Conference/Book Chapter/Others | L82: CSE
A83: 82 | B83: Haldorai A.; Ramu A.; Mohanram S.; Chen M.-Y. | C83: Preface | D83: EAI/Springer Innovations in Communication and Computing | G83: 2021 | I83: https://www.scopus.com/inward/record.uri?eid=2-s2.0-85092701460&partnerID=40&md5=4f6f3b2c41ea7a9b4ae2896c41525034 | J83: Editorial | K83: Scopus/WoS Conference/Book Chapter/Others | L83: CSE
A84: 83 | B84: Krishnapriya N.; Kumareshan N. | C84: Machine Learning Based Energy Efficient High Performance Routing Protocol for Underwater Communication | D84: Ad-Hoc and Sensor Wireless Networks | E84: 54 | G84: 2022 | I84: https://www.scopus.com/inward/record.uri?eid=2-s2.0-85143486693&partnerID=40&md5=48fa55d3e8d524dc0792671f423b51fa | J84: Article | K84: SCI | L84: ECE
A85: 84 | B85: Saravanan D.; Gokilakrishnan G.; Raajeshkrishna C.R. | C85: Effect of carbon/kevlar reinforcement and hybrid order on mechanical properties of glass/epoxy composites | D85: Advances in Materials and Processing Technologies | E85: 8 | G85: 2022 | H85: 10.1080/2374068X.2021.1965719 | I85: https://www.scopus.com/inward/record.uri?eid=2-s2.0-85112753125&doi=10.1080%2f2374068X.2021.1965719&partnerID=40&md5=7e93cd29fc5a04f6ea9b28a9fbf31022 | J85: Article | K85: SCI | L85: MECH | M85: Dr. Kumareshan N
A86: 85 | B86: Siva Ramkumar M.; Felshiya Rajakumari R.; Kannan N.; Premkumar R.; Mohanasundaram S.; Purushotham S.; Ramya D.; Rajan K. | C86: Semiconductor Materials for Solar PV Technology and Challenges towards Electrical Engineering | D86: Advances in Materials Science and Engineering | E86: 2022 | G86: 2022 | H86: 10.1155/2022/7272489 | I86: https://www.scopus.com/inward/record.uri?eid=2-s2.0-85137129585&doi=10.1155%2f2022%2f7272489&partnerID=40&md5=87f9a7c4d9a89c968c3c1a3d90df7071 | J86: Article | K86: SCI | L86: EEE | M86: Dr. Gokilakrishnan G
A87: 86 | B87: Kandasamy S.K.; Maheswaran S.; Karuppusamy S.A.; Indra J.; Anand R.; Rega P.; Kavitha A.; Immanuvel Arokia James K.; Nehru K.; Kathiresan K. | C87: Design and Fabrication of Flexible Nanoantenna-Based Sensor Using Graphene-Coated Carbon Cloth | D87: Advances in Materials Science and Engineering | E87: 2022 | G87: 2022 | H87: 10.1155/2022/2265904 | I87: https://www.scopus.com/inward/record.uri?eid=2-s2.0-85138617636&doi=10.1155%2f2022%2f2265904&partnerID=40&md5=ac38c8706f2b64a35979e5c00c6cfd06 | J87: Article | K87: Scopus/WoS Journals | L87: ECE | M87: Mr. Premkumar R
A88: 87 | B88: Jagadeesan P.; Sudharsan N.; Subash S.M.; Thirumoorthy P.; Sugumaran B.; Bari J.A.; Vetturayasudharsanan R.; Ambika D.; Sharmiladevi K.; Karuppanan K. | C88: Study on Performance of Infilled Wall in an RC-Framed Structure Using a Reinforcing Band | D88: Advances in Materials Science and Engineering | E88: 2022 | G88: 2022 | H88: 10.1155/2022/8643959 | I88: https://www.scopus.com/inward/record.uri?eid=2-s2.0-85138598372&doi=10.1155%2f2022%2f8643959&partnerID=40&md5=bf75e10ee4623866856b2e0c11879e01 | J88: Article | K88: Scopus/WoS Journals | L88: MECH | M88: Others
A89: 88 | B89: Vinayagar K.; Ganeshan P.; Raja P.N.; Zakir Hussain M.S.; Kumar P.V.; Ramshankar P.; Mohanavel V.; Mathankumar N.; Raja K.; Bezabih T.T. | C89: Optimization of Crashworthiness Parameters of Thin-Walled Conoidal Structures | D89: Advances in Materials Science and Engineering | E89: 2022 | G89: 2022 | H89: 10.1155/2022/4475605 | I89: https://www.scopus.com/inward/record.uri?eid=2-s2.0-85140828470&doi=10.1155%2f2022%2f4475605&partnerID=40&md5=482fd62e3d9c6219c5bda4f8bf8e564c | J89: Article | K89: Scopus/WoS Journals | L89: MECH | M89: Dr. Sugumaran B
A90: 89 | B90: Dhanasekar S.; Ganesan A.T.; Rani T.L.; Vinjamuri V.K.; Nageswara Rao M.; Shankar E.; Dharamvir; Kumar P.S.; Misganaw Golie W. | C90: A Comprehensive Study of Ceramic Matrix Composites for Space Applications | D90: Advances in Materials Science and Engineering | E90: 2022 | G90: 2022 | H90: 10.1155/2022/6160591 | I90: https://www.scopus.com/inward/record.uri?eid=2-s2.0-85138648487&doi=10.1155%2f2022%2f6160591&partnerID=40&md5=e0155e09b90125c0d911540a7d0ade11 | J90: Article | K90: Scopus/WoS Journals | L90: ECE | M90: Dr. Ganeshan P
A91: 90 | B91: Vidhya P.; Sathyanarayanamoorthi V.; Petchiammal M.; Rathinam R. | C91: Analysis of IR and Raman Spectra of Isatin | D91: AIP Conference Proceedings | E91: 2446 | G91: 2022 | H91: 10.1063/5.0109035 | I91: https://www.scopus.com/inward/record.uri?eid=2-s2.0-85144032885&doi=10.1063%2f5.0109035&partnerID=40&md5=2f4d21dc6e38cce42e53ac07bad417b7 | J91: Conference paper | K91: Scopus/WoS Conference/Book Chapter/Others | L91: ECE | M91: Dr. Dhanasekar S
A92: 91 | B92: Krishnaraja A.R.; Kulanthaivel P.; Ramshankar P.; Wilson V.H.; Palanisamy P.; Vivek S.; Sampathkumar V.; Ganeshan P.; Sashikkumar M.C.; Raja K.; Selvaraj S.K.; John Rajan A.; Jose S. | C92: Performance of Polyvinyl Alcohol and Polypropylene Fibers under Simulated Cementitious Composites Pore Solution | D92: Advances in Materials Science and Engineering | E92: 2022 | G92: 2022 | H92: 10.1155/2022/9669803 | I92: https://www.scopus.com/inward/record.uri?eid=2-s2.0-85135033488&doi=10.1155%2f2022%2f9669803&partnerID=40&md5=77743e3b4fe7e2902782e4a9bc9f8f98 | J92: Article | K92: Scopus/WoS Journals | L92: MECH
A93: 92 | B93: Suresh Kumar R.; Senthil Kumar S.; Rajendran C.; Samuel Chelladurai S.J.; Balcha G. | C93: Investigation on Corrosion Behaviour of LM25-SiCp Composite Using Taguchi Method | D93: Advances in Materials Science and Engineering | E93: 2022 | G93: 2022 | H93: 10.1155/2022/4341018 | I93: https://www.scopus.com/inward/record.uri?eid=2-s2.0-85128429858&doi=10.1155%2f2022%2f4341018&partnerID=40&md5=3c7c1e6eafb4a504369167b1037b9315 | J93: Article | K93: Scopus/WoS Journals | L93: MECH | M93: Dr. Ganeshan P
A94: 93 | B94: Ramakrishnan T.; Senthil Kumar S.; Samuel Chelladurai S.J.; Gnanasekaran S.; Geetha N.K.; Arthanari R.; Debtera B. | C94: Effect of Moisture Content on Mechanical Properties of AAM Natural Fiber-Reinforced Isophthalic Polyester Composites | D94: Advances in Materials Science and Engineering | E94: 2022 | G94: 2022 | H94: 10.1155/2022/3533143 | I94: https://www.scopus.com/inward/record.uri?eid=2-s2.0-85124286791&doi=10.1155%2f2022%2f3533143&partnerID=40&md5=ebc2ff28cbbfd808f8184aa6366bf8bb | J94: Article | K94: Scopus/WoS Journals | L94: MECH | M94: Dr. Suresh Kumar R
A95: 94 | B95: Albaqami M.D.; Dwivedi Y.D.; Krishnamoorthy N.; Kumar M.L.; Manjunatha L.H.; Chowdary C.M.; Wabaidur S.M.; Prasad A.R.; Chikhale R.V.; Kumar S.P. | C95: Investigation on Mechanical and Thermal Properties of a Kenaf/Jute Fiber-Reinforced Polyester Hybrid Biocomposite | D95: Advances in Polymer Technology | E95: 2022 | G95: 2022 | H95: 10.1155/2022/7408135 | I95: https://www.scopus.com/inward/record.uri?eid=2-s2.0-85135109884&doi=10.1155%2f2022%2f7408135&partnerID=40&md5=b24593658f5387534738e07340f377b9 | J95: Article | K95: SCI | L95: MECH | M95: Dr. Ganeshkumar S
A96: 95 | B96: Sivakumar S.; Babu W.R.; Ravikumar A.; Karthik S.S.; Kumar L.K.; Senthilkumar R. | C96: Comparison of artificial neural network techniques in prediction of wind speed using combinations of metrological variables | D96: The Future of Wind Energy | G96: 2022 | I96: https://www.scopus.com/inward/record.uri?eid=2-s2.0-85141970552&partnerID=40&md5=df5c4e64c8455043cc2bed6bda7d491e | J96: Book chapter | K96: Scopus/WoS Conference/Book Chapter/Others | L96: EEE | M96: Dr. Krishnamoorthy N
A97: 96 | B97: Nisar K.S.; Jothimani K.; Ravichandran C.; Baleanu D.; Kumar D. | C97: New approach on controllability of Hilfer fractional derivatives with nondense domain | D97: AIMS Mathematics | E97: 7 | G97: 2022 | H97: 10.3934/math.2022561 | I97: https://www.scopus.com/inward/record.uri?eid=2-s2.0-85126930228&doi=10.3934%2fmath.2022561&partnerID=40&md5=2f65f17925b620809bde75b2d45fd66b | J97: Article | K97: SCI | L97: S&H
A98: 97 | B98: Ravichandran C.; Jothimani K.; Nisar K.S.; Mahmoud E.E.; Yahia I.S. | C98: An interpretation on controllability of Hilfer fractional derivative with nondense domain | D98: Alexandria Engineering Journal | E98: 61 | G98: 2022 | H98: 10.1016/j.aej.2022.03.011 | I98: https://www.scopus.com/inward/record.uri?eid=2-s2.0-85127167285&doi=10.1016%2fj.aej.2022.03.011&partnerID=40&md5=2436450fc200e2ddff2fca63424c6eaf | J98: Article | K98: SCI | L98: S&H | M98: Others
A99: 98 | B99: Babu R.G.; Lavanya D.; Raja L.; Velmurugan S.; Nalini N.; Krishnan R. | C99: IoT for precision in agricultural system | D99: AIP Conference Proceedings | E99: 2405 | G99: 2022 | H99: 10.1063/5.0072865 | I99: https://www.scopus.com/inward/record.uri?eid=2-s2.0-85128089116&doi=10.1063%2f5.0072865&partnerID=40&md5=b09680e58470bc85875dbc67d70c92f0 | J99: Conference paper | K99: Scopus/WoS Conference/Book Chapter/Others | L99: ECE | M99: Others
A100: 99 | B100: Haldorai A.; Sivaraj J.; Nagabushanam M.; Kingston Roberts M. | C100: Cognitive Wireless Networks Based Spectrum Sensing Strategies: A Comparative Analysis | D100: Applied Computational Intelligence and Soft Computing | E100: 2022 | G100: 2022 | H100: 10.1155/2022/6988847 | I100: https://www.scopus.com/inward/record.uri?eid=2-s2.0-85141657839&doi=10.1155%2f2022%2f6988847&partnerID=40&md5=5bdc105152a950436893bd0c803093d7 | J100: Article | K100: SCI | L100: CSE
...

Sheet Name of the Faculty 2023
A1: S.No | B1: Name of the Faculty | C1: Deptartment | D1: Dept | E1: SCI - 2023 | F1: Scopus/WoS Journals - 2023 | G1: Scopus/WoS Conference/Book Chapter/Others - 2023 | H1: Student Publication | I1: Book | J1: Total | O1: Combined Department
A2: 1 | B2: Dr. Dinesh Kumar P | C2: AIDS | D2: AIDS | E2: =COUNTIFS('2024 -2025-2026'!$M:$M,B2,'2024 -2025-2026'!$K:$K,"SCI",'2024 -2025-2026'!$G:$G,"2023") -> 0 | F2: =COUNTIFS('2024 -2025-2026'!$M:$M,B2,'2024 -2025-2026'!$K:$K,"Scopus/WoS Journals",'2024 -2025-2026'!$G:$G,"2023") -> 0 | G2: =COUNTIFS('2024 -2025-2026'!$M:$M,B2,'2024 -2025-2026'!$K:$K,"Scopus/WoS Conference/Book Chapter/Others", '2024 -2025-2026'!$G:$G,"2023") -> 0 | H2: =COUNTIFS('2024 -2025-2026'!$M:$M,B2,'2024 -2025-2026'!$K:$K,"Student Publication",'2024 -2025-2026'!$G:$G,"2023") -> 0 | I2: =COUNTIFS('2024 -2025-2026'!$M:$M,B2,'2024 -2025-2026'!$K:$K,"Book",'2024 -2025-2026'!$G:$G,"2023") -> 0 | J2: =SUM(E2:H2) -> 0 | L2: SCI | M2: =SUM(E2:E1248) -> 189 | O2: AIDS
A3: 2 | B3: Dr. Geetha M P | C3: AIDS | D3: AIDS | E3: =COUNTIFS('2024 -2025-2026'!$M:$M,B3,'2024 -2025-2026'!$K:$K,"SCI",'2024 -2025-2026'!$G:$G,"2023") -> 0 | F3: =COUNTIFS('2024 -2025-2026'!$M:$M,B3,'2024 -2025-2026'!$K:$K,"Scopus/WoS Journals",'2024 -2025-2026'!$G:$G,"2023") -> 0 | G3: =COUNTIFS('2024 -2025-2026'!$M:$M,B3,'2024 -2025-2026'!$K:$K,"Scopus/WoS Conference/Book Chapter/Others", '2024 -2025-2026'!$G:$G,"2023") -> 0 | H3: =COUNTIFS('2024 -2025-2026'!$M:$M,B3,'2024 -2025-2026'!$K:$K,"Student Publication",'2024 -2025-2026'!$G:$G,"2023") -> 0 | I3: =COUNTIFS('2024 -2025-2026'!$M:$M,B3,'2024 -2025-2026'!$K:$K,"Book",'2024 -2025-2026'!$G:$G,"2023") -> 0 | J3: =SUM(E3:H3) -> 0 | L3: Scopus/WoS Journals | M3: =SUM(F:F) -> 10 | O3: AIML
A4: 3 | B4: Dr. Kanimozhi T | C4: AIDS | D4: AIDS | E4: =COUNTIFS('2024 -2025-2026'!$M:$M,B4,'2024 -2025-2026'!$K:$K,"SCI",'2024 -2025-2026'!$G:$G,"2023") -> 0 | F4: =COUNTIFS('2024 -2025-2026'!$M:$M,B4,'2024 -2025-2026'!$K:$K,"Scopus/WoS Journals",'2024 -2025-2026'!$G:$G,"2023") -> 0 | G4: =COUNTIFS('2024 -2025-2026'!$M:$M,B4,'2024 -2025-2026'!$K:$K,"Scopus/WoS Conference/Book Chapter/Others", '2024 -2025-2026'!$G:$G,"2023") -> 0 | H4: =COUNTIFS('2024 -2025-2026'!$M:$M,B4,'2024 -2025-2026'!$K:$K,"Student Publication",'2024 -2025-2026'!$G:$G,"2023") -> 0 | I4: =COUNTIFS('2024 -2025-2026'!$M:$M,B4,'2024 -2025-2026'!$K:$K,"Book",'2024 -2025-2026'!$G:$G,"2023") -> 0 | J4: =SUM(E4:H4) -> 0 | L4: Scopus/WoS Conference/Book Chapter/Others | M4: =SUM(G:G) -> 296 | O4: CCE
A5: 4 | B5: Dr. Lakshmi M | C5: AIDS | D5: AIDS | E5: =COUNTIFS('2024 -2025-2026'!$M:$M,B5,'2024 -2025-2026'!$K:$K,"SCI",'2024 -2025-2026'!$G:$G,"2023") -> 0 | F5: =COUNTIFS('2024 -2025-2026'!$M:$M,B5,'2024 -2025-2026'!$K:$K,"Scopus/WoS Journals",'2024 -2025-2026'!$G:$G,"2023") -> 0 | G5: =COUNTIFS('2024 -2025-2026'!$M:$M,B5,'2024 -2025-2026'!$K:$K,"Scopus/WoS Conference/Book Chapter/Others", '2024 -2025-2026'!$G:$G,"2023") -> 0 | H5: =COUNTIFS('2024 -2025-2026'!$M:$M,B5,'2024 -2025-2026'!$K:$K,"Student Publication",'2024 -2025-2026'!$G:$G,"2023") -> 0 | I5: =COUNTIFS('2024 -2025-2026'!$M:$M,B5,'2024 -2025-2026'!$K:$K,"Book",'2024 -2025-2026'!$G:$G,"2023") -> 0 | J5: =SUM(E5:H5) -> 0 | L5: Student Publication | M5: =SUM(H:H) -> 122 | O5: CSBS
A6: 5 | B6: Dr. Mohammed Mustafa M | C6: AIDS | D6: AIDS | E6: =COUNTIFS('2024 -2025-2026'!$M:$M,B6,'2024 -2025-2026'!$K:$K,"SCI",'2024 -2025-2026'!$G:$G,"2023") -> 0 | F6: =COUNTIFS('2024 -2025-2026'!$M:$M,B6,'2024 -2025-2026'!$K:$K,"Scopus/WoS Journals",'2024 -2025-2026'!$G:$G,"2023") -> 0 | G6: =COUNTIFS('2024 -2025-2026'!$M:$M,B6,'2024 -2025-2026'!$K:$K,"Scopus/WoS Conference/Book Chapter/Others", '2024 -2025-2026'!$G:$G,"2023") -> 0 | H6: =COUNTIFS('2024 -2025-2026'!$M:$M,B6,'2024 -2025-2026'!$K:$K,"Student Publication",'2024 -2025-2026'!$G:$G,"2023") -> 0 | I6: =COUNTIFS('2024 -2025-2026'!$M:$M,B6,'2024 -2025-2026'!$K:$K,"Book",'2024 -2025-2026'!$G:$G,"2023") -> 0 | J6: =SUM(E6:H6) -> 0 | L6: Book | M6: =SUM(I:I) -> 4 | O6: CSE
A7: 6 | B7: Dr. Nivaashini M | C7: AIDS | D7: AIDS | E7: =COUNTIFS('2024 -2025-2026'!$M:$M,B7,'2024 -2025-2026'!$K:$K,"SCI",'2024 -2025-2026'!$G:$G,"2023") -> 0 | F7: =COUNTIFS('2024 -2025-2026'!$M:$M,B7,'2024 -2025-2026'!$K:$K,"Scopus/WoS Journals",'2024 -2025-2026'!$G:$G,"2023") -> 0 | G7: =COUNTIFS('2024 -2025-2026'!$M:$M,B7,'2024 -2025-2026'!$K:$K,"Scopus/WoS Conference/Book Chapter/Others", '2024 -2025-2026'!$G:$G,"2023") -> 0 | H7: =COUNTIFS('2024 -2025-2026'!$M:$M,B7,'2024 -2025-2026'!$K:$K,"Student Publication",'2024 -2025-2026'!$G:$G,"2023") -> 0 | I7: =COUNTIFS('2024 -2025-2026'!$M:$M,B7,'2024 -2025-2026'!$K:$K,"Book",'2024 -2025-2026'!$G:$G,"2023") -> 0 | J7: =SUM(E7:H7) -> 0 | L7: Total | M7: =SUM(M2:M6) -> 621 | O7: ECE
A8: 7 | B8: Dr. Sathish Kumar G | C8: AIDS | D8: AIDS | E8: =COUNTIFS('2024 -2025-2026'!$M:$M,B8,'2024 -2025-2026'!$K:$K,"SCI",'2024 -2025-2026'!$G:$G,"2023") -> 1 | F8: =COUNTIFS('2024 -2025-2026'!$M:$M,B8,'2024 -2025-2026'!$K:$K,"Scopus/WoS Journals",'2024 -2025-2026'!$G:$G,"2023") -> 0 | G8: =COUNTIFS('2024 -2025-2026'!$M:$M,B8,'2024 -2025-2026'!$K:$K,"Scopus/WoS Conference/Book Chapter/Others", '2024 -2025-2026'!$G:$G,"2023") -> 1 | H8: =COUNTIFS('2024 -2025-2026'!$M:$M,B8,'2024 -2025-2026'!$K:$K,"Student Publication",'2024 -2025-2026'!$G:$G,"2023") -> 0 | I8: =COUNTIFS('2024 -2025-2026'!$M:$M,B8,'2024 -2025-2026'!$K:$K,"Book",'2024 -2025-2026'!$G:$G,"2023") -> 0 | J8: =SUM(E8:H8) -> 2 | O8: MECH
A9: 8 | B9: Dr. Thenmozhi M | C9: AIDS | D9: AIDS | E9: =COUNTIFS('2024 -2025-2026'!$M:$M,B9,'2024 -2025-2026'!$K:$K,"SCI",'2024 -2025-2026'!$G:$G,"2023") -> 0 | F9: =COUNTIFS('2024 -2025-2026'!$M:$M,B9,'2024 -2025-2026'!$K:$K,"Scopus/WoS Journals",'2024 -2025-2026'!$G:$G,"2023") -> 0 | G9: =COUNTIFS('2024 -2025-2026'!$M:$M,B9,'2024 -2025-2026'!$K:$K,"Scopus/WoS Conference/Book Chapter/Others", '2024 -2025-2026'!$G:$G,"2023") -> 1 | H9: =COUNTIFS('2024 -2025-2026'!$M:$M,B9,'2024 -2025-2026'!$K:$K,"Student Publication",'2024 -2025-2026'!$G:$G,"2023") -> 1 | I9: =COUNTIFS('2024 -2025-2026'!$M:$M,B9,'2024 -2025-2026'!$K:$K,"Book",'2024 -2025-2026'!$G:$G,"2023") -> 0 | J9: =SUM(E9:H9) -> 2 | O9: EEE
A10: 9 | B10: Dr. Vimal S | C10: AIDS | D10: AIDS | E10: =COUNTIFS('2024 -2025-2026'!$M:$M,B10,'2024 -2025-2026'!$K:$K,"SCI",'2024 -2025-2026'!$G:$G,"2023") -> 0 | F10: =COUNTIFS('2024 -2025-2026'!$M:$M,B10,'2024 -2025-2026'!$K:$K,"Scopus/WoS Journals",'2024 -2025-2026'!$G:$G,"2023") -> 0 | G10: =COUNTIFS('2024 -2025-2026'!$M:$M,B10,'2024 -2025-2026'!$K:$K,"Scopus/WoS Conference/Book Chapter/Others", '2024 -2025-2026'!$G:$G,"2023") -> 0 | H10: =COUNTIFS('2024 -2025-2026'!$M:$M,B10,'2024 -2025-2026'!$K:$K,"Student Publication",'2024 -2025-2026'!$G:$G,"2023") -> 0 | I10: =COUNTIFS('2024 -2025-2026'!$M:$M,B10,'2024 -2025-2026'!$K:$K,"Book",'2024 -2025-2026'!$G:$G,"2023") -> 0 | J10: =SUM(E10:H10) -> 0 | O10: IT
A11: 10 | B11: Mr. Sridharan S | C11: AIDS | D11: AIDS | E11: =COUNTIFS('2024 -2025-2026'!$M:$M,B11,'2024 -2025-2026'!$K:$K,"SCI",'2024 -2025-2026'!$G:$G,"2023") -> 0 | F11: =COUNTIFS('2024 -2025-2026'!$M:$M,B11,'2024 -2025-2026'!$K:$K,"Scopus/WoS Journals",'2024 -2025-2026'!$G:$G,"2023") -> 0 | G11: =COUNTIFS('2024 -2025-2026'!$M:$M,B11,'2024 -2025-2026'!$K:$K,"Scopus/WoS Conference/Book Chapter/Others", '2024 -2025-2026'!$G:$G,"2023") -> 0 | H11: =COUNTIFS('2024 -2025-2026'!$M:$M,B11,'2024 -2025-2026'!$K:$K,"Student Publication",'2024 -2025-2026'!$G:$G,"2023") -> 0 | I11: =COUNTIFS('2024 -2025-2026'!$M:$M,B11,'2024 -2025-2026'!$K:$K,"Book",'2024 -2025-2026'!$G:$G,"2023") -> 0 | J11: =SUM(E11:H11) -> 0 | O11: S&H (Eng)
A12: 11 | B12: Ms. Anitha E | C12: AIDS | D12: AIDS | E12: =COUNTIFS('2024 -2025-2026'!$M:$M,B12,'2024 -2025-2026'!$K:$K,"SCI",'2024 -2025-2026'!$G:$G,"2023") -> 0 | F12: =COUNTIFS('2024 -2025-2026'!$M:$M,B12,'2024 -2025-2026'!$K:$K,"Scopus/WoS Journals",'2024 -2025-2026'!$G:$G,"2023") -> 1 | G12: =COUNTIFS('2024 -2025-2026'!$M:$M,B12,'2024 -2025-2026'!$K:$K,"Scopus/WoS Conference/Book Chapter/Others", '2024 -2025-2026'!$G:$G,"2023") -> 0 | H12: =COUNTIFS('2024 -2025-2026'!$M:$M,B12,'2024 -2025-2026'!$K:$K,"Student Publication",'2024 -2025-2026'!$G:$G,"2023") -> 2 | I12: =COUNTIFS('2024 -2025-2026'!$M:$M,B12,'2024 -2025-2026'!$K:$K,"Book",'2024 -2025-2026'!$G:$G,"2023") -> 0 | J12: =SUM(E12:H12) -> 3 | O12: CSE, IT, CCE
A13: 12 | B13: Ms. Divyaprabha R | C13: AIDS | D13: AIDS | E13: =COUNTIFS('2024 -2025-2026'!$M:$M,B13,'2024 -2025-2026'!$K:$K,"SCI",'2024 -2025-2026'!$G:$G,"2023") -> 0 | F13: =COUNTIFS('2024 -2025-2026'!$M:$M,B13,'2024 -2025-2026'!$K:$K,"Scopus/WoS Journals",'2024 -2025-2026'!$G:$G,"2023") -> 0 | G13: =COUNTIFS('2024 -2025-2026'!$M:$M,B13,'2024 -2025-2026'!$K:$K,"Scopus/WoS Conference/Book Chapter/Others", '2024 -2025-2026'!$G:$G,"2023") -> 0 | H13: =COUNTIFS('2024 -2025-2026'!$M:$M,B13,'2024 -2025-2026'!$K:$K,"Student Publication",'2024 -2025-2026'!$G:$G,"2023") -> 0 | I13: =COUNTIFS('2024 -2025-2026'!$M:$M,B13,'2024 -2025-2026'!$K:$K,"Book",'2024 -2025-2026'!$G:$G,"2023") -> 0 | J13: =SUM(E13:H13) -> 0 | O13: MECH, S&H (Eng)
A14: 13 | B14: Ms. Esther Pushpam | C14: AIDS | D14: AIDS | E14: =COUNTIFS('2024 -2025-2026'!$M:$M,B14,'2024 -2025-2026'!$K:$K,"SCI",'2024 -2025-2026'!$G:$G,"2023") -> 0 | F14: =COUNTIFS('2024 -2025-2026'!$M:$M,B14,'2024 -2025-2026'!$K:$K,"Scopus/WoS Journals",'2024 -2025-2026'!$G:$G,"2023") -> 0 | G14: =COUNTIFS('2024 -2025-2026'!$M:$M,B14,'2024 -2025-2026'!$K:$K,"Scopus/WoS Conference/Book Chapter/Others", '2024 -2025-2026'!$G:$G,"2023") -> 0 | H14: =COUNTIFS('2024 -2025-2026'!$M:$M,B14,'2024 -2025-2026'!$K:$K,"Student Publication",'2024 -2025-2026'!$G:$G,"2023") -> 0 | I14: =COUNTIFS('2024 -2025-2026'!$M:$M,B14,'2024 -2025-2026'!$K:$K,"Book",'2024 -2025-2026'!$G:$G,"2023") -> 0 | J14: =SUM(E14:H14) -> 0 | O14: S&H (Che)
A15: 14 | B15: Ms. Geetha Rajakumari R | C15: AIDS | D15: AIDS | E15: =COUNTIFS('2024 -2025-2026'!$M:$M,B15,'2024 -2025-2026'!$K:$K,"SCI",'2024 -2025-2026'!$G:$G,"2023") -> 0 | F15: =COUNTIFS('2024 -2025-2026'!$M:$M,B15,'2024 -2025-2026'!$K:$K,"Scopus/WoS Journals",'2024 -2025-2026'!$G:$G,"2023") -> 0 | G15: =COUNTIFS('2024 -2025-2026'!$M:$M,B15,'2024 -2025-2026'!$K:$K,"Scopus/WoS Conference/Book Chapter/Others", '2024 -2025-2026'!$G:$G,"2023") -> 0 | H15: =COUNTIFS('2024 -2025-2026'!$M:$M,B15,'2024 -2025-2026'!$K:$K,"Student Publication",'2024 -2025-2026'!$G:$G,"2023") -> 0 | I15: =COUNTIFS('2024 -2025-2026'!$M:$M,B15,'2024 -2025-2026'!$K:$K,"Book",'2024 -2025-2026'!$G:$G,"2023") -> 0 | J15: =SUM(E15:H15) -> 0 | O15: S&H (Maths)
A16: 15 | B16: Ms. Gowri S | C16: AIDS | D16: AIDS | E16: =COUNTIFS('2024 -2025-2026'!$M:$M,B16,'2024 -2025-2026'!$K:$K,"SCI",'2024 -2025-2026'!$G:$G,"2023") -> 0 | F16: =COUNTIFS('2024 -2025-2026'!$M:$M,B16,'2024 -2025-2026'!$K:$K,"Scopus/WoS Journals",'2024 -2025-2026'!$G:$G,"2023") -> 0 | G16: =COUNTIFS('2024 -2025-2026'!$M:$M,B16,'2024 -2025-2026'!$K:$K,"Scopus/WoS Conference/Book Chapter/Others", '2024 -2025-2026'!$G:$G,"2023") -> 0 | H16: =COUNTIFS('2024 -2025-2026'!$M:$M,B16,'2024 -2025-2026'!$K:$K,"Student Publication",'2024 -2025-2026'!$G:$G,"2023") -> 0 | I16: =COUNTIFS('2024 -2025-2026'!$M:$M,B16,'2024 -2025-2026'!$K:$K,"Book",'2024 -2025-2026'!$G:$G,"2023") -> 0 | J16: =SUM(E16:H16) -> 0 | O16: S&H (Phy)
A17: 16 | B17: Ms. Parvathy K | C17: AIDS | D17: AIDS | E17: =COUNTIFS('2024 -2025-2026'!$M:$M,B17,'2024 -2025-2026'!$K:$K,"SCI",'2024 -2025-2026'!$G:$G,"2023") -> 0 | F17: =COUNTIFS('2024 -2025-2026'!$M:$M,B17,'2024 -2025-2026'!$K:$K,"Scopus/WoS Journals",'2024 -2025-2026'!$G:$G,"2023") -> 0 | G17: =COUNTIFS('2024 -2025-2026'!$M:$M,B17,'2024 -2025-2026'!$K:$K,"Scopus/WoS Conference/Book Chapter/Others", '2024 -2025-2026'!$G:$G,"2023") -> 2 | H17: =COUNTIFS('2024 -2025-2026'!$M:$M,B17,'2024 -2025-2026'!$K:$K,"Student Publication",'2024 -2025-2026'!$G:$G,"2023") -> 0 | I17: =COUNTIFS('2024 -2025-2026'!$M:$M,B17,'2024 -2025-2026'!$K:$K,"Book",'2024 -2025-2026'!$G:$G,"2023") -> 0 | J17: =SUM(E17:H17) -> 2 | O17: Student Publication AIDS
A18: 17 | B18: Ms. Rajalakshmi S | C18: AIDS | D18: AIDS | E18: =COUNTIFS('2024 -2025-2026'!$M:$M,B18,'2024 -2025-2026'!$K:$K,"SCI",'2024 -2025-2026'!$G:$G,"2023") -> 0 | F18: =COUNTIFS('2024 -2025-2026'!$M:$M,B18,'2024 -2025-2026'!$K:$K,"Scopus/WoS Journals",'2024 -2025-2026'!$G:$G,"2023") -> 0 | G18: =COUNTIFS('2024 -2025-2026'!$M:$M,B18,'2024 -2025-2026'!$K:$K,"Scopus/WoS Conference/Book Chapter/Others", '2024 -2025-2026'!$G:$G,"2023") -> 0 | H18: =COUNTIFS('2024 -2025-2026'!$M:$M,B18,'2024 -2025-2026'!$K:$K,"Student Publication",'2024 -2025-2026'!$G:$G,"2023") -> 0 | I18: =COUNTIFS('2024 -2025-2026'!$M:$M,B18,'2024 -2025-2026'!$K:$K,"Book",'2024 -2025-2026'!$G:$G,"2023") -> 0 | J18: =SUM(E18:H18) -> 0 | O18: Student Publication CCE
A19: 18 | B19: Ms. Sangavi V | C19: AIDS | D19: AIDS | E19: =COUNTIFS('2024 -2025-2026'!$M:$M,B19,'2024 -2025-2026'!$K:$K,"SCI",'2024 -2025-2026'!$G:$G,"2023") -> 0 | F19: =COUNTIFS('2024 -2025-2026'!$M:$M,B19,'2024 -2025-2026'!$K:$K,"Scopus/WoS Journals",'2024 -2025-2026'!$G:$G,"2023") -> 0 | G19: =COUNTIFS('2024 -2025-2026'!$M:$M,B19,'2024 -2025-2026'!$K:$K,"Scopus/WoS Conference/Book Chapter/Others", '2024 -2025-2026'!$G:$G,"2023") -> 0 | H19: =COUNTIFS('2024 -2025-2026'!$M:$M,B19,'2024 -2025-2026'!$K:$K,"Student Publication",'2024 -2025-2026'!$G:$G,"2023") -> 0 | I19: =COUNTIFS('2024 -2025-2026'!$M:$M,B19,'2024 -2025-2026'!$K:$K,"Book",'2024 -2025-2026'!$G:$G,"2023") -> 0 | J19: =SUM(E19:H19) -> 0 | O19: Student Publication CSBS
... A26: 108 | B26: Dr. Raja L | C26: AIDS | D26: AIDS | E26: =COUNTIFS('2024 -2025-2026'!$M:$M,B26,'2024 -2025-2026'!$K:$K,"SCI",'2024 -2025-2026'!$G:$G,"2023") -> 1 | F26: =COUNTIFS('2024 -2025-2026'!$M:$M,B26,'2024 -2025-2026'!$K:$K,"Scopus/WoS Journals",'2024 -2025-2026'!$G:$G,"2023") -> 0 | G26: =COUNTIFS('2024 -2025-2026'!$M:$M,B26,'2024 -2025-2026'!$K:$K,"Scopus/WoS Conference/Book Chapter/Others", '2024 -2025-2026'!$G:$G,"2023") -> 2 | H26: =COUNTIFS('2024 -2025-2026'!$M:$M,B26,'2024 -2025-2026'!$K:$K,"Student Publication",'2024 -2025-2026'!$G:$G,"2023") -> 3 | I26: =COUNTIFS('2024 -2025-2026'!$M:$M,B26,'2024 -2025-2026'!$K:$K,"Book",'2024 -2025-2026'!$G:$G,"2023") -> 0 | J26: =SUM(E26:H26) -> 6 | O26: Student Publication AIML
A27: 141 | B27: Dr. Suganyadevi K | C27: AIDS | D27: AIDS | E27: =COUNTIFS('2024 -2025-2026'!$M:$M,B27,'2024 -2025-2026'!$K:$K,"SCI",'2024 -2025-2026'!$G:$G,"2023") -> 1 | F27: =COUNTIFS('2024 -2025-2026'!$M:$M,B27,'2024 -2025-2026'!$K:$K,"Scopus/WoS Journals",'2024 -2025-2026'!$G:$G,"2023") -> 0 | G27: =COUNTIFS('2024 -2025-2026'!$M:$M,B27,'2024 -2025-2026'!$K:$K,"Scopus/WoS Conference/Book Chapter/Others", '2024 -2025-2026'!$G:$G,"2023") -> 1 | H27: =COUNTIFS('2024 -2025-2026'!$M:$M,B27,'2024 -2025-2026'!$K:$K,"Student Publication",'2024 -2025-2026'!$G:$G,"2023") -> 2 | I27: =COUNTIFS('2024 -2025-2026'!$M:$M,B27,'2024 -2025-2026'!$K:$K,"Book",'2024 -2025-2026'!$G:$G,"2023") -> 0 | J27: =SUM(E27:H27) -> 4
A28: 250 | B28: Others AIDS | C28: AIDS | D28: AIDS | E28: =COUNTIFS('2024 -2025-2026'!$M:$M,B28,'2024 -2025-2026'!$K:$K,"SCI",'2024 -2025-2026'!$G:$G,"2023") -> 0 | F28: =COUNTIFS('2024 -2025-2026'!$M:$M,B28,'2024 -2025-2026'!$K:$K,"Scopus/WoS Journals",'2024 -2025-2026'!$G:$G,"2023") -> 0 | G28: =COUNTIFS('2024 -2025-2026'!$M:$M,B28,'2024 -2025-2026'!$K:$K,"Scopus/WoS Conference/Book Chapter/Others", '2024 -2025-2026'!$G:$G,"2023") -> 0 | H28: =COUNTIFS('2024 -2025-2026'!$M:$M,B28,'2024 -2025-2026'!$K:$K,"Student Publication",'2024 -2025-2026'!$G:$G,"2023") -> 0 | I28: =COUNTIFS('2024 -2025-2026'!$M:$M,B28,'2024 -2025-2026'!$K:$K,"Book",'2024 -2025-2026'!$G:$G,"2023") -> 0 | J28: =SUM(E28:H28) -> 0
A29: 266 | B29: Mr. Divakar R | C29: AIDS | D29: AIDS | E29: =COUNTIFS('2024 -2025-2026'!$M:$M,B29,'2024 -2025-2026'!$K:$K,"SCI",'2024 -2025-2026'!$G:$G,"2023") -> 0 | F29: =COUNTIFS('2024 -2025-2026'!$M:$M,B29,'2024 -2025-2026'!$K:$K,"Scopus/WoS Journals",'2024 -2025-2026'!$G:$G,"2023") -> 0 | G29: =COUNTIFS('2024 -2025-2026'!$M:$M,B29,'2024 -2025-2026'!$K:$K,"Scopus/WoS Conference/Book Chapter/Others", '2024 -2025-2026'!$G:$G,"2023") -> 0 | H29: =COUNTIFS('2024 -2025-2026'!$M:$M,B29,'2024 -2025-2026'!$K:$K,"Student Publication",'2024 -2025-2026'!$G:$G,"2023") -> 0 | I29: =COUNTIFS('2024 -2025-2026'!$M:$M,B29,'2024 -2025-2026'!$K:$K,"Book",'2024 -2025-2026'!$G:$G,"2023") -> 0 | J29: =SUM(E29:H29) -> 0
A30: 267 | B30: Dr. Rajesh Kumar C | C30: AIDS | D30: AIDS | E30: =COUNTIFS('2024 -2025-2026'!$M:$M,B30,'2024 -2025-2026'!$K:$K,"SCI",'2024 -2025-2026'!$G:$G,"2023") -> 0 | F30: =COUNTIFS('2024 -2025-2026'!$M:$M,B30,'2024 -2025-2026'!$K:$K,"Scopus/WoS Journals",'2024 -2025-2026'!$G:$G,"2023") -> 0 | G30: =COUNTIFS('2024 -2025-2026'!$M:$M,B30,'2024 -2025-2026'!$K:$K,"Scopus/WoS Conference/Book Chapter/Others", '2024 -2025-2026'!$G:$G,"2023") -> 0 | H30: =COUNTIFS('2024 -2025-2026'!$M:$M,B30,'2024 -2025-2026'!$K:$K,"Student Publication",'2024 -2025-2026'!$G:$G,"2023") -> 0 | I30: =COUNTIFS('2024 -2025-2026'!$M:$M,B30,'2024 -2025-2026'!$K:$K,"Book",'2024 -2025-2026'!$G:$G,"2023") -> 0 | J30: =SUM(E30:H30) -> 0
A31: 268 | B31: Mr. Sam Peter S | C31: AIDS | D31: AIDS | E31: =COUNTIFS('2024 -2025-2026'!$M:$M,B31,'2024 -2025-2026'!$K:$K,"SCI",'2024 -2025-2026'!$G:$G,"2023") -> 0 | F31: =COUNTIFS('2024 -2025-2026'!$M:$M,B31,'2024 -2025-2026'!$K:$K,"Scopus/WoS Journals",'2024 -2025-2026'!$G:$G,"2023") -> 0 | G31: =COUNTIFS('2024 -2025-2026'!$M:$M,B31,'2024 -2025-2026'!$K:$K,"Scopus/WoS Conference/Book Chapter/Others", '2024 -2025-2026'!$G:$G,"2023") -> 0 | H31: =COUNTIFS('2024 -2025-2026'!$M:$M,B31,'2024 -2025-2026'!$K:$K,"Student Publication",'2024 -2025-2026'!$G:$G,"2023") -> 0 | I31: =COUNTIFS('2024 -2025-2026'!$M:$M,B31,'2024 -2025-2026'!$K:$K,"Book",'2024 -2025-2026'!$G:$G,"2023") -> 0 | J31: =SUM(E31:H31) -> 0
A32: 269 | B32: Ms. Chitra P | C32: AIDS | D32: AIDS | E32: =COUNTIFS('2024 -2025-2026'!$M:$M,B32,'2024 -2025-2026'!$K:$K,"SCI",'2024 -2025-2026'!$G:$G,"2023") -> 0 | F32: =COUNTIFS('2024 -2025-2026'!$M:$M,B32,'2024 -2025-2026'!$K:$K,"Scopus/WoS Journals",'2024 -2025-2026'!$G:$G,"2023") -> 0 | G32: =COUNTIFS('2024 -2025-2026'!$M:$M,B32,'2024 -2025-2026'!$K:$K,"Scopus/WoS Conference/Book Chapter/Others", '2024 -2025-2026'!$G:$G,"2023") -> 0 | H32: =COUNTIFS('2024 -2025-2026'!$M:$M,B32,'2024 -2025-2026'!$K:$K,"Student Publication",'2024 -2025-2026'!$G:$G,"2023") -> 0 | I32: =COUNTIFS('2024 -2025-2026'!$M:$M,B32,'2024 -2025-2026'!$K:$K,"Book",'2024 -2025-2026'!$G:$G,"2023") -> 0 | J32: =SUM(E32:H32) -> 0
A33: 270 | B33: Ms. Durga Devi G | C33: AIDS | D33: AIDS | E33: =COUNTIFS('2024 -2025-2026'!$M:$M,B33,'2024 -2025-2026'!$K:$K,"SCI",'2024 -2025-2026'!$G:$G,"2023") -> 0 | F33: =COUNTIFS('2024 -2025-2026'!$M:$M,B33,'2024 -2025-2026'!$K:$K,"Scopus/WoS Journals",'2024 -2025-2026'!$G:$G,"2023") -> 0 | G33: =COUNTIFS('2024 -2025-2026'!$M:$M,B33,'2024 -2025-2026'!$K:$K,"Scopus/WoS Conference/Book Chapter/Others", '2024 -2025-2026'!$G:$G,"2023") -> 0 | H33: =COUNTIFS('2024 -2025-2026'!$M:$M,B33,'2024 -2025-2026'!$K:$K,"Student Publication",'2024 -2025-2026'!$G:$G,"2023") -> 0 | I33: =COUNTIFS('2024 -2025-2026'!$M:$M,B33,'2024 -2025-2026'!$K:$K,"Book",'2024 -2025-2026'!$G:$G,"2023") -> 0 | J33: =SUM(E33:H33) -> 0
A34: 271 | B34: Ms. Hemamalini D | C34: AIDS | D34: AIDS | E34: =COUNTIFS('2024 -2025-2026'!$M:$M,B34,'2024 -2025-2026'!$K:$K,"SCI",'2024 -2025-2026'!$G:$G,"2023") -> 0 | F34: =COUNTIFS('2024 -2025-2026'!$M:$M,B34,'2024 -2025-2026'!$K:$K,"Scopus/WoS Journals",'2024 -2025-2026'!$G:$G,"2023") -> 0 | G34: =COUNTIFS('2024 -2025-2026'!$M:$M,B34,'2024 -2025-2026'!$K:$K,"Scopus/WoS Conference/Book Chapter/Others", '2024 -2025-2026'!$G:$G,"2023") -> 0 | H34: =COUNTIFS('2024 -2025-2026'!$M:$M,B34,'2024 -2025-2026'!$K:$K,"Student Publication",'2024 -2025-2026'!$G:$G,"2023") -> 0 | I34: =COUNTIFS('2024 -2025-2026'!$M:$M,B34,'2024 -2025-2026'!$K:$K,"Book",'2024 -2025-2026'!$G:$G,"2023") -> 0 | J34: =SUM(E34:H34) -> 0
A35: 272 | B35: Ms. Parimalam K | C35: AIDS | D35: AIDS | E35: =COUNTIFS('2024 -2025-2026'!$M:$M,B35,'2024 -2025-2026'!$K:$K,"SCI",'2024 -2025-2026'!$G:$G,"2023") -> 0 | F35: =COUNTIFS('2024 -2025-2026'!$M:$M,B35,'2024 -2025-2026'!$K:$K,"Scopus/WoS Journals",'2024 -2025-2026'!$G:$G,"2023") -> 0 | G35: =COUNTIFS('2024 -2025-2026'!$M:$M,B35,'2024 -2025-2026'!$K:$K,"Scopus/WoS Conference/Book Chapter/Others", '2024 -2025-2026'!$G:$G,"2023") -> 0 | H35: =COUNTIFS('2024 -2025-2026'!$M:$M,B35,'2024 -2025-2026'!$K:$K,"Student Publication",'2024 -2025-2026'!$G:$G,"2023") -> 0 | I35: =COUNTIFS('2024 -2025-2026'!$M:$M,B35,'2024 -2025-2026'!$K:$K,"Book",'2024 -2025-2026'!$G:$G,"2023") -> 0 | J35: =SUM(E35:H35) -> 0
A36: 273 | B36: Ms. Pooranam N | C36: AIDS | D36: AIDS | E36: =COUNTIFS('2024 -2025-2026'!$M:$M,B36,'2024 -2025-2026'!$K:$K,"SCI",'2024 -2025-2026'!$G:$G,"2023") -> 0 | F36: =COUNTIFS('2024 -2025-2026'!$M:$M,B36,'2024 -2025-2026'!$K:$K,"Scopus/WoS Journals",'2024 -2025-2026'!$G:$G,"2023") -> 0 | G36: =COUNTIFS('2024 -2025-2026'!$M:$M,B36,'2024 -2025-2026'!$K:$K,"Scopus/WoS Conference/Book Chapter/Others", '2024 -2025-2026'!$G:$G,"2023") -> 0 | H36: =COUNTIFS('2024 -2025-2026'!$M:$M,B36,'2024 -2025-2026'!$K:$K,"Student Publication",'2024 -2025-2026'!$G:$G,"2023") -> 0 | I36: =COUNTIFS('2024 -2025-2026'!$M:$M,B36,'2024 -2025-2026'!$K:$K,"Book",'2024 -2025-2026'!$G:$G,"2023") -> 0 | J36: =SUM(E36:H36) -> 0
A37: 274 | B37: Ms. Saranya C | C37: AIDS | D37: AIDS | E37: =COUNTIFS('2024 -2025-2026'!$M:$M,B37,'2024 -2025-2026'!$K:$K,"SCI",'2024 -2025-2026'!$G:$G,"2023") -> 0 | F37: =COUNTIFS('2024 -2025-2026'!$M:$M,B37,'2024 -2025-2026'!$K:$K,"Scopus/WoS Journals",'2024 -2025-2026'!$G:$G,"2023") -> 0 | G37: =COUNTIFS('2024 -2025-2026'!$M:$M,B37,'2024 -2025-2026'!$K:$K,"Scopus/WoS Conference/Book Chapter/Others", '2024 -2025-2026'!$G:$G,"2023") -> 0 | H37: =COUNTIFS('2024 -2025-2026'!$M:$M,B37,'2024 -2025-2026'!$K:$K,"Student Publication",'2024 -2025-2026'!$G:$G,"2023") -> 0 | I37: =COUNTIFS('2024 -2025-2026'!$M:$M,B37,'2024 -2025-2026'!$K:$K,"Book",'2024 -2025-2026'!$G:$G,"2023") -> 0 | J37: =SUM(E37:H37) -> 0
A38: 275 | B38: Dr. Shobana G | C38: AIDS | D38: AIDS | E38: =COUNTIFS('2024 -2025-2026'!$M:$M,B38,'2024 -2025-2026'!$K:$K,"SCI",'2024 -2025-2026'!$G:$G,"2023") -> 0 | F38: =COUNTIFS('2024 -2025-2026'!$M:$M,B38,'2024 -2025-2026'!$K:$K,"Scopus/WoS Journals",'2024 -2025-2026'!$G:$G,"2023") -> 0 | G38: =COUNTIFS('2024 -2025-2026'!$M:$M,B38,'2024 -2025-2026'!$K:$K,"Scopus/WoS Conference/Book Chapter/Others", '2024 -2025-2026'!$G:$G,"2023") -> 0 | H38: =COUNTIFS('2024 -2025-2026'!$M:$M,B38,'2024 -2025-2026'!$K:$K,"Student Publication",'2024 -2025-2026'!$G:$G,"2023") -> 0 | I38: =COUNTIFS('2024 -2025-2026'!$M:$M,B38,'2024 -2025-2026'!$K:$K,"Book",'2024 -2025-2026'!$G:$G,"2023") -> 0 | J38: =SUM(E38:H38) -> 0
A39: 276 | B39: Dr. Sivaramakrishnan A | C39: AIDS | D39: AIDS | E39: =COUNTIFS('2024 -2025-2026'!$M:$M,B39,'2024 -2025-2026'!$K:$K,"SCI",'2024 -2025-2026'!$G:$G,"2023") -> 0 | F39: =COUNTIFS('2024 -2025-2026'!$M:$M,B39,'2024 -2025-2026'!$K:$K,"Scopus/WoS Journals",'2024 -2025-2026'!$G:$G,"2023") -> 0 | G39: =COUNTIFS('2024 -2025-2026'!$M:$M,B39,'2024 -2025-2026'!$K:$K,"Scopus/WoS Conference/Book Chapter/Others", '2024 -2025-2026'!$G:$G,"2023") -> 0 | H39: =COUNTIFS('2024 -2025-2026'!$M:$M,B39,'2024 -2025-2026'!$K:$K,"Student Publication",'2024 -2025-2026'!$G:$G,"2023") -> 0 | I39: =COUNTIFS('2024 -2025-2026'!$M:$M,B39,'2024 -2025-2026'!$K:$K,"Book",'2024 -2025-2026'!$G:$G,"2023") -> 0 | J39: =SUM(E39:H39) -> 0
A40: 307 | E40: =COUNTIFS('2024 -2025-2026'!$M:$M,B40,'2024 -2025-2026'!$K:$K,"SCI",'2024 -2025-2026'!$G:$G,"2023") -> 0 | F40: =COUNTIFS('2024 -2025-2026'!$M:$M,B40,'2024 -2025-2026'!$K:$K,"Scopus/WoS Journals",'2024 -2025-2026'!$G:$G,"2023") -> 0 | G40: =COUNTIFS('2024 -2025-2026'!$M:$M,B40,'2024 -2025-2026'!$K:$K,"Scopus/WoS Conference/Book Chapter/Others", '2024 -2025-2026'!$G:$G,"2023") -> 0 | H40: =COUNTIFS('2024 -2025-2026'!$M:$M,B40,'2024 -2025-2026'!$K:$K,"Student Publication",'2024 -2025-2026'!$G:$G,"2023") -> 0 | I40: =COUNTIFS('2024 -2025-2026'!$M:$M,B40,'2024 -2025-2026'!$K:$K,"Book",'2024 -2025-2026'!$G:$G,"2023") -> 0 | J40: =SUM(E40:H40) -> 0
A41: 23 | B41: Dr. Karunakaran V | C41: AIML | D41: AIML | E41: =COUNTIFS('2024 -2025-2026'!$M:$M,B41,'2024 -2025-2026'!$K:$K,"SCI",'2024 -2025-2026'!$G:$G,"2023") -> 0 | F41: =COUNTIFS('2024 -2025-2026'!$M:$M,B41,'2024 -2025-2026'!$K:$K,"Scopus/WoS Journals",'2024 -2025-2026'!$G:$G,"2023") -> 0 | G41: =COUNTIFS('2024 -2025-2026'!$M:$M,B41,'2024 -2025-2026'!$K:$K,"Scopus/WoS Conference/Book Chapter/Others", '2024 -2025-2026'!$G:$G,"2023") -> 1 | H41: =COUNTIFS('2024 -2025-2026'!$M:$M,B41,'2024 -2025-2026'!$K:$K,"Student Publication",'2024 -2025-2026'!$G:$G,"2023") -> 0 | I41: =COUNTIFS('2024 -2025-2026'!$M:$M,B41,'2024 -2025-2026'!$K:$K,"Book",'2024 -2025-2026'!$G:$G,"2023") -> 0 | J41: =SUM(E41:H41) -> 1
A42: 24 | B42: Dr. Sumathi S | C42: AIML | D42: AIML | E42: =COUNTIFS('2024 -2025-2026'!$M:$M,B42,'2024 -2025-2026'!$K:$K,"SCI",'2024 -2025-2026'!$G:$G,"2023") -> 0 | F42: =COUNTIFS('2024 -2025-2026'!$M:$M,B42,'2024 -2025-2026'!$K:$K,"Scopus/WoS Journals",'2024 -2025-2026'!$G:$G,"2023") -> 0 | G42: =COUNTIFS('2024 -2025-2026'!$M:$M,B42,'2024 -2025-2026'!$K:$K,"Scopus/WoS Conference/Book Chapter/Others", '2024 -2025-2026'!$G:$G,"2023") -> 0 | H42: =COUNTIFS('2024 -2025-2026'!$M:$M,B42,'2024 -2025-2026'!$K:$K,"Student Publication",'2024 -2025-2026'!$G:$G,"2023") -> 2 | I42: =COUNTIFS('2024 -2025-2026'!$M:$M,B42,'2024 -2025-2026'!$K:$K,"Book",'2024 -2025-2026'!$G:$G,"2023") -> 0 | J42: =SUM(E42:H42) -> 2
A43: 25 | B43: Dr. Kathiresan K | C43: AIML | D43: AIML | E43: =COUNTIFS('2024 -2025-2026'!$M:$M,B43,'2024 -2025-2026'!$K:$K,"SCI",'2024 -2025-2026'!$G:$G,"2023") -> 0 | F43: =COUNTIFS('2024 -2025-2026'!$M:$M,B43,'2024 -2025-2026'!$K:$K,"Scopus/WoS Journals",'2024 -2025-2026'!$G:$G,"2023") -> 0 | G43: =COUNTIFS('2024 -2025-2026'!$M:$M,B43,'2024 -2025-2026'!$K:$K,"Scopus/WoS Conference/Book Chapter/Others", '2024 -2025-2026'!$G:$G,"2023") -> 0 | H43: =COUNTIFS('2024 -2025-2026'!$M:$M,B43,'2024 -2025-2026'!$K:$K,"Student Publication",'2024 -2025-2026'!$G:$G,"2023") -> 0 | I43: =COUNTIFS('2024 -2025-2026'!$M:$M,B43,'2024 -2025-2026'!$K:$K,"Book",'2024 -2025-2026'!$G:$G,"2023") -> 0 | J43: =SUM(E43:H43) -> 0
A44: 26 | B44: Ms. Preethi P | C44: AIML | D44: AIML | E44: =COUNTIFS('2024 -2025-2026'!$M:$M,B44,'2024 -2025-2026'!$K:$K,"SCI",'2024 -2025-2026'!$G:$G,"2023") -> 0 | F44: =COUNTIFS('2024 -2025-2026'!$M:$M,B44,'2024 -2025-2026'!$K:$K,"Scopus/WoS Journals",'2024 -2025-2026'!$G:$G,"2023") -> 0 | G44: =COUNTIFS('2024 -2025-2026'!$M:$M,B44,'2024 -2025-2026'!$K:$K,"Scopus/WoS Conference/Book Chapter/Others", '2024 -2025-2026'!$G:$G,"2023") -> 0 | H44: =COUNTIFS('2024 -2025-2026'!$M:$M,B44,'2024 -2025-2026'!$K:$K,"Student Publication",'2024 -2025-2026'!$G:$G,"2023") -> 0 | I44: =COUNTIFS('2024 -2025-2026'!$M:$M,B44,'2024 -2025-2026'!$K:$K,"Book",'2024 -2025-2026'!$G:$G,"2023") -> 0 | J44: =SUM(E44:H44) -> 0
A45: 27 | B45: Ms. Sindhuja S | C45: AIML | D45: AIML | E45: =COUNTIFS('2024 -2025-2026'!$M:$M,B45,'2024 -2025-2026'!$K:$K,"SCI",'2024 -2025-2026'!$G:$G,"2023") -> 0 | F45: =COUNTIFS('2024 -2025-2026'!$M:$M,B45,'2024 -2025-2026'!$K:$K,"Scopus/WoS Journals",'2024 -2025-2026'!$G:$G,"2023") -> 0 | G45: =COUNTIFS('2024 -2025-2026'!$M:$M,B45,'2024 -2025-2026'!$K:$K,"Scopus/WoS Conference/Book Chapter/Others", '2024 -2025-2026'!$G:$G,"2023") -> 0 | H45: =COUNTIFS('2024 -2025-2026'!$M:$M,B45,'2024 -2025-2026'!$K:$K,"Student Publication",'2024 -2025-2026'!$G:$G,"2023") -> 0 | I45: =COUNTIFS('2024 -2025-2026'!$M:$M,B45,'2024 -2025-2026'!$K:$K,"Book",'2024 -2025-2026'!$G:$G,"2023") -> 0 | J45: =SUM(E45:H45) -> 0
A46: 28 | B46: Ms. Kalaivani T | C46: AIML | D46: AIML | E46: =COUNTIFS('2024 -2025-2026'!$M:$M,B46,'2024 -2025-2026'!$K:$K,"SCI",'2024 -2025-2026'!$G:$G,"2023") -> 0 | F46: =COUNTIFS('2024 -2025-2026'!$M:$M,B46,'2024 -2025-2026'!$K:$K,"Scopus/WoS Journals",'2024 -2025-2026'!$G:$G,"2023") -> 0 | G46: =COUNTIFS('2024 -2025-2026'!$M:$M,B46,'2024 -2025-2026'!$K:$K,"Scopus/WoS Conference/Book Chapter/Others", '2024 -2025-2026'!$G:$G,"2023") -> 0 | H46: =COUNTIFS('2024 -2025-2026'!$M:$M,B46,'2024 -2025-2026'!$K:$K,"Student Publication",'2024 -2025-2026'!$G:$G,"2023") -> 0 | I46: =COUNTIFS('2024 -2025-2026'!$M:$M,B46,'2024 -2025-2026'!$K:$K,"Book",'2024 -2025-2026'!$G:$G,"2023") -> 0 | J46: =SUM(E46:H46) -> 0
A47: 29 | B47: Ms. Charanya P | C47: AIML | D47: AIML | E47: =COUNTIFS('2024 -2025-2026'!$M:$M,B47,'2024 -2025-2026'!$K:$K,"SCI",'2024 -2025-2026'!$G:$G,"2023") -> 0 | F47: =COUNTIFS('2024 -2025-2026'!$M:$M,B47,'2024 -2025-2026'!$K:$K,"Scopus/WoS Journals",'2024 -2025-2026'!$G:$G,"2023") -> 0 | G47: =COUNTIFS('2024 -2025-2026'!$M:$M,B47,'2024 -2025-2026'!$K:$K,"Scopus/WoS Conference/Book Chapter/Others", '2024 -2025-2026'!$G:$G,"2023") -> 0 | H47: =COUNTIFS('2024 -2025-2026'!$M:$M,B47,'2024 -2025-2026'!$K:$K,"Student Publication",'2024 -2025-2026'!$G:$G,"2023") -> 0 | I47: =COUNTIFS('2024 -2025-2026'!$M:$M,B47,'2024 -2025-2026'!$K:$K,"Book",'2024 -2025-2026'!$G:$G,"2023") -> 0 | J47: =SUM(E47:H47) -> 0
A48: 253 | B48: Others AIML | C48: AIML | D48: AIML | E48: =COUNTIFS('2024 -2025-2026'!$M:$M,B48,'2024 -2025-2026'!$K:$K,"SCI",'2024 -2025-2026'!$G:$G,"2023") -> 0 | F48: =COUNTIFS('2024 -2025-2026'!$M:$M,B48,'2024 -2025-2026'!$K:$K,"Scopus/WoS Journals",'2024 -2025-2026'!$G:$G,"2023") -> 0 | G48: =COUNTIFS('2024 -2025-2026'!$M:$M,B48,'2024 -2025-2026'!$K:$K,"Scopus/WoS Conference/Book Chapter/Others", '2024 -2025-2026'!$G:$G,"2023") -> 0 | H48: =COUNTIFS('2024 -2025-2026'!$M:$M,B48,'2024 -2025-2026'!$K:$K,"Student Publication",'2024 -2025-2026'!$G:$G,"2023") -> 0 | I48: =COUNTIFS('2024 -2025-2026'!$M:$M,B48,'2024 -2025-2026'!$K:$K,"Book",'2024 -2025-2026'!$G:$G,"2023") -> 0 | J48: =SUM(E48:H48) -> 0
A49: 277 | B49: Dr. Brindha Senthil Kumar | C49: AIML | D49: AIML | E49: =COUNTIFS('2024 -2025-2026'!$M:$M,B49,'2024 -2025-2026'!$K:$K,"SCI",'2024 -2025-2026'!$G:$G,"2023") -> 0 | F49: =COUNTIFS('2024 -2025-2026'!$M:$M,B49,'2024 -2025-2026'!$K:$K,"Scopus/WoS Journals",'2024 -2025-2026'!$G:$G,"2023") -> 0 | G49: =COUNTIFS('2024 -2025-2026'!$M:$M,B49,'2024 -2025-2026'!$K:$K,"Scopus/WoS Conference/Book Chapter/Others", '2024 -2025-2026'!$G:$G,"2023") -> 0 | H49: =COUNTIFS('2024 -2025-2026'!$M:$M,B49,'2024 -2025-2026'!$K:$K,"Student Publication",'2024 -2025-2026'!$G:$G,"2023") -> 0 | I49: =COUNTIFS('2024 -2025-2026'!$M:$M,B49,'2024 -2025-2026'!$K:$K,"Book",'2024 -2025-2026'!$G:$G,"2023") -> 0 | J49: =SUM(E49:H49) -> 0
A50: 278 | B50: Dr. Varatharajan N | C50: AIML | D50: AIML | E50: =COUNTIFS('2024 -2025-2026'!$M:$M,B50,'2024 -2025-2026'!$K:$K,"SCI",'2024 -2025-2026'!$G:$G,"2023") -> 0 | F50: =COUNTIFS('2024 -2025-2026'!$M:$M,B50,'2024 -2025-2026'!$K:$K,"Scopus/WoS Journals",'2024 -2025-2026'!$G:$G,"2023") -> 0 | G50: =COUNTIFS('2024 -2025-2026'!$M:$M,B50,'2024 -2025-2026'!$K:$K,"Scopus/WoS Conference/Book Chapter/Others", '2024 -2025-2026'!$G:$G,"2023") -> 0 | H50: =COUNTIFS('2024 -2025-2026'!$M:$M,B50,'2024 -2025-2026'!$K:$K,"Student Publication",'2024 -2025-2026'!$G:$G,"2023") -> 0 | I50: =COUNTIFS('2024 -2025-2026'!$M:$M,B50,'2024 -2025-2026'!$K:$K,"Book",'2024 -2025-2026'!$G:$G,"2023") -> 0 | J50: =SUM(E50:H50) -> 0
A51: 279 | B51: Mr. Vikkram R | C51: AIML | D51: AIML | E51: =COUNTIFS('2024 -2025-2026'!$M:$M,B51,'2024 -2025-2026'!$K:$K,"SCI",'2024 -2025-2026'!$G:$G,"2023") -> 0 | F51: =COUNTIFS('2024 -2025-2026'!$M:$M,B51,'2024 -2025-2026'!$K:$K,"Scopus/WoS Journals",'2024 -2025-2026'!$G:$G,"2023") -> 0 | G51: =COUNTIFS('2024 -2025-2026'!$M:$M,B51,'2024 -2025-2026'!$K:$K,"Scopus/WoS Conference/Book Chapter/Others", '2024 -2025-2026'!$G:$G,"2023") -> 0 | H51: =COUNTIFS('2024 -2025-2026'!$M:$M,B51,'2024 -2025-2026'!$K:$K,"Student Publication",'2024 -2025-2026'!$G:$G,"2023") -> 0 | I51: =COUNTIFS('2024 -2025-2026'!$M:$M,B51,'2024 -2025-2026'!$K:$K,"Book",'2024 -2025-2026'!$G:$G,"2023") -> 0 | J51: =SUM(E51:H51) -> 0
A52: 280 | B52: Ms. Suganya A | C52: AIML | D52: AIML | E52: =COUNTIFS('2024 -2025-2026'!$M:$M,B52,'2024 -2025-2026'!$K:$K,"SCI",'2024 -2025-2026'!$G:$G,"2023") -> 0 | F52: =COUNTIFS('2024 -2025-2026'!$M:$M,B52,'2024 -2025-2026'!$K:$K,"Scopus/WoS Journals",'2024 -2025-2026'!$G:$G,"2023") -> 0 | G52: =COUNTIFS('2024 -2025-2026'!$M:$M,B52,'2024 -2025-2026'!$K:$K,"Scopus/WoS Conference/Book Chapter/Others", '2024 -2025-2026'!$G:$G,"2023") -> 0 | H52: =COUNTIFS('2024 -2025-2026'!$M:$M,B52,'2024 -2025-2026'!$K:$K,"Student Publication",'2024 -2025-2026'!$G:$G,"2023") -> 0 | I52: =COUNTIFS('2024 -2025-2026'!$M:$M,B52,'2024 -2025-2026'!$K:$K,"Book",'2024 -2025-2026'!$G:$G,"2023") -> 0 | J52: =SUM(E52:H52) -> 0
... A290: 225 | B290: Dr. Yogeswari B | C290: S&H | D290: S & H (Phy) | E290: =COUNTIFS('2024 -2025-2026'!$M:$M,B290,'2024 -2025-2026'!$K:$K,"SCI",'2024 -2025-2026'!$G:$G,"2023") -> 5 | F290: =COUNTIFS('2024 -2025-2026'!$M:$M,B290,'2024 -2025-2026'!$K:$K,"Scopus/WoS Journals",'2024 -2025-2026'!$G:$G,"2023") -> 0 | G290: =COUNTIFS('2024 -2025-2026'!$M:$M,B290,'2024 -2025-2026'!$K:$K,"Scopus/WoS Conference/Book Chapter/Others", '2024 -2025-2026'!$G:$G,"2023") -> 1 | H290: =COUNTIFS('2024 -2025-2026'!$M:$M,B290,'2024 -2025-2026'!$K:$K,"Student Publication",'2024 -2025-2026'!$G:$G,"2023") -> 0 | I290: =COUNTIFS('2024 -2025-2026'!$M:$M,B290,'2024 -2025-2026'!$K:$K,"Book",'2024 -2025-2026'!$G:$G,"2023") -> 0 | J290: =SUM(E290:H290) -> 6
A291: 303 | C291: S&H | D291: S & H (Phy) | E291: =COUNTIFS('2024 -2025-2026'!$M:$M,B291,'2024 -2025-2026'!$K:$K,"SCI",'2024 -2025-2026'!$G:$G,"2023") -> 0 | F291: =COUNTIFS('2024 -2025-2026'!$M:$M,B291,'2024 -2025-2026'!$K:$K,"Scopus/WoS Journals",'2024 -2025-2026'!$G:$G,"2023") -> 0 | G291: =COUNTIFS('2024 -2025-2026'!$M:$M,B291,'2024 -2025-2026'!$K:$K,"Scopus/WoS Conference/Book Chapter/Others", '2024 -2025-2026'!$G:$G,"2023") -> 0 | H291: =COUNTIFS('2024 -2025-2026'!$M:$M,B291,'2024 -2025-2026'!$K:$K,"Student Publication",'2024 -2025-2026'!$G:$G,"2023") -> 0 | I291: =COUNTIFS('2024 -2025-2026'!$M:$M,B291,'2024 -2025-2026'!$K:$K,"Book",'2024 -2025-2026'!$G:$G,"2023") -> 0 | J291: =SUM(E291:H291) -> 0
A292: 255 | B292: Others Maths | C292: S&H | D292: S&H | E292: =COUNTIFS('2024 -2025-2026'!$M:$M,B292,'2024 -2025-2026'!$K:$K,"SCI",'2024 -2025-2026'!$G:$G,"2023") -> 1 | F292: =COUNTIFS('2024 -2025-2026'!$M:$M,B292,'2024 -2025-2026'!$K:$K,"Scopus/WoS Journals",'2024 -2025-2026'!$G:$G,"2023") -> 0 | G292: =COUNTIFS('2024 -2025-2026'!$M:$M,B292,'2024 -2025-2026'!$K:$K,"Scopus/WoS Conference/Book Chapter/Others", '2024 -2025-2026'!$G:$G,"2023") -> 0 | H292: =COUNTIFS('2024 -2025-2026'!$M:$M,B292,'2024 -2025-2026'!$K:$K,"Student Publication",'2024 -2025-2026'!$G:$G,"2023") -> 0 | I292: =COUNTIFS('2024 -2025-2026'!$M:$M,B292,'2024 -2025-2026'!$K:$K,"Book",'2024 -2025-2026'!$G:$G,"2023") -> 0 | J292: =SUM(E292:H292) -> 1
A293: 260 | B293: Others S&H | C293: S&H | D293: S&H | E293: =COUNTIFS('2024 -2025-2026'!$M:$M,B293,'2024 -2025-2026'!$K:$K,"SCI",'2024 -2025-2026'!$G:$G,"2023") -> 0 | F293: =COUNTIFS('2024 -2025-2026'!$M:$M,B293,'2024 -2025-2026'!$K:$K,"Scopus/WoS Journals",'2024 -2025-2026'!$G:$G,"2023") -> 0 | G293: =COUNTIFS('2024 -2025-2026'!$M:$M,B293,'2024 -2025-2026'!$K:$K,"Scopus/WoS Conference/Book Chapter/Others", '2024 -2025-2026'!$G:$G,"2023") -> 1 | H293: =COUNTIFS('2024 -2025-2026'!$M:$M,B293,'2024 -2025-2026'!$K:$K,"Student Publication",'2024 -2025-2026'!$G:$G,"2023") -> 0 | I293: =COUNTIFS('2024 -2025-2026'!$M:$M,B293,'2024 -2025-2026'!$K:$K,"Book",'2024 -2025-2026'!$G:$G,"2023") -> 0 | J293: =SUM(E293:H293) -> 1
A294: 261 | B294: Student Publication S&H | C294: S&H | D294: S&H | E294: =COUNTIFS('2024 -2025-2026'!$M:$M,B294,'2024 -2025-2026'!$K:$K,"SCI",'2024 -2025-2026'!$G:$G,"2023") -> 0 | F294: =COUNTIFS('2024 -2025-2026'!$M:$M,B294,'2024 -2025-2026'!$K:$K,"Scopus/WoS Journals",'2024 -2025-2026'!$G:$G,"2023") -> 0 | G294: =COUNTIFS('2024 -2025-2026'!$M:$M,B294,'2024 -2025-2026'!$K:$K,"Scopus/WoS Conference/Book Chapter/Others", '2024 -2025-2026'!$G:$G,"2023") -> 0 | H294: =COUNTIFS('2024 -2025-2026'!$M:$M,B294,'2024 -2025-2026'!$K:$K,"Student Publication",'2024 -2025-2026'!$G:$G,"2023") -> 0 | I294: =COUNTIFS('2024 -2025-2026'!$M:$M,B294,'2024 -2025-2026'!$K:$K,"Book",'2024 -2025-2026'!$G:$G,"2023") -> 0 | J294: =SUM(E294:H294) -> 0
A295: 298 | B295: Dr. Sivagurusundar R | C295: S&H | D295: S&H | E295: =COUNTIFS('2024 -2025-2026'!$M:$M,B295,'2024 -2025-2026'!$K:$K,"SCI",'2024 -2025-2026'!$G:$G,"2023") -> 0 | F295: =COUNTIFS('2024 -2025-2026'!$M:$M,B295,'2024 -2025-2026'!$K:$K,"Scopus/WoS Journals",'2024 -2025-2026'!$G:$G,"2023") -> 0 | G295: =COUNTIFS('2024 -2025-2026'!$M:$M,B295,'2024 -2025-2026'!$K:$K,"Scopus/WoS Conference/Book Chapter/Others", '2024 -2025-2026'!$G:$G,"2023") -> 0 | H295: =COUNTIFS('2024 -2025-2026'!$M:$M,B295,'2024 -2025-2026'!$K:$K,"Student Publication",'2024 -2025-2026'!$G:$G,"2023") -> 0 | I295: =COUNTIFS('2024 -2025-2026'!$M:$M,B295,'2024 -2025-2026'!$K:$K,"Book",'2024 -2025-2026'!$G:$G,"2023") -> 0 | J295: =SUM(E295:H295) -> 0
A296: 299 | B296: Dr. Vennila R | C296: S&H | D296: S&H (Maths) | E296: =COUNTIFS('2024 -2025-2026'!$M:$M,B296,'2024 -2025-2026'!$K:$K,"SCI",'2024 -2025-2026'!$G:$G,"2023") -> 0 | F296: =COUNTIFS('2024 -2025-2026'!$M:$M,B296,'2024 -2025-2026'!$K:$K,"Scopus/WoS Journals",'2024 -2025-2026'!$G:$G,"2023") -> 0 | G296: =COUNTIFS('2024 -2025-2026'!$M:$M,B296,'2024 -2025-2026'!$K:$K,"Scopus/WoS Conference/Book Chapter/Others", '2024 -2025-2026'!$G:$G,"2023") -> 0 | H296: =COUNTIFS('2024 -2025-2026'!$M:$M,B296,'2024 -2025-2026'!$K:$K,"Student Publication",'2024 -2025-2026'!$G:$G,"2023") -> 0 | I296: =COUNTIFS('2024 -2025-2026'!$M:$M,B296,'2024 -2025-2026'!$K:$K,"Book",'2024 -2025-2026'!$G:$G,"2023") -> 0 | J296: =SUM(E296:H296) -> 0
A297: 300 | B297: Dr. Vinnarasi S | C297: S&H | D297: S&H (Maths) | E297: =COUNTIFS('2024 -2025-2026'!$M:$M,B297,'2024 -2025-2026'!$K:$K,"SCI",'2024 -2025-2026'!$G:$G,"2023") -> 0 | F297: =COUNTIFS('2024 -2025-2026'!$M:$M,B297,'2024 -2025-2026'!$K:$K,"Scopus/WoS Journals",'2024 -2025-2026'!$G:$G,"2023") -> 0 | G297: =COUNTIFS('2024 -2025-2026'!$M:$M,B297,'2024 -2025-2026'!$K:$K,"Scopus/WoS Conference/Book Chapter/Others", '2024 -2025-2026'!$G:$G,"2023") -> 0 | H297: =COUNTIFS('2024 -2025-2026'!$M:$M,B297,'2024 -2025-2026'!$K:$K,"Student Publication",'2024 -2025-2026'!$G:$G,"2023") -> 0 | I297: =COUNTIFS('2024 -2025-2026'!$M:$M,B297,'2024 -2025-2026'!$K:$K,"Book",'2024 -2025-2026'!$G:$G,"2023") -> 0 | J297: =SUM(E297:H297) -> 0
A298: 239 | B298: Student Publication | C298: SP | D298: SP | E298: =COUNTIFS('2024 -2025-2026'!$M:$M,B298,'2024 -2025-2026'!$K:$K,"SCI",'2024 -2025-2026'!$G:$G,"2023") -> 0 | F298: =COUNTIFS('2024 -2025-2026'!$M:$M,B298,'2024 -2025-2026'!$K:$K,"Scopus/WoS Journals",'2024 -2025-2026'!$G:$G,"2023") -> 0 | G298: =COUNTIFS('2024 -2025-2026'!$M:$M,B298,'2024 -2025-2026'!$K:$K,"Scopus/WoS Conference/Book Chapter/Others", '2024 -2025-2026'!$G:$G,"2023") -> 0 | H298: =COUNTIFS('2024 -2025-2026'!$M:$M,B298,'2024 -2025-2026'!$K:$K,"Student Publication",'2024 -2025-2026'!$G:$G,"2023") -> 0 | I298: =COUNTIFS('2024 -2025-2026'!$M:$M,B298,'2024 -2025-2026'!$K:$K,"Book",'2024 -2025-2026'!$G:$G,"2023") -> 0 | J298: =SUM(E298:H298) -> 0
A299: 240 | B299: Student Publication AIDS | C299: SP AIDS | D299: SP AIDS | E299: =COUNTIFS('2024 -2025-2026'!$M:$M,B299,'2024 -2025-2026'!$K:$K,"SCI",'2024 -2025-2026'!$G:$G,"2023") -> 0 | F299: =COUNTIFS('2024 -2025-2026'!$M:$M,B299,'2024 -2025-2026'!$K:$K,"Scopus/WoS Journals",'2024 -2025-2026'!$G:$G,"2023") -> 0 | G299: =COUNTIFS('2024 -2025-2026'!$M:$M,B299,'2024 -2025-2026'!$K:$K,"Scopus/WoS Conference/Book Chapter/Others", '2024 -2025-2026'!$G:$G,"2023") -> 0 | H299: =COUNTIFS('2024 -2025-2026'!$M:$M,B299,'2024 -2025-2026'!$K:$K,"Student Publication",'2024 -2025-2026'!$G:$G,"2023") -> 0 | I299: =COUNTIFS('2024 -2025-2026'!$M:$M,B299,'2024 -2025-2026'!$K:$K,"Book",'2024 -2025-2026'!$G:$G,"2023") -> 0 | J299: =SUM(E299:H299) -> 0
A300: 241 | B300: Student Publication CCE | C300: SP CCE | D300: SP CCE | E300: =COUNTIFS('2024 -2025-2026'!$M:$M,B300,'2024 -2025-2026'!$K:$K,"SCI",'2024 -2025-2026'!$G:$G,"2023") -> 0 | F300: =COUNTIFS('2024 -2025-2026'!$M:$M,B300,'2024 -2025-2026'!$K:$K,"Scopus/WoS Journals",'2024 -2025-2026'!$G:$G,"2023") -> 0 | G300: =COUNTIFS('2024 -2025-2026'!$M:$M,B300,'2024 -2025-2026'!$K:$K,"Scopus/WoS Conference/Book Chapter/Others", '2024 -2025-2026'!$G:$G,"2023") -> 0 | H300: =COUNTIFS('2024 -2025-2026'!$M:$M,B300,'2024 -2025-2026'!$K:$K,"Student Publication",'2024 -2025-2026'!$G:$G,"2023") -> 0 | I300: =COUNTIFS('2024 -2025-2026'!$M:$M,B300,'2024 -2025-2026'!$K:$K,"Book",'2024 -2025-2026'!$G:$G,"2023") -> 0 | J300: =SUM(E300:H300) -> 0
A301: 242 | B301: Student Publication CSBS | C301: SP CSBS | D301: SP CSBS | E301: =COUNTIFS('2024 -2025-2026'!$M:$M,B301,'2024 -2025-2026'!$K:$K,"SCI",'2024 -2025-2026'!$G:$G,"2023") -> 0 | F301: =COUNTIFS('2024 -2025-2026'!$M:$M,B301,'2024 -2025-2026'!$K:$K,"Scopus/WoS Journals",'2024 -2025-2026'!$G:$G,"2023") -> 0 | G301: =COUNTIFS('2024 -2025-2026'!$M:$M,B301,'2024 -2025-2026'!$K:$K,"Scopus/WoS Conference/Book Chapter/Others", '2024 -2025-2026'!$G:$G,"2023") -> 0 | H301: =COUNTIFS('2024 -2025-2026'!$M:$M,B301,'2024 -2025-2026'!$K:$K,"Student Publication",'2024 -2025-2026'!$G:$G,"2023") -> 0 | I301: =COUNTIFS('2024 -2025-2026'!$M:$M,B301,'2024 -2025-2026'!$K:$K,"Book",'2024 -2025-2026'!$G:$G,"2023") -> 0 | J301: =SUM(E301:H301) -> 0
A302: 243 | B302: Student Publication CSE | C302: SP CSE | D302: SP CSE | E302: =COUNTIFS('2024 -2025-2026'!$M:$M,B302,'2024 -2025-2026'!$K:$K,"SCI",'2024 -2025-2026'!$G:$G,"2023") -> 0 | F302: =COUNTIFS('2024 -2025-2026'!$M:$M,B302,'2024 -2025-2026'!$K:$K,"Scopus/WoS Journals",'2024 -2025-2026'!$G:$G,"2023") -> 0 | G302: =COUNTIFS('2024 -2025-2026'!$M:$M,B302,'2024 -2025-2026'!$K:$K,"Scopus/WoS Conference/Book Chapter/Others", '2024 -2025-2026'!$G:$G,"2023") -> 0 | H302: =COUNTIFS('2024 -2025-2026'!$M:$M,B302,'2024 -2025-2026'!$K:$K,"Student Publication",'2024 -2025-2026'!$G:$G,"2023") -> 0 | I302: =COUNTIFS('2024 -2025-2026'!$M:$M,B302,'2024 -2025-2026'!$K:$K,"Book",'2024 -2025-2026'!$G:$G,"2023") -> 0 | J302: =SUM(E302:H302) -> 0
A303: 244 | B303: Student Publication ECE | C303: SP ECE | D303: SP ECE | E303: =COUNTIFS('2024 -2025-2026'!$M:$M,B303,'2024 -2025-2026'!$K:$K,"SCI",'2024 -2025-2026'!$G:$G,"2023") -> 0 | F303: =COUNTIFS('2024 -2025-2026'!$M:$M,B303,'2024 -2025-2026'!$K:$K,"Scopus/WoS Journals",'2024 -2025-2026'!$G:$G,"2023") -> 0 | G303: =COUNTIFS('2024 -2025-2026'!$M:$M,B303,'2024 -2025-2026'!$K:$K,"Scopus/WoS Conference/Book Chapter/Others", '2024 -2025-2026'!$G:$G,"2023") -> 0 | H303: =COUNTIFS('2024 -2025-2026'!$M:$M,B303,'2024 -2025-2026'!$K:$K,"Student Publication",'2024 -2025-2026'!$G:$G,"2023") -> 0 | I303: =COUNTIFS('2024 -2025-2026'!$M:$M,B303,'2024 -2025-2026'!$K:$K,"Book",'2024 -2025-2026'!$G:$G,"2023") -> 0 | J303: =SUM(E303:H303) -> 0
... A306: 247 | B306: Student Publication Mech | C306: SP Mech | D306: SP Mech | E306: =COUNTIFS('2024 -2025-2026'!$M:$M,B306,'2024 -2025-2026'!$K:$K,"SCI",'2024 -2025-2026'!$G:$G,"2023") -> 0 | F306: =COUNTIFS('2024 -2025-2026'!$M:$M,B306,'2024 -2025-2026'!$K:$K,"Scopus/WoS Journals",'2024 -2025-2026'!$G:$G,"2023") -> 0 | G306: =COUNTIFS('2024 -2025-2026'!$M:$M,B306,'2024 -2025-2026'!$K:$K,"Scopus/WoS Conference/Book Chapter/Others", '2024 -2025-2026'!$G:$G,"2023") -> 0 | H306: =COUNTIFS('2024 -2025-2026'!$M:$M,B306,'2024 -2025-2026'!$K:$K,"Student Publication",'2024 -2025-2026'!$G:$G,"2023") -> 0 | I306: =COUNTIFS('2024 -2025-2026'!$M:$M,B306,'2024 -2025-2026'!$K:$K,"Book",'2024 -2025-2026'!$G:$G,"2023") -> 0 | J306: =SUM(E306:H306) -> 0
A307: 248 | B307: Student Publication AIML | E307: =COUNTIFS('2024 -2025-2026'!$M:$M,B307,'2024 -2025-2026'!$K:$K,"SCI",'2024 -2025-2026'!$G:$G,"2023") -> 0 | F307: =COUNTIFS('2024 -2025-2026'!$M:$M,B307,'2024 -2025-2026'!$K:$K,"Scopus/WoS Journals",'2024 -2025-2026'!$G:$G,"2023") -> 0 | G307: =COUNTIFS('2024 -2025-2026'!$M:$M,B307,'2024 -2025-2026'!$K:$K,"Scopus/WoS Conference/Book Chapter/Others", '2024 -2025-2026'!$G:$G,"2023") -> 0 | H307: =COUNTIFS('2024 -2025-2026'!$M:$M,B307,'2024 -2025-2026'!$K:$K,"Student Publication",'2024 -2025-2026'!$G:$G,"2023") -> 0 | I307: =COUNTIFS('2024 -2025-2026'!$M:$M,B307,'2024 -2025-2026'!$K:$K,"Book",'2024 -2025-2026'!$G:$G,"2023") -> 0 | J307: =SUM(E307:H307) -> 0
A308: 302 | B308: Dr. Vani S | E308: =COUNTIFS('2024 -2025-2026'!$M:$M,B308,'2024 -2025-2026'!$K:$K,"SCI",'2024 -2025-2026'!$G:$G,"2023") -> 0 | F308: =COUNTIFS('2024 -2025-2026'!$M:$M,B308,'2024 -2025-2026'!$K:$K,"Scopus/WoS Journals",'2024 -2025-2026'!$G:$G,"2023") -> 0 | G308: =COUNTIFS('2024 -2025-2026'!$M:$M,B308,'2024 -2025-2026'!$K:$K,"Scopus/WoS Conference/Book Chapter/Others", '2024 -2025-2026'!$G:$G,"2023") -> 0 | H308: =COUNTIFS('2024 -2025-2026'!$M:$M,B308,'2024 -2025-2026'!$K:$K,"Student Publication",'2024 -2025-2026'!$G:$G,"2023") -> 0 | I308: =COUNTIFS('2024 -2025-2026'!$M:$M,B308,'2024 -2025-2026'!$K:$K,"Book",'2024 -2025-2026'!$G:$G,"2023") -> 0 | J308: =SUM(E308:H308) -> 0
A309: 308 | B309: Dr. Saranya D | E309: =COUNTIFS('2024 -2025-2026'!$M:$M,B309,'2024 -2025-2026'!$K:$K,"SCI",'2024 -2025-2026'!$G:$G,"2023") -> 0 | F309: =COUNTIFS('2024 -2025-2026'!$M:$M,B309,'2024 -2025-2026'!$K:$K,"Scopus/WoS Journals",'2024 -2025-2026'!$G:$G,"2023") -> 0 | G309: =COUNTIFS('2024 -2025-2026'!$M:$M,B309,'2024 -2025-2026'!$K:$K,"Scopus/WoS Conference/Book Chapter/Others", '2024 -2025-2026'!$G:$G,"2023") -> 0 | H309: =COUNTIFS('2024 -2025-2026'!$M:$M,B309,'2024 -2025-2026'!$K:$K,"Student Publication",'2024 -2025-2026'!$G:$G,"2023") -> 0 | I309: =COUNTIFS('2024 -2025-2026'!$M:$M,B309,'2024 -2025-2026'!$K:$K,"Book",'2024 -2025-2026'!$G:$G,"2023") -> 0 | J309: =SUM(E309:H309) -> 0
A310: 309 | E310: =COUNTIFS('2024 -2025-2026'!$M:$M,B310,'2024 -2025-2026'!$K:$K,"SCI",'2024 -2025-2026'!$G:$G,"2023") -> 0 | F310: =COUNTIFS('2024 -2025-2026'!$M:$M,B310,'2024 -2025-2026'!$K:$K,"Scopus/WoS Journals",'2024 -2025-2026'!$G:$G,"2023") -> 0 | G310: =COUNTIFS('2024 -2025-2026'!$M:$M,B310,'2024 -2025-2026'!$K:$K,"Scopus/WoS Conference/Book Chapter/Others", '2024 -2025-2026'!$G:$G,"2023") -> 0 | H310: =COUNTIFS('2024 -2025-2026'!$M:$M,B310,'2024 -2025-2026'!$K:$K,"Student Publication",'2024 -2025-2026'!$G:$G,"2023") -> 0 | I310: =COUNTIFS('2024 -2025-2026'!$M:$M,B310,'2024 -2025-2026'!$K:$K,"Book",'2024 -2025-2026'!$G:$G,"2023") -> 0 | J310: =SUM(E310:H310) -> 0
A311: 310 | E311: =COUNTIFS('2024 -2025-2026'!$M:$M,B311,'2024 -2025-2026'!$K:$K,"SCI",'2024 -2025-2026'!$G:$G,"2023") -> 0 | F311: =COUNTIFS('2024 -2025-2026'!$M:$M,B311,'2024 -2025-2026'!$K:$K,"Scopus/WoS Journals",'2024 -2025-2026'!$G:$G,"2023") -> 0 | G311: =COUNTIFS('2024 -2025-2026'!$M:$M,B311,'2024 -2025-2026'!$K:$K,"Scopus/WoS Conference/Book Chapter/Others", '2024 -2025-2026'!$G:$G,"2023") -> 0 | H311: =COUNTIFS('2024 -2025-2026'!$M:$M,B311,'2024 -2025-2026'!$K:$K,"Student Publication",'2024 -2025-2026'!$G:$G,"2023") -> 0 | I311: =COUNTIFS('2024 -2025-2026'!$M:$M,B311,'2024 -2025-2026'!$K:$K,"Book",'2024 -2025-2026'!$G:$G,"2023") -> 0 | J311: =SUM(E311:H311) -> 0
A312: 311 | E312: =COUNTIFS('2024 -2025-2026'!$M:$M,B312,'2024 -2025-2026'!$K:$K,"SCI",'2024 -2025-2026'!$G:$G,"2023") -> 0 | F312: =COUNTIFS('2024 -2025-2026'!$M:$M,B312,'2024 -2025-2026'!$K:$K,"Scopus/WoS Journals",'2024 -2025-2026'!$G:$G,"2023") -> 0 | G312: =COUNTIFS('2024 -2025-2026'!$M:$M,B312,'2024 -2025-2026'!$K:$K,"Scopus/WoS Conference/Book Chapter/Others", '2024 -2025-2026'!$G:$G,"2023") -> 0 | H312: =COUNTIFS('2024 -2025-2026'!$M:$M,B312,'2024 -2025-2026'!$K:$K,"Student Publication",'2024 -2025-2026'!$G:$G,"2023") -> 0 | I312: =COUNTIFS('2024 -2025-2026'!$M:$M,B312,'2024 -2025-2026'!$K:$K,"Book",'2024 -2025-2026'!$G:$G,"2023") -> 0 | J312: =SUM(E312:H312) -> 0
A313: 312 | E313: =COUNTIFS('2024 -2025-2026'!$M:$M,B313,'2024 -2025-2026'!$K:$K,"SCI",'2024 -2025-2026'!$G:$G,"2023") -> 0 | F313: =COUNTIFS('2024 -2025-2026'!$M:$M,B313,'2024 -2025-2026'!$K:$K,"Scopus/WoS Journals",'2024 -2025-2026'!$G:$G,"2023") -> 0 | G313: =COUNTIFS('2024 -2025-2026'!$M:$M,B313,'2024 -2025-2026'!$K:$K,"Scopus/WoS Conference/Book Chapter/Others", '2024 -2025-2026'!$G:$G,"2023") -> 0 | H313: =COUNTIFS('2024 -2025-2026'!$M:$M,B313,'2024 -2025-2026'!$K:$K,"Student Publication",'2024 -2025-2026'!$G:$G,"2023") -> 0 | I313: =COUNTIFS('2024 -2025-2026'!$M:$M,B313,'2024 -2025-2026'!$K:$K,"Book",'2024 -2025-2026'!$G:$G,"2023") -> 0 | J313: =SUM(E313:H313) -> 0
A314: 313 | E314: =COUNTIFS('2024 -2025-2026'!$M:$M,B314,'2024 -2025-2026'!$K:$K,"SCI",'2024 -2025-2026'!$G:$G,"2023") -> 0 | F314: =COUNTIFS('2024 -2025-2026'!$M:$M,B314,'2024 -2025-2026'!$K:$K,"Scopus/WoS Journals",'2024 -2025-2026'!$G:$G,"2023") -> 0 | G314: =COUNTIFS('2024 -2025-2026'!$M:$M,B314,'2024 -2025-2026'!$K:$K,"Scopus/WoS Conference/Book Chapter/Others", '2024 -2025-2026'!$G:$G,"2023") -> 0 | H314: =COUNTIFS('2024 -2025-2026'!$M:$M,B314,'2024 -2025-2026'!$K:$K,"Student Publication",'2024 -2025-2026'!$G:$G,"2023") -> 0 | I314: =COUNTIFS('2024 -2025-2026'!$M:$M,B314,'2024 -2025-2026'!$K:$K,"Book",'2024 -2025-2026'!$G:$G,"2023") -> 0 | J314: =SUM(E314:H314) -> 0
A315: 314 | E315: =COUNTIFS('2024 -2025-2026'!$M:$M,B315,'2024 -2025-2026'!$K:$K,"SCI",'2024 -2025-2026'!$G:$G,"2023") -> 0 | F315: =COUNTIFS('2024 -2025-2026'!$M:$M,B315,'2024 -2025-2026'!$K:$K,"Scopus/WoS Journals",'2024 -2025-2026'!$G:$G,"2023") -> 0 | G315: =COUNTIFS('2024 -2025-2026'!$M:$M,B315,'2024 -2025-2026'!$K:$K,"Scopus/WoS Conference/Book Chapter/Others", '2024 -2025-2026'!$G:$G,"2023") -> 0 | H315: =COUNTIFS('2024 -2025-2026'!$M:$M,B315,'2024 -2025-2026'!$K:$K,"Student Publication",'2024 -2025-2026'!$G:$G,"2023") -> 0 | I315: =COUNTIFS('2024 -2025-2026'!$M:$M,B315,'2024 -2025-2026'!$K:$K,"Book",'2024 -2025-2026'!$G:$G,"2023") -> 0 | J315: =SUM(E315:H315) -> 0
A316: 315 | E316: =COUNTIFS('2024 -2025-2026'!$M:$M,B316,'2024 -2025-2026'!$K:$K,"SCI",'2024 -2025-2026'!$G:$G,"2023") -> 0 | F316: =COUNTIFS('2024 -2025-2026'!$M:$M,B316,'2024 -2025-2026'!$K:$K,"Scopus/WoS Journals",'2024 -2025-2026'!$G:$G,"2023") -> 0 | G316: =COUNTIFS('2024 -2025-2026'!$M:$M,B316,'2024 -2025-2026'!$K:$K,"Scopus/WoS Conference/Book Chapter/Others", '2024 -2025-2026'!$G:$G,"2023") -> 0 | H316: =COUNTIFS('2024 -2025-2026'!$M:$M,B316,'2024 -2025-2026'!$K:$K,"Student Publication",'2024 -2025-2026'!$G:$G,"2023") -> 0 | I316: =COUNTIFS('2024 -2025-2026'!$M:$M,B316,'2024 -2025-2026'!$K:$K,"Book",'2024 -2025-2026'!$G:$G,"2023") -> 0 | J316: =SUM(E316:H316) -> 0
A317: 316 | E317: =COUNTIFS('2024 -2025-2026'!$M:$M,B317,'2024 -2025-2026'!$K:$K,"SCI",'2024 -2025-2026'!$G:$G,"2023") -> 0 | F317: =COUNTIFS('2024 -2025-2026'!$M:$M,B317,'2024 -2025-2026'!$K:$K,"Scopus/WoS Journals",'2024 -2025-2026'!$G:$G,"2023") -> 0 | G317: =COUNTIFS('2024 -2025-2026'!$M:$M,B317,'2024 -2025-2026'!$K:$K,"Scopus/WoS Conference/Book Chapter/Others", '2024 -2025-2026'!$G:$G,"2023") -> 0 | H317: =COUNTIFS('2024 -2025-2026'!$M:$M,B317,'2024 -2025-2026'!$K:$K,"Student Publication",'2024 -2025-2026'!$G:$G,"2023") -> 0 | I317: =COUNTIFS('2024 -2025-2026'!$M:$M,B317,'2024 -2025-2026'!$K:$K,"Book",'2024 -2025-2026'!$G:$G,"2023") -> 0 | J317: =SUM(E317:H317) -> 0
A318: 317 | E318: =COUNTIFS('2024 -2025-2026'!$M:$M,B318,'2024 -2025-2026'!$K:$K,"SCI",'2024 -2025-2026'!$G:$G,"2023") -> 0 | F318: =COUNTIFS('2024 -2025-2026'!$M:$M,B318,'2024 -2025-2026'!$K:$K,"Scopus/WoS Journals",'2024 -2025-2026'!$G:$G,"2023") -> 0 | G318: =COUNTIFS('2024 -2025-2026'!$M:$M,B318,'2024 -2025-2026'!$K:$K,"Scopus/WoS Conference/Book Chapter/Others", '2024 -2025-2026'!$G:$G,"2023") -> 0 | H318: =COUNTIFS('2024 -2025-2026'!$M:$M,B318,'2024 -2025-2026'!$K:$K,"Student Publication",'2024 -2025-2026'!$G:$G,"2023") -> 0 | I318: =COUNTIFS('2024 -2025-2026'!$M:$M,B318,'2024 -2025-2026'!$K:$K,"Book",'2024 -2025-2026'!$G:$G,"2023") -> 0 | J318: =SUM(E318:H318) -> 0
A319: 318 | E319: =COUNTIFS('2024 -2025-2026'!$M:$M,B319,'2024 -2025-2026'!$K:$K,"SCI",'2024 -2025-2026'!$G:$G,"2023") -> 0 | F319: =COUNTIFS('2024 -2025-2026'!$M:$M,B319,'2024 -2025-2026'!$K:$K,"Scopus/WoS Journals",'2024 -2025-2026'!$G:$G,"2023") -> 0 | G319: =COUNTIFS('2024 -2025-2026'!$M:$M,B319,'2024 -2025-2026'!$K:$K,"Scopus/WoS Conference/Book Chapter/Others", '2024 -2025-2026'!$G:$G,"2023") -> 0 | H319: =COUNTIFS('2024 -2025-2026'!$M:$M,B319,'2024 -2025-2026'!$K:$K,"Student Publication",'2024 -2025-2026'!$G:$G,"2023") -> 0 | I319: =COUNTIFS('2024 -2025-2026'!$M:$M,B319,'2024 -2025-2026'!$K:$K,"Book",'2024 -2025-2026'!$G:$G,"2023") -> 0 | J319: =SUM(E319:H319) -> 0
A320: 319 | E320: =COUNTIFS('2024 -2025-2026'!$M:$M,B320,'2024 -2025-2026'!$K:$K,"SCI",'2024 -2025-2026'!$G:$G,"2023") -> 0 | F320: =COUNTIFS('2024 -2025-2026'!$M:$M,B320,'2024 -2025-2026'!$K:$K,"Scopus/WoS Journals",'2024 -2025-2026'!$G:$G,"2023") -> 0 | G320: =COUNTIFS('2024 -2025-2026'!$M:$M,B320,'2024 -2025-2026'!$K:$K,"Scopus/WoS Conference/Book Chapter/Others", '2024 -2025-2026'!$G:$G,"2023") -> 0 | H320: =COUNTIFS('2024 -2025-2026'!$M:$M,B320,'2024 -2025-2026'!$K:$K,"Student Publication",'2024 -2025-2026'!$G:$G,"2023") -> 0 | I320: =COUNTIFS('2024 -2025-2026'!$M:$M,B320,'2024 -2025-2026'!$K:$K,"Book",'2024 -2025-2026'!$G:$G,"2023") -> 0 | J320: =SUM(E320:H320) -> 0
A321: 320 | E321: =COUNTIFS('2024 -2025-2026'!$M:$M,B321,'2024 -2025-2026'!$K:$K,"SCI",'2024 -2025-2026'!$G:$G,"2023") -> 0 | F321: =COUNTIFS('2024 -2025-2026'!$M:$M,B321,'2024 -2025-2026'!$K:$K,"Scopus/WoS Journals",'2024 -2025-2026'!$G:$G,"2023") -> 0 | G321: =COUNTIFS('2024 -2025-2026'!$M:$M,B321,'2024 -2025-2026'!$K:$K,"Scopus/WoS Conference/Book Chapter/Others", '2024 -2025-2026'!$G:$G,"2023") -> 0 | H321: =COUNTIFS('2024 -2025-2026'!$M:$M,B321,'2024 -2025-2026'!$K:$K,"Student Publication",'2024 -2025-2026'!$G:$G,"2023") -> 0 | I321: =COUNTIFS('2024 -2025-2026'!$M:$M,B321,'2024 -2025-2026'!$K:$K,"Book",'2024 -2025-2026'!$G:$G,"2023") -> 0 | J321: =SUM(E321:H321) -> 0
... A327: 326 | E327: =COUNTIFS('2024 -2025-2026'!$M:$M,B327,'2024 -2025-2026'!$K:$K,"SCI",'2024 -2025-2026'!$G:$G,"2023") -> 0 | F327: =COUNTIFS('2024 -2025-2026'!$M:$M,B327,'2024 -2025-2026'!$K:$K,"Scopus/WoS Journals",'2024 -2025-2026'!$G:$G,"2023") -> 0 | G327: =COUNTIFS('2024 -2025-2026'!$M:$M,B327,'2024 -2025-2026'!$K:$K,"Scopus/WoS Conference/Book Chapter/Others", '2024 -2025-2026'!$G:$G,"2023") -> 0 | H327: =COUNTIFS('2024 -2025-2026'!$M:$M,B327,'2024 -2025-2026'!$K:$K,"Student Publication",'2024 -2025-2026'!$G:$G,"2023") -> 0 | I327: =COUNTIFS('2024 -2025-2026'!$M:$M,B327,'2024 -2025-2026'!$K:$K,"Book",'2024 -2025-2026'!$G:$G,"2023") -> 0 | J327: =SUM(E327:H327) -> 0
A328: 327 | I328: =COUNTIFS('2024 -2025-2026'!$M:$M,B328,'2024 -2025-2026'!$K:$K,"Book",'2024 -2025-2026'!$G:$G,"2023") -> 0 | J328: =SUM(E328:H328) -> 0
A329: 328 | I329: =COUNTIFS('2024 -2025-2026'!$M:$M,B329,'2024 -2025-2026'!$K:$K,"Book",'2024 -2025-2026'!$G:$G,"2023") -> 0 | J329: =SUM(E329:H329) -> 0
A330: 329 | I330: =COUNTIFS('2024 -2025-2026'!$M:$M,B330,'2024 -2025-2026'!$K:$K,"Book",'2024 -2025-2026'!$G:$G,"2023") -> 0 | J330: =SUM(E330:H330) -> 0
A331: 330 | I331: =COUNTIFS('2024 -2025-2026'!$M:$M,B331,'2024 -2025-2026'!$K:$K,"Book",'2024 -2025-2026'!$G:$G,"2023") -> 0 | J331: =SUM(E331:H331) -> 0
A332: 331 | I332: =COUNTIFS('2024 -2025-2026'!$M:$M,B332,'2024 -2025-2026'!$K:$K,"Book",'2024 -2025-2026'!$G:$G,"2023") -> 0 | J332: =SUM(E332:H332) -> 0
A333: 332 | I333: =COUNTIFS('2024 -2025-2026'!$M:$M,B333,'2024 -2025-2026'!$K:$K,"Book",'2024 -2025-2026'!$G:$G,"2023") -> 0 | J333: =SUM(E333:H333) -> 0
A334: 333 | I334: =COUNTIFS('2024 -2025-2026'!$M:$M,B334,'2024 -2025-2026'!$K:$K,"Book",'2024 -2025-2026'!$G:$G,"2023") -> 0 | J334: =SUM(E334:H334) -> 0
A335: 334 | I335: =COUNTIFS('2024 -2025-2026'!$M:$M,B335,'2024 -2025-2026'!$K:$K,"Book",'2024 -2025-2026'!$G:$G,"2023") -> 0 | J335: =SUM(E335:H335) -> 0
A336: 335 | I336: =COUNTIFS('2024 -2025-2026'!$M:$M,B336,'2024 -2025-2026'!$K:$K,"Book",'2024 -2025-2026'!$G:$G,"2023") -> 0 | J336: =SUM(E336:H336) -> 0
A337: 336 | I337: =COUNTIFS('2024 -2025-2026'!$M:$M,B337,'2024 -2025-2026'!$K:$K,"Book",'2024 -2025-2026'!$G:$G,"2023") -> 0 | J337: =SUM(E337:H337) -> 0
A338: 337 | I338: =COUNTIFS('2024 -2025-2026'!$M:$M,B338,'2024 -2025-2026'!$K:$K,"Book",'2024 -2025-2026'!$G:$G,"2023") -> 0 | J338: =SUM(E338:H338) -> 0
A339: 338 | I339: =COUNTIFS('2024 -2025-2026'!$M:$M,B339,'2024 -2025-2026'!$K:$K,"Book",'2024 -2025-2026'!$G:$G,"2023") -> 0 | J339: =SUM(E339:H339) -> 0
... A372: 371 | I372: =COUNTIFS('2024 -2025-2026'!$M:$M,B372,'2024 -2025-2026'!$K:$K,"Book",'2024 -2025-2026'!$G:$G,"2023") -> 0 | J372: =SUM(E372:H372) -> 0
I373: =COUNTIFS('2024 -2025-2026'!$M:$M,B373,'2024 -2025-2026'!$K:$K,"Book",'2024 -2025-2026'!$G:$G,"2023") -> 0 | J373: =SUM(E373:H373) -> 0
I374: =COUNTIFS('2024 -2025-2026'!$M:$M,B374,'2024 -2025-2026'!$K:$K,"Book",'2024 -2025-2026'!$G:$G,"2023") -> 0 | J374: =SUM(E374:H374) -> 0
I375: =COUNTIFS('2024 -2025-2026'!$M:$M,B375,'2024 -2025-2026'!$K:$K,"Book",'2024 -2025-2026'!$G:$G,"2023") -> 0 | J375: =SUM(E375:H375) -> 0
I376: =COUNTIFS('2024 -2025-2026'!$M:$M,B376,'2024 -2025-2026'!$K:$K,"Book",'2024 -2025-2026'!$G:$G,"2023") -> 0 | J376: =SUM(E376:H376) -> 0
I377: =COUNTIFS('2024 -2025-2026'!$M:$M,B377,'2024 -2025-2026'!$K:$K,"Book",'2024 -2025-2026'!$G:$G,"2023") -> 0 | J377: =SUM(E377:H377) -> 0
I378: =COUNTIFS('2024 -2025-2026'!$M:$M,B378,'2024 -2025-2026'!$K:$K,"Book",'2024 -2025-2026'!$G:$G,"2023") -> 0 | J378: =SUM(E378:H378) -> 0
I379: =COUNTIFS('2024 -2025-2026'!$M:$M,B379,'2024 -2025-2026'!$K:$K,"Book",'2024 -2025-2026'!$G:$G,"2023") -> 0 | J379: =SUM(E379:H379) -> 0
I380: =COUNTIFS('2024 -2025-2026'!$M:$M,B380,'2024 -2025-2026'!$K:$K,"Book",'2024 -2025-2026'!$G:$G,"2023") -> 0 | J380: =SUM(E380:H380) -> 0
I381: =COUNTIFS('2024 -2025-2026'!$M:$M,B381,'2024 -2025-2026'!$K:$K,"Book",'2024 -2025-2026'!$G:$G,"2023") -> 0 | J381: =SUM(E381:H381) -> 0
I382: =COUNTIFS('2024 -2025-2026'!$M:$M,B382,'2024 -2025-2026'!$K:$K,"Book",'2024 -2025-2026'!$G:$G,"2023") -> 0 | J382: =SUM(E382:H382) -> 0
...

Sheet Name of the Faculty 2024
A1: S.No | B1: Name of the Faculty | C1: Dept | D1: SCI - 2024 | E1: Scopus/WoS Journals - 2024 | F1: Scopus/WoS Conference/Book Chapter/Others - 2024 | G1: Student Publication | H1: Total | I1: TOTAL WITHOUT STUDENT pUBLICATION | M1: Combined Department
A2: 1 | B2: Dr. Dinesh Kumar P | C2: AIDS | D2: =COUNTIFS('2024 -2025-2026'!$M:$M,B2,'2024 -2025-2026'!$K:$K,"SCI",'2024 -2025-2026'!$G:$G,"2024") -> 0 | E2: =COUNTIFS('2024 -2025-2026'!$M:$M,B2,'2024 -2025-2026'!$K:$K,"Scopus/WoS Journals",'2024 -2025-2026'!$G:$G,"2024") -> 0 | F2: =COUNTIFS('2024 -2025-2026'!$M:$M,B2,'2024 -2025-2026'!$K:$K,"Scopus/WoS Conference/Book Chapter/Others", '2024 -2025-2026'!$G:$G,"2024") -> 1 | G2: =COUNTIFS('2024 -2025-2026'!$M:$M,B2,'2024 -2025-2026'!$K:$K,"Student Publication",'2024 -2025-2026'!$G:$G,"2024") -> 0 | H2: =SUM(D2:G2) -> 1 | I2: =SUM(D2:F2) -> 1 | J2: SCI | K2: =SUM(D2:D1248) -> 260 | M2: AIDS
A3: 2 | B3: Dr. Geetha M P | C3: AIDS | D3: =COUNTIFS('2024 -2025-2026'!$M:$M,B3,'2024 -2025-2026'!$K:$K,"SCI",'2024 -2025-2026'!$G:$G,"2024") -> 1 | E3: =COUNTIFS('2024 -2025-2026'!$M:$M,B3,'2024 -2025-2026'!$K:$K,"Scopus/WoS Journals",'2024 -2025-2026'!$G:$G,"2024") -> 0 | F3: =COUNTIFS('2024 -2025-2026'!$M:$M,B3,'2024 -2025-2026'!$K:$K,"Scopus/WoS Conference/Book Chapter/Others", '2024 -2025-2026'!$G:$G,"2024") -> 0 | G3: =COUNTIFS('2024 -2025-2026'!$M:$M,B3,'2024 -2025-2026'!$K:$K,"Student Publication",'2024 -2025-2026'!$G:$G,"2024") -> 3 | H3: =SUM(D3:G3) -> 4 | I3: =SUM(D3:F3) -> 1 | J3: Scopus/WoS Journals | K3: =SUM(E:E) -> 44 | M3: AIML
A4: 3 | B4: Dr. Kanimozhi T | C4: AIDS | D4: =COUNTIFS('2024 -2025-2026'!$M:$M,B4,'2024 -2025-2026'!$K:$K,"SCI",'2024 -2025-2026'!$G:$G,"2024") -> 1 | E4: =COUNTIFS('2024 -2025-2026'!$M:$M,B4,'2024 -2025-2026'!$K:$K,"Scopus/WoS Journals",'2024 -2025-2026'!$G:$G,"2024") -> 0 | F4: =COUNTIFS('2024 -2025-2026'!$M:$M,B4,'2024 -2025-2026'!$K:$K,"Scopus/WoS Conference/Book Chapter/Others", '2024 -2025-2026'!$G:$G,"2024") -> 3 | G4: =COUNTIFS('2024 -2025-2026'!$M:$M,B4,'2024 -2025-2026'!$K:$K,"Student Publication",'2024 -2025-2026'!$G:$G,"2024") -> 1 | H4: =SUM(D4:G4) -> 5 | I4: =SUM(D4:F4) -> 4 | J4: Scopus/WoS Conference/Book Chapter/Others | K4: =SUM(F:F) -> 407 | M4: CCE
A5: 4 | B5: Dr. Lakshmi M | C5: AIDS | D5: =COUNTIFS('2024 -2025-2026'!$M:$M,B5,'2024 -2025-2026'!$K:$K,"SCI",'2024 -2025-2026'!$G:$G,"2024") -> 0 | E5: =COUNTIFS('2024 -2025-2026'!$M:$M,B5,'2024 -2025-2026'!$K:$K,"Scopus/WoS Journals",'2024 -2025-2026'!$G:$G,"2024") -> 0 | F5: =COUNTIFS('2024 -2025-2026'!$M:$M,B5,'2024 -2025-2026'!$K:$K,"Scopus/WoS Conference/Book Chapter/Others", '2024 -2025-2026'!$G:$G,"2024") -> 0 | G5: =COUNTIFS('2024 -2025-2026'!$M:$M,B5,'2024 -2025-2026'!$K:$K,"Student Publication",'2024 -2025-2026'!$G:$G,"2024") -> 0 | H5: =SUM(D5:G5) -> 0 | I5: =SUM(D5:F5) -> 0 | J5: Student Publication | K5: =SUM(G:G) -> 251 | M5: CSBS
A6: 5 | B6: Dr. Mohammed Mustafa M | C6: AIDS | D6: =COUNTIFS('2024 -2025-2026'!$M:$M,B6,'2024 -2025-2026'!$K:$K,"SCI",'2024 -2025-2026'!$G:$G,"2024") -> 0 | E6: =COUNTIFS('2024 -2025-2026'!$M:$M,B6,'2024 -2025-2026'!$K:$K,"Scopus/WoS Journals",'2024 -2025-2026'!$G:$G,"2024") -> 0 | F6: =COUNTIFS('2024 -2025-2026'!$M:$M,B6,'2024 -2025-2026'!$K:$K,"Scopus/WoS Conference/Book Chapter/Others", '2024 -2025-2026'!$G:$G,"2024") -> 0 | G6: =COUNTIFS('2024 -2025-2026'!$M:$M,B6,'2024 -2025-2026'!$K:$K,"Student Publication",'2024 -2025-2026'!$G:$G,"2024") -> 1 | H6: =SUM(D6:G6) -> 1 | I6: =SUM(D6:F6) -> 0 | J6: Total | K6: =SUM(K2:K5) -> 962 | M6: CSE
A7: 6 | B7: Dr. Nivaashini M | C7: AIDS | D7: =COUNTIFS('2024 -2025-2026'!$M:$M,B7,'2024 -2025-2026'!$K:$K,"SCI",'2024 -2025-2026'!$G:$G,"2024") -> 1 | E7: =COUNTIFS('2024 -2025-2026'!$M:$M,B7,'2024 -2025-2026'!$K:$K,"Scopus/WoS Journals",'2024 -2025-2026'!$G:$G,"2024") -> 0 | F7: =COUNTIFS('2024 -2025-2026'!$M:$M,B7,'2024 -2025-2026'!$K:$K,"Scopus/WoS Conference/Book Chapter/Others", '2024 -2025-2026'!$G:$G,"2024") -> 5 | G7: =COUNTIFS('2024 -2025-2026'!$M:$M,B7,'2024 -2025-2026'!$K:$K,"Student Publication",'2024 -2025-2026'!$G:$G,"2024") -> 2 | H7: =SUM(D7:G7) -> 8 | I7: =SUM(D7:F7) -> 6 | M7: ECE
A8: 7 | B8: Dr. Sathish Kumar G | C8: AIDS | D8: =COUNTIFS('2024 -2025-2026'!$M:$M,B8,'2024 -2025-2026'!$K:$K,"SCI",'2024 -2025-2026'!$G:$G,"2024") -> 4 | E8: =COUNTIFS('2024 -2025-2026'!$M:$M,B8,'2024 -2025-2026'!$K:$K,"Scopus/WoS Journals",'2024 -2025-2026'!$G:$G,"2024") -> 0 | F8: =COUNTIFS('2024 -2025-2026'!$M:$M,B8,'2024 -2025-2026'!$K:$K,"Scopus/WoS Conference/Book Chapter/Others", '2024 -2025-2026'!$G:$G,"2024") -> 0 | G8: =COUNTIFS('2024 -2025-2026'!$M:$M,B8,'2024 -2025-2026'!$K:$K,"Student Publication",'2024 -2025-2026'!$G:$G,"2024") -> 1 | H8: =SUM(D8:G8) -> 5 | I8: =SUM(D8:F8) -> 4 | M8: MECH
A9: 8 | B9: Dr. Thenmozhi M | C9: AIDS | D9: =COUNTIFS('2024 -2025-2026'!$M:$M,B9,'2024 -2025-2026'!$K:$K,"SCI",'2024 -2025-2026'!$G:$G,"2024") -> 0 | E9: =COUNTIFS('2024 -2025-2026'!$M:$M,B9,'2024 -2025-2026'!$K:$K,"Scopus/WoS Journals",'2024 -2025-2026'!$G:$G,"2024") -> 0 | F9: =COUNTIFS('2024 -2025-2026'!$M:$M,B9,'2024 -2025-2026'!$K:$K,"Scopus/WoS Conference/Book Chapter/Others", '2024 -2025-2026'!$G:$G,"2024") -> 4 | G9: =COUNTIFS('2024 -2025-2026'!$M:$M,B9,'2024 -2025-2026'!$K:$K,"Student Publication",'2024 -2025-2026'!$G:$G,"2024") -> 5 | H9: =SUM(D9:G9) -> 9 | I9: =SUM(D9:F9) -> 4 | M9: EEE
A10: 9 | B10: Dr. Vimal S | C10: AIDS | D10: =COUNTIFS('2024 -2025-2026'!$M:$M,B10,'2024 -2025-2026'!$K:$K,"SCI",'2024 -2025-2026'!$G:$G,"2024") -> 0 | E10: =COUNTIFS('2024 -2025-2026'!$M:$M,B10,'2024 -2025-2026'!$K:$K,"Scopus/WoS Journals",'2024 -2025-2026'!$G:$G,"2024") -> 0 | F10: =COUNTIFS('2024 -2025-2026'!$M:$M,B10,'2024 -2025-2026'!$K:$K,"Scopus/WoS Conference/Book Chapter/Others", '2024 -2025-2026'!$G:$G,"2024") -> 0 | G10: =COUNTIFS('2024 -2025-2026'!$M:$M,B10,'2024 -2025-2026'!$K:$K,"Student Publication",'2024 -2025-2026'!$G:$G,"2024") -> 0 | H10: =SUM(D10:G10) -> 0 | I10: =SUM(D10:F10) -> 0 | M10: IT
A11: 10 | B11: Mr. Sridharan S | C11: AIDS | D11: =COUNTIFS('2024 -2025-2026'!$M:$M,B11,'2024 -2025-2026'!$K:$K,"SCI",'2024 -2025-2026'!$G:$G,"2024") -> 0 | E11: =COUNTIFS('2024 -2025-2026'!$M:$M,B11,'2024 -2025-2026'!$K:$K,"Scopus/WoS Journals",'2024 -2025-2026'!$G:$G,"2024") -> 0 | F11: =COUNTIFS('2024 -2025-2026'!$M:$M,B11,'2024 -2025-2026'!$K:$K,"Scopus/WoS Conference/Book Chapter/Others", '2024 -2025-2026'!$G:$G,"2024") -> 0 | G11: =COUNTIFS('2024 -2025-2026'!$M:$M,B11,'2024 -2025-2026'!$K:$K,"Student Publication",'2024 -2025-2026'!$G:$G,"2024") -> 0 | H11: =SUM(D11:G11) -> 0 | I11: =SUM(D11:F11) -> 0 | M11: S&H (Eng)
A12: 11 | B12: Ms. Anitha E | C12: AIDS | D12: =COUNTIFS('2024 -2025-2026'!$M:$M,B12,'2024 -2025-2026'!$K:$K,"SCI",'2024 -2025-2026'!$G:$G,"2024") -> 0 | E12: =COUNTIFS('2024 -2025-2026'!$M:$M,B12,'2024 -2025-2026'!$K:$K,"Scopus/WoS Journals",'2024 -2025-2026'!$G:$G,"2024") -> 0 | F12: =COUNTIFS('2024 -2025-2026'!$M:$M,B12,'2024 -2025-2026'!$K:$K,"Scopus/WoS Conference/Book Chapter/Others", '2024 -2025-2026'!$G:$G,"2024") -> 0 | G12: =COUNTIFS('2024 -2025-2026'!$M:$M,B12,'2024 -2025-2026'!$K:$K,"Student Publication",'2024 -2025-2026'!$G:$G,"2024") -> 0 | H12: =SUM(D12:G12) -> 0 | I12: =SUM(D12:F12) -> 0 | M12: CSE, IT, CCE
A13: 12 | B13: Ms. Divyaprabha R | C13: AIDS | D13: =COUNTIFS('2024 -2025-2026'!$M:$M,B13,'2024 -2025-2026'!$K:$K,"SCI",'2024 -2025-2026'!$G:$G,"2024") -> 0 | E13: =COUNTIFS('2024 -2025-2026'!$M:$M,B13,'2024 -2025-2026'!$K:$K,"Scopus/WoS Journals",'2024 -2025-2026'!$G:$G,"2024") -> 0 | F13: =COUNTIFS('2024 -2025-2026'!$M:$M,B13,'2024 -2025-2026'!$K:$K,"Scopus/WoS Conference/Book Chapter/Others", '2024 -2025-2026'!$G:$G,"2024") -> 0 | G13: =COUNTIFS('2024 -2025-2026'!$M:$M,B13,'2024 -2025-2026'!$K:$K,"Student Publication",'2024 -2025-2026'!$G:$G,"2024") -> 0 | H13: =SUM(D13:G13) -> 0 | I13: =SUM(D13:F13) -> 0 | M13: MECH, S&H (Eng)
A14: 13 | B14: Ms. Esther Pushpam | C14: AIDS | D14: =COUNTIFS('2024 -2025-2026'!$M:$M,B14,'2024 -2025-2026'!$K:$K,"SCI",'2024 -2025-2026'!$G:$G,"2024") -> 0 | E14: =COUNTIFS('2024 -2025-2026'!$M:$M,B14,'2024 -2025-2026'!$K:$K,"Scopus/WoS Journals",'2024 -2025-2026'!$G:$G,"2024") -> 0 | F14: =COUNTIFS('2024 -2025-2026'!$M:$M,B14,'2024 -2025-2026'!$K:$K,"Scopus/WoS Conference/Book Chapter/Others", '2024 -2025-2026'!$G:$G,"2024") -> 0 | G14: =COUNTIFS('2024 -2025-2026'!$M:$M,B14,'2024 -2025-2026'!$K:$K,"Student Publication",'2024 -2025-2026'!$G:$G,"2024") -> 0 | H14: =SUM(D14:G14) -> 0 | I14: =SUM(D14:F14) -> 0 | M14: S&H (Che)
A15: 14 | B15: Ms. Geetha Rajakumari R | C15: AIDS | D15: =COUNTIFS('2024 -2025-2026'!$M:$M,B15,'2024 -2025-2026'!$K:$K,"SCI",'2024 -2025-2026'!$G:$G,"2024") -> 0 | E15: =COUNTIFS('2024 -2025-2026'!$M:$M,B15,'2024 -2025-2026'!$K:$K,"Scopus/WoS Journals",'2024 -2025-2026'!$G:$G,"2024") -> 0 | F15: =COUNTIFS('2024 -2025-2026'!$M:$M,B15,'2024 -2025-2026'!$K:$K,"Scopus/WoS Conference/Book Chapter/Others", '2024 -2025-2026'!$G:$G,"2024") -> 2 | G15: =COUNTIFS('2024 -2025-2026'!$M:$M,B15,'2024 -2025-2026'!$K:$K,"Student Publication",'2024 -2025-2026'!$G:$G,"2024") -> 1 | H15: =SUM(D15:G15) -> 3 | I15: =SUM(D15:F15) -> 2 | M15: S&H (Maths)
A16: 15 | B16: Ms. Gowri S | C16: AIDS | D16: =COUNTIFS('2024 -2025-2026'!$M:$M,B16,'2024 -2025-2026'!$K:$K,"SCI",'2024 -2025-2026'!$G:$G,"2024") -> 0 | E16: =COUNTIFS('2024 -2025-2026'!$M:$M,B16,'2024 -2025-2026'!$K:$K,"Scopus/WoS Journals",'2024 -2025-2026'!$G:$G,"2024") -> 0 | F16: =COUNTIFS('2024 -2025-2026'!$M:$M,B16,'2024 -2025-2026'!$K:$K,"Scopus/WoS Conference/Book Chapter/Others", '2024 -2025-2026'!$G:$G,"2024") -> 0 | G16: =COUNTIFS('2024 -2025-2026'!$M:$M,B16,'2024 -2025-2026'!$K:$K,"Student Publication",'2024 -2025-2026'!$G:$G,"2024") -> 0 | H16: =SUM(D16:G16) -> 0 | I16: =SUM(D16:F16) -> 0 | M16: S&H (Phy)
A17: 16 | B17: Ms. Parvathy K | C17: AIDS | D17: =COUNTIFS('2024 -2025-2026'!$M:$M,B17,'2024 -2025-2026'!$K:$K,"SCI",'2024 -2025-2026'!$G:$G,"2024") -> 0 | E17: =COUNTIFS('2024 -2025-2026'!$M:$M,B17,'2024 -2025-2026'!$K:$K,"Scopus/WoS Journals",'2024 -2025-2026'!$G:$G,"2024") -> 0 | F17: =COUNTIFS('2024 -2025-2026'!$M:$M,B17,'2024 -2025-2026'!$K:$K,"Scopus/WoS Conference/Book Chapter/Others", '2024 -2025-2026'!$G:$G,"2024") -> 1 | G17: =COUNTIFS('2024 -2025-2026'!$M:$M,B17,'2024 -2025-2026'!$K:$K,"Student Publication",'2024 -2025-2026'!$G:$G,"2024") -> 0 | H17: =SUM(D17:G17) -> 1 | I17: =SUM(D17:F17) -> 1 | M17: Student Publication AIDS
A18: 17 | B18: Ms. Rajalakshmi S | C18: AIDS | D18: =COUNTIFS('2024 -2025-2026'!$M:$M,B18,'2024 -2025-2026'!$K:$K,"SCI",'2024 -2025-2026'!$G:$G,"2024") -> 0 | E18: =COUNTIFS('2024 -2025-2026'!$M:$M,B18,'2024 -2025-2026'!$K:$K,"Scopus/WoS Journals",'2024 -2025-2026'!$G:$G,"2024") -> 0 | F18: =COUNTIFS('2024 -2025-2026'!$M:$M,B18,'2024 -2025-2026'!$K:$K,"Scopus/WoS Conference/Book Chapter/Others", '2024 -2025-2026'!$G:$G,"2024") -> 0 | G18: =COUNTIFS('2024 -2025-2026'!$M:$M,B18,'2024 -2025-2026'!$K:$K,"Student Publication",'2024 -2025-2026'!$G:$G,"2024") -> 0 | H18: =SUM(D18:G18) -> 0 | I18: =SUM(D18:F18) -> 0 | M18: Student Publication CCE
... A26: 25 | B26: Dr. Kathiresan K | C26: AIML | D26: =COUNTIFS('2024 -2025-2026'!$M:$M,B26,'2024 -2025-2026'!$K:$K,"SCI",'2024 -2025-2026'!$G:$G,"2024") -> 1 | E26: =COUNTIFS('2024 -2025-2026'!$M:$M,B26,'2024 -2025-2026'!$K:$K,"Scopus/WoS Journals",'2024 -2025-2026'!$G:$G,"2024") -> 0 | F26: =COUNTIFS('2024 -2025-2026'!$M:$M,B26,'2024 -2025-2026'!$K:$K,"Scopus/WoS Conference/Book Chapter/Others", '2024 -2025-2026'!$G:$G,"2024") -> 1 | G26: =COUNTIFS('2024 -2025-2026'!$M:$M,B26,'2024 -2025-2026'!$K:$K,"Student Publication",'2024 -2025-2026'!$G:$G,"2024") -> 0 | H26: =SUM(D26:G26) -> 2 | I26: =SUM(D26:F26) -> 2 | M26: Student Publication AIML
A27: 26 | B27: Ms. Preethi P | C27: AIML | D27: =COUNTIFS('2024 -2025-2026'!$M:$M,B27,'2024 -2025-2026'!$K:$K,"SCI",'2024 -2025-2026'!$G:$G,"2024") -> 1 | E27: =COUNTIFS('2024 -2025-2026'!$M:$M,B27,'2024 -2025-2026'!$K:$K,"Scopus/WoS Journals",'2024 -2025-2026'!$G:$G,"2024") -> 0 | F27: =COUNTIFS('2024 -2025-2026'!$M:$M,B27,'2024 -2025-2026'!$K:$K,"Scopus/WoS Conference/Book Chapter/Others", '2024 -2025-2026'!$G:$G,"2024") -> 0 | G27: =COUNTIFS('2024 -2025-2026'!$M:$M,B27,'2024 -2025-2026'!$K:$K,"Student Publication",'2024 -2025-2026'!$G:$G,"2024") -> 1 | H27: =SUM(D27:G27) -> 2 | I27: =SUM(D27:F27) -> 1
A28: 27 | B28: Ms. Sindhuja S | C28: AIML | D28: =COUNTIFS('2024 -2025-2026'!$M:$M,B28,'2024 -2025-2026'!$K:$K,"SCI",'2024 -2025-2026'!$G:$G,"2024") -> 0 | E28: =COUNTIFS('2024 -2025-2026'!$M:$M,B28,'2024 -2025-2026'!$K:$K,"Scopus/WoS Journals",'2024 -2025-2026'!$G:$G,"2024") -> 0 | F28: =COUNTIFS('2024 -2025-2026'!$M:$M,B28,'2024 -2025-2026'!$K:$K,"Scopus/WoS Conference/Book Chapter/Others", '2024 -2025-2026'!$G:$G,"2024") -> 2 | G28: =COUNTIFS('2024 -2025-2026'!$M:$M,B28,'2024 -2025-2026'!$K:$K,"Student Publication",'2024 -2025-2026'!$G:$G,"2024") -> 0 | H28: =SUM(D28:G28) -> 2 | I28: =SUM(D28:F28) -> 2
A29: 28 | B29: Ms. Kalaivani T | C29: AIML | D29: =COUNTIFS('2024 -2025-2026'!$M:$M,B29,'2024 -2025-2026'!$K:$K,"SCI",'2024 -2025-2026'!$G:$G,"2024") -> 0 | E29: =COUNTIFS('2024 -2025-2026'!$M:$M,B29,'2024 -2025-2026'!$K:$K,"Scopus/WoS Journals",'2024 -2025-2026'!$G:$G,"2024") -> 0 | F29: =COUNTIFS('2024 -2025-2026'!$M:$M,B29,'2024 -2025-2026'!$K:$K,"Scopus/WoS Conference/Book Chapter/Others", '2024 -2025-2026'!$G:$G,"2024") -> 0 | G29: =COUNTIFS('2024 -2025-2026'!$M:$M,B29,'2024 -2025-2026'!$K:$K,"Student Publication",'2024 -2025-2026'!$G:$G,"2024") -> 0 | H29: =SUM(D29:G29) -> 0 | I29: =SUM(D29:F29) -> 0
A30: 29 | B30: Ms. Charanya P | C30: AIML | D30: =COUNTIFS('2024 -2025-2026'!$M:$M,B30,'2024 -2025-2026'!$K:$K,"SCI",'2024 -2025-2026'!$G:$G,"2024") -> 0 | E30: =COUNTIFS('2024 -2025-2026'!$M:$M,B30,'2024 -2025-2026'!$K:$K,"Scopus/WoS Journals",'2024 -2025-2026'!$G:$G,"2024") -> 0 | F30: =COUNTIFS('2024 -2025-2026'!$M:$M,B30,'2024 -2025-2026'!$K:$K,"Scopus/WoS Conference/Book Chapter/Others", '2024 -2025-2026'!$G:$G,"2024") -> 0 | G30: =COUNTIFS('2024 -2025-2026'!$M:$M,B30,'2024 -2025-2026'!$K:$K,"Student Publication",'2024 -2025-2026'!$G:$G,"2024") -> 1 | H30: =SUM(D30:G30) -> 1 | I30: =SUM(D30:F30) -> 0
A31: 30 | B31: Dr. Babitha Lincy R | C31: CCE | D31: =COUNTIFS('2024 -2025-2026'!$M:$M,B31,'2024 -2025-2026'!$K:$K,"SCI",'2024 -2025-2026'!$G:$G,"2024") -> 5 | E31: =COUNTIFS('2024 -2025-2026'!$M:$M,B31,'2024 -2025-2026'!$K:$K,"Scopus/WoS Journals",'2024 -2025-2026'!$G:$G,"2024") -> 0 | F31: =COUNTIFS('2024 -2025-2026'!$M:$M,B31,'2024 -2025-2026'!$K:$K,"Scopus/WoS Conference/Book Chapter/Others", '2024 -2025-2026'!$G:$G,"2024") -> 5 | G31: =COUNTIFS('2024 -2025-2026'!$M:$M,B31,'2024 -2025-2026'!$K:$K,"Student Publication",'2024 -2025-2026'!$G:$G,"2024") -> 2 | H31: =SUM(D31:G31) -> 12 | I31: =SUM(D31:F31) -> 10
A32: 31 | B32: Dr. Dhamodharan S | C32: CCE | D32: =COUNTIFS('2024 -2025-2026'!$M:$M,B32,'2024 -2025-2026'!$K:$K,"SCI",'2024 -2025-2026'!$G:$G,"2024") -> 1 | E32: =COUNTIFS('2024 -2025-2026'!$M:$M,B32,'2024 -2025-2026'!$K:$K,"Scopus/WoS Journals",'2024 -2025-2026'!$G:$G,"2024") -> 0 | F32: =COUNTIFS('2024 -2025-2026'!$M:$M,B32,'2024 -2025-2026'!$K:$K,"Scopus/WoS Conference/Book Chapter/Others", '2024 -2025-2026'!$G:$G,"2024") -> 3 | G32: =COUNTIFS('2024 -2025-2026'!$M:$M,B32,'2024 -2025-2026'!$K:$K,"Student Publication",'2024 -2025-2026'!$G:$G,"2024") -> 1 | H32: =SUM(D32:G32) -> 5 | I32: =SUM(D32:F32) -> 4
A33: 32 | B33: Dr. Ganesh C | C33: CCE | D33: =COUNTIFS('2024 -2025-2026'!$M:$M,B33,'2024 -2025-2026'!$K:$K,"SCI",'2024 -2025-2026'!$G:$G,"2024") -> 1 | E33: =COUNTIFS('2024 -2025-2026'!$M:$M,B33,'2024 -2025-2026'!$K:$K,"Scopus/WoS Journals",'2024 -2025-2026'!$G:$G,"2024") -> 0 | F33: =COUNTIFS('2024 -2025-2026'!$M:$M,B33,'2024 -2025-2026'!$K:$K,"Scopus/WoS Conference/Book Chapter/Others", '2024 -2025-2026'!$G:$G,"2024") -> 1 | G33: =COUNTIFS('2024 -2025-2026'!$M:$M,B33,'2024 -2025-2026'!$K:$K,"Student Publication",'2024 -2025-2026'!$G:$G,"2024") -> 1 | H33: =SUM(D33:G33) -> 3 | I33: =SUM(D33:F33) -> 2
A34: 33 | B34: Dr. Thirrunavukkarasu R R | C34: CCE | D34: =COUNTIFS('2024 -2025-2026'!$M:$M,B34,'2024 -2025-2026'!$K:$K,"SCI",'2024 -2025-2026'!$G:$G,"2024") -> 0 | E34: =COUNTIFS('2024 -2025-2026'!$M:$M,B34,'2024 -2025-2026'!$K:$K,"Scopus/WoS Journals",'2024 -2025-2026'!$G:$G,"2024") -> 0 | F34: =COUNTIFS('2024 -2025-2026'!$M:$M,B34,'2024 -2025-2026'!$K:$K,"Scopus/WoS Conference/Book Chapter/Others", '2024 -2025-2026'!$G:$G,"2024") -> 1 | G34: =COUNTIFS('2024 -2025-2026'!$M:$M,B34,'2024 -2025-2026'!$K:$K,"Student Publication",'2024 -2025-2026'!$G:$G,"2024") -> 0 | H34: =SUM(D34:G34) -> 1 | I34: =SUM(D34:F34) -> 1
A35: 34 | B35: Dr. Vivek C | C35: CCE | D35: =COUNTIFS('2024 -2025-2026'!$M:$M,B35,'2024 -2025-2026'!$K:$K,"SCI",'2024 -2025-2026'!$G:$G,"2024") -> 3 | E35: =COUNTIFS('2024 -2025-2026'!$M:$M,B35,'2024 -2025-2026'!$K:$K,"Scopus/WoS Journals",'2024 -2025-2026'!$G:$G,"2024") -> 0 | F35: =COUNTIFS('2024 -2025-2026'!$M:$M,B35,'2024 -2025-2026'!$K:$K,"Scopus/WoS Conference/Book Chapter/Others", '2024 -2025-2026'!$G:$G,"2024") -> 0 | G35: =COUNTIFS('2024 -2025-2026'!$M:$M,B35,'2024 -2025-2026'!$K:$K,"Student Publication",'2024 -2025-2026'!$G:$G,"2024") -> 1 | H35: =SUM(D35:G35) -> 4 | I35: =SUM(D35:F35) -> 3
A36: 35 | B36: Mr. Arun R | C36: CCE | D36: =COUNTIFS('2024 -2025-2026'!$M:$M,B36,'2024 -2025-2026'!$K:$K,"SCI",'2024 -2025-2026'!$G:$G,"2024") -> 0 | E36: =COUNTIFS('2024 -2025-2026'!$M:$M,B36,'2024 -2025-2026'!$K:$K,"Scopus/WoS Journals",'2024 -2025-2026'!$G:$G,"2024") -> 0 | F36: =COUNTIFS('2024 -2025-2026'!$M:$M,B36,'2024 -2025-2026'!$K:$K,"Scopus/WoS Conference/Book Chapter/Others", '2024 -2025-2026'!$G:$G,"2024") -> 1 | G36: =COUNTIFS('2024 -2025-2026'!$M:$M,B36,'2024 -2025-2026'!$K:$K,"Student Publication",'2024 -2025-2026'!$G:$G,"2024") -> 1 | H36: =SUM(D36:G36) -> 2 | I36: =SUM(D36:F36) -> 1
A37: 36 | B37: Ms. Banu Priya N | C37: CCE | D37: =COUNTIFS('2024 -2025-2026'!$M:$M,B37,'2024 -2025-2026'!$K:$K,"SCI",'2024 -2025-2026'!$G:$G,"2024") -> 0 | E37: =COUNTIFS('2024 -2025-2026'!$M:$M,B37,'2024 -2025-2026'!$K:$K,"Scopus/WoS Journals",'2024 -2025-2026'!$G:$G,"2024") -> 0 | F37: =COUNTIFS('2024 -2025-2026'!$M:$M,B37,'2024 -2025-2026'!$K:$K,"Scopus/WoS Conference/Book Chapter/Others", '2024 -2025-2026'!$G:$G,"2024") -> 1 | G37: =COUNTIFS('2024 -2025-2026'!$M:$M,B37,'2024 -2025-2026'!$K:$K,"Student Publication",'2024 -2025-2026'!$G:$G,"2024") -> 1 | H37: =SUM(D37:G37) -> 2 | I37: =SUM(D37:F37) -> 1
A38: 37 | B38: Ms. Dency Flora G | C38: CCE | D38: =COUNTIFS('2024 -2025-2026'!$M:$M,B38,'2024 -2025-2026'!$K:$K,"SCI",'2024 -2025-2026'!$G:$G,"2024") -> 0 | E38: =COUNTIFS('2024 -2025-2026'!$M:$M,B38,'2024 -2025-2026'!$K:$K,"Scopus/WoS Journals",'2024 -2025-2026'!$G:$G,"2024") -> 0 | F38: =COUNTIFS('2024 -2025-2026'!$M:$M,B38,'2024 -2025-2026'!$K:$K,"Scopus/WoS Conference/Book Chapter/Others", '2024 -2025-2026'!$G:$G,"2024") -> 0 | G38: =COUNTIFS('2024 -2025-2026'!$M:$M,B38,'2024 -2025-2026'!$K:$K,"Student Publication",'2024 -2025-2026'!$G:$G,"2024") -> 1 | H38: =SUM(D38:G38) -> 1 | I38: =SUM(D38:F38) -> 0
... A248: 247 | B248: Student Publication Mech | C248: SP Mech | D248: =COUNTIFS('2024 -2025-2026'!$M:$M,B248,'2024 -2025-2026'!$K:$K,"SCI",'2024 -2025-2026'!$G:$G,"2024") -> 0 | E248: =COUNTIFS('2024 -2025-2026'!$M:$M,B248,'2024 -2025-2026'!$K:$K,"Scopus/WoS Journals",'2024 -2025-2026'!$G:$G,"2024") -> 0 | F248: =COUNTIFS('2024 -2025-2026'!$M:$M,B248,'2024 -2025-2026'!$K:$K,"Scopus/WoS Conference/Book Chapter/Others", '2024 -2025-2026'!$G:$G,"2024") -> 0 | G248: =COUNTIFS('2024 -2025-2026'!$M:$M,B248,'2024 -2025-2026'!$K:$K,"Student Publication",'2024 -2025-2026'!$G:$G,"2024") -> 1 | H248: =SUM(D248:G248) -> 1 | I248: =SUM(D248:F248) -> 0
A249: 248 | B249: Student Publication AIML | D249: =COUNTIFS('2024 -2025-2026'!$M:$M,B249,'2024 -2025-2026'!$K:$K,"SCI",'2024 -2025-2026'!$G:$G,"2024") -> 0 | E249: =COUNTIFS('2024 -2025-2026'!$M:$M,B249,'2024 -2025-2026'!$K:$K,"Scopus/WoS Journals",'2024 -2025-2026'!$G:$G,"2024") -> 0 | F249: =COUNTIFS('2024 -2025-2026'!$M:$M,B249,'2024 -2025-2026'!$K:$K,"Scopus/WoS Conference/Book Chapter/Others", '2024 -2025-2026'!$G:$G,"2024") -> 0 | G249: =COUNTIFS('2024 -2025-2026'!$M:$M,B249,'2024 -2025-2026'!$K:$K,"Student Publication",'2024 -2025-2026'!$G:$G,"2024") -> 0 | H249: =SUM(D249:G249) -> 0 | I249: =SUM(D249:F249) -> 0
A250: 249 | B250: Others CSE | C250: CSE | D250: =COUNTIFS('2024 -2025-2026'!$M:$M,B250,'2024 -2025-2026'!$K:$K,"SCI",'2024 -2025-2026'!$G:$G,"2024") -> 0 | E250: =COUNTIFS('2024 -2025-2026'!$M:$M,B250,'2024 -2025-2026'!$K:$K,"Scopus/WoS Journals",'2024 -2025-2026'!$G:$G,"2024") -> 0 | F250: =COUNTIFS('2024 -2025-2026'!$M:$M,B250,'2024 -2025-2026'!$K:$K,"Scopus/WoS Conference/Book Chapter/Others", '2024 -2025-2026'!$G:$G,"2024") -> 1 | G250: =COUNTIFS('2024 -2025-2026'!$M:$M,B250,'2024 -2025-2026'!$K:$K,"Student Publication",'2024 -2025-2026'!$G:$G,"2024") -> 3 | H250: =SUM(D250:G250) -> 4 | I250: =SUM(D250:F250) -> 1
A251: 250 | B251: Others AIDS | C251: AIDS | D251: =COUNTIFS('2024 -2025-2026'!$M:$M,B251,'2024 -2025-2026'!$K:$K,"SCI",'2024 -2025-2026'!$G:$G,"2024") -> 7 | E251: =COUNTIFS('2024 -2025-2026'!$M:$M,B251,'2024 -2025-2026'!$K:$K,"Scopus/WoS Journals",'2024 -2025-2026'!$G:$G,"2024") -> 0 | F251: =COUNTIFS('2024 -2025-2026'!$M:$M,B251,'2024 -2025-2026'!$K:$K,"Scopus/WoS Conference/Book Chapter/Others", '2024 -2025-2026'!$G:$G,"2024") -> 2 | G251: =COUNTIFS('2024 -2025-2026'!$M:$M,B251,'2024 -2025-2026'!$K:$K,"Student Publication",'2024 -2025-2026'!$G:$G,"2024") -> 1 | H251: =SUM(D251:G251) -> 10 | I251: =SUM(D251:F251) -> 9
A252: 251 | B252: Others CCE | C252: CCE | D252: =COUNTIFS('2024 -2025-2026'!$M:$M,B252,'2024 -2025-2026'!$K:$K,"SCI",'2024 -2025-2026'!$G:$G,"2024") -> 0 | E252: =COUNTIFS('2024 -2025-2026'!$M:$M,B252,'2024 -2025-2026'!$K:$K,"Scopus/WoS Journals",'2024 -2025-2026'!$G:$G,"2024") -> 0 | F252: =COUNTIFS('2024 -2025-2026'!$M:$M,B252,'2024 -2025-2026'!$K:$K,"Scopus/WoS Conference/Book Chapter/Others", '2024 -2025-2026'!$G:$G,"2024") -> 0 | G252: =COUNTIFS('2024 -2025-2026'!$M:$M,B252,'2024 -2025-2026'!$K:$K,"Student Publication",'2024 -2025-2026'!$G:$G,"2024") -> 0 | H252: =SUM(D252:G252) -> 0 | I252: =SUM(D252:F252) -> 0
A253: 252 | B253: Others EEE | C253: EEE | D253: =COUNTIFS('2024 -2025-2026'!$M:$M,B253,'2024 -2025-2026'!$K:$K,"SCI",'2024 -2025-2026'!$G:$G,"2024") -> 0 | E253: =COUNTIFS('2024 -2025-2026'!$M:$M,B253,'2024 -2025-2026'!$K:$K,"Scopus/WoS Journals",'2024 -2025-2026'!$G:$G,"2024") -> 0 | F253: =COUNTIFS('2024 -2025-2026'!$M:$M,B253,'2024 -2025-2026'!$K:$K,"Scopus/WoS Conference/Book Chapter/Others", '2024 -2025-2026'!$G:$G,"2024") -> 0 | G253: =COUNTIFS('2024 -2025-2026'!$M:$M,B253,'2024 -2025-2026'!$K:$K,"Student Publication",'2024 -2025-2026'!$G:$G,"2024") -> 0 | H253: =SUM(D253:G253) -> 0 | I253: =SUM(D253:F253) -> 0
A254: 253 | B254: Others AIML | C254: AIML | D254: =COUNTIFS('2024 -2025-2026'!$M:$M,B254,'2024 -2025-2026'!$K:$K,"SCI",'2024 -2025-2026'!$G:$G,"2024") -> 0 | E254: =COUNTIFS('2024 -2025-2026'!$M:$M,B254,'2024 -2025-2026'!$K:$K,"Scopus/WoS Journals",'2024 -2025-2026'!$G:$G,"2024") -> 0 | F254: =COUNTIFS('2024 -2025-2026'!$M:$M,B254,'2024 -2025-2026'!$K:$K,"Scopus/WoS Conference/Book Chapter/Others", '2024 -2025-2026'!$G:$G,"2024") -> 0 | G254: =COUNTIFS('2024 -2025-2026'!$M:$M,B254,'2024 -2025-2026'!$K:$K,"Student Publication",'2024 -2025-2026'!$G:$G,"2024") -> 0 | H254: =SUM(D254:G254) -> 0 | I254: =SUM(D254:F254) -> 0
A255: 254 | B255: Others ECE | C255: ECE | D255: =COUNTIFS('2024 -2025-2026'!$M:$M,B255,'2024 -2025-2026'!$K:$K,"SCI",'2024 -2025-2026'!$G:$G,"2024") -> 0 | E255: =COUNTIFS('2024 -2025-2026'!$M:$M,B255,'2024 -2025-2026'!$K:$K,"Scopus/WoS Journals",'2024 -2025-2026'!$G:$G,"2024") -> 0 | F255: =COUNTIFS('2024 -2025-2026'!$M:$M,B255,'2024 -2025-2026'!$K:$K,"Scopus/WoS Conference/Book Chapter/Others", '2024 -2025-2026'!$G:$G,"2024") -> 3 | G255: =COUNTIFS('2024 -2025-2026'!$M:$M,B255,'2024 -2025-2026'!$K:$K,"Student Publication",'2024 -2025-2026'!$G:$G,"2024") -> 2 | H255: =SUM(D255:G255) -> 5 | I255: =SUM(D255:F255) -> 3
A256: 255 | B256: Others Maths | C256: S&H | D256: =COUNTIFS('2024 -2025-2026'!$M:$M,B256,'2024 -2025-2026'!$K:$K,"SCI",'2024 -2025-2026'!$G:$G,"2024") -> 0 | E256: =COUNTIFS('2024 -2025-2026'!$M:$M,B256,'2024 -2025-2026'!$K:$K,"Scopus/WoS Journals",'2024 -2025-2026'!$G:$G,"2024") -> 0 | F256: =COUNTIFS('2024 -2025-2026'!$M:$M,B256,'2024 -2025-2026'!$K:$K,"Scopus/WoS Conference/Book Chapter/Others", '2024 -2025-2026'!$G:$G,"2024") -> 0 | G256: =COUNTIFS('2024 -2025-2026'!$M:$M,B256,'2024 -2025-2026'!$K:$K,"Student Publication",'2024 -2025-2026'!$G:$G,"2024") -> 0 | H256: =SUM(D256:G256) -> 0 | I256: =SUM(D256:F256) -> 0
A257: 256 | B257: Others Mech | C257: Mech | D257: =COUNTIFS('2024 -2025-2026'!$M:$M,B257,'2024 -2025-2026'!$K:$K,"SCI",'2024 -2025-2026'!$G:$G,"2024") -> 0 | E257: =COUNTIFS('2024 -2025-2026'!$M:$M,B257,'2024 -2025-2026'!$K:$K,"Scopus/WoS Journals",'2024 -2025-2026'!$G:$G,"2024") -> 0 | F257: =COUNTIFS('2024 -2025-2026'!$M:$M,B257,'2024 -2025-2026'!$K:$K,"Scopus/WoS Conference/Book Chapter/Others", '2024 -2025-2026'!$G:$G,"2024") -> 0 | G257: =COUNTIFS('2024 -2025-2026'!$M:$M,B257,'2024 -2025-2026'!$K:$K,"Student Publication",'2024 -2025-2026'!$G:$G,"2024") -> 0 | H257: =SUM(D257:G257) -> 0 | I257: =SUM(D257:F257) -> 0
A258: 257 | B258: Others IT | C258: IT | D258: =COUNTIFS('2024 -2025-2026'!$M:$M,B258,'2024 -2025-2026'!$K:$K,"SCI",'2024 -2025-2026'!$G:$G,"2024") -> 0 | E258: =COUNTIFS('2024 -2025-2026'!$M:$M,B258,'2024 -2025-2026'!$K:$K,"Scopus/WoS Journals",'2024 -2025-2026'!$G:$G,"2024") -> 0 | F258: =COUNTIFS('2024 -2025-2026'!$M:$M,B258,'2024 -2025-2026'!$K:$K,"Scopus/WoS Conference/Book Chapter/Others", '2024 -2025-2026'!$G:$G,"2024") -> 0 | G258: =COUNTIFS('2024 -2025-2026'!$M:$M,B258,'2024 -2025-2026'!$K:$K,"Student Publication",'2024 -2025-2026'!$G:$G,"2024") -> 0 | H258: =SUM(D258:G258) -> 0 | I258: =SUM(D258:F258) -> 0
A259: 258 | B259: Others CSBS | C259: CSBS | D259: =COUNTIFS('2024 -2025-2026'!$M:$M,B259,'2024 -2025-2026'!$K:$K,"SCI",'2024 -2025-2026'!$G:$G,"2024") -> 0 | E259: =COUNTIFS('2024 -2025-2026'!$M:$M,B259,'2024 -2025-2026'!$K:$K,"Scopus/WoS Journals",'2024 -2025-2026'!$G:$G,"2024") -> 0 | F259: =COUNTIFS('2024 -2025-2026'!$M:$M,B259,'2024 -2025-2026'!$K:$K,"Scopus/WoS Conference/Book Chapter/Others", '2024 -2025-2026'!$G:$G,"2024") -> 0 | G259: =COUNTIFS('2024 -2025-2026'!$M:$M,B259,'2024 -2025-2026'!$K:$K,"Student Publication",'2024 -2025-2026'!$G:$G,"2024") -> 0 | H259: =SUM(D259:G259) -> 0 | I259: =SUM(D259:F259) -> 0
A260: 259 | B260: Others English | C260: S & H (Eng) | D260: =COUNTIFS('2024 -2025-2026'!$M:$M,B260,'2024 -2025-2026'!$K:$K,"SCI",'2024 -2025-2026'!$G:$G,"2024") -> 0 | E260: =COUNTIFS('2024 -2025-2026'!$M:$M,B260,'2024 -2025-2026'!$K:$K,"Scopus/WoS Journals",'2024 -2025-2026'!$G:$G,"2024") -> 0 | F260: =COUNTIFS('2024 -2025-2026'!$M:$M,B260,'2024 -2025-2026'!$K:$K,"Scopus/WoS Conference/Book Chapter/Others", '2024 -2025-2026'!$G:$G,"2024") -> 1 | G260: =COUNTIFS('2024 -2025-2026'!$M:$M,B260,'2024 -2025-2026'!$K:$K,"Student Publication",'2024 -2025-2026'!$G:$G,"2024") -> 0 | H260: =SUM(D260:G260) -> 1 | I260: =SUM(D260:F260) -> 1
A261: 260 | B261: Others S&H | C261: S&H | D261: =COUNTIFS('2024 -2025-2026'!$M:$M,B261,'2024 -2025-2026'!$K:$K,"SCI",'2024 -2025-2026'!$G:$G,"2024") -> 0 | E261: =COUNTIFS('2024 -2025-2026'!$M:$M,B261,'2024 -2025-2026'!$K:$K,"Scopus/WoS Journals",'2024 -2025-2026'!$G:$G,"2024") -> 0 | F261: =COUNTIFS('2024 -2025-2026'!$M:$M,B261,'2024 -2025-2026'!$K:$K,"Scopus/WoS Conference/Book Chapter/Others", '2024 -2025-2026'!$G:$G,"2024") -> 0 | G261: =COUNTIFS('2024 -2025-2026'!$M:$M,B261,'2024 -2025-2026'!$K:$K,"Student Publication",'2024 -2025-2026'!$G:$G,"2024") -> 0 | H261: =SUM(D261:G261) -> 0 | I261: =SUM(D261:F261) -> 0
... A302: 301 | B302: Dr. Solomon Roach R | C302: CCE | D302: =COUNTIFS('2024 -2025-2026'!$M:$M,B302,'2024 -2025-2026'!$K:$K,"SCI",'2024 -2025-2026'!$G:$G,"2024") -> 0 | E302: =COUNTIFS('2024 -2025-2026'!$M:$M,B302,'2024 -2025-2026'!$K:$K,"Scopus/WoS Journals",'2024 -2025-2026'!$G:$G,"2024") -> 0 | F302: =COUNTIFS('2024 -2025-2026'!$M:$M,B302,'2024 -2025-2026'!$K:$K,"Scopus/WoS Conference/Book Chapter/Others", '2024 -2025-2026'!$G:$G,"2024") -> 0 | G302: =COUNTIFS('2024 -2025-2026'!$M:$M,B302,'2024 -2025-2026'!$K:$K,"Student Publication",'2024 -2025-2026'!$G:$G,"2024") -> 0 | H302: =SUM(D302:G302) -> 0 | I302: =SUM(D302:F302) -> 0
A303: 302 | B303: Dr. Vani S | D303: =COUNTIFS('2024 -2025-2026'!$M:$M,B303,'2024 -2025-2026'!$K:$K,"SCI",'2024 -2025-2026'!$G:$G,"2024") -> 0 | E303: =COUNTIFS('2024 -2025-2026'!$M:$M,B303,'2024 -2025-2026'!$K:$K,"Scopus/WoS Journals",'2024 -2025-2026'!$G:$G,"2024") -> 0 | F303: =COUNTIFS('2024 -2025-2026'!$M:$M,B303,'2024 -2025-2026'!$K:$K,"Scopus/WoS Conference/Book Chapter/Others", '2024 -2025-2026'!$G:$G,"2024") -> 0 | G303: =COUNTIFS('2024 -2025-2026'!$M:$M,B303,'2024 -2025-2026'!$K:$K,"Student Publication",'2024 -2025-2026'!$G:$G,"2024") -> 0 | H303: =SUM(D303:G303) -> 0 | I303: =SUM(D303:F303) -> 0
A304: 303 | C304: S & H (Phy) | D304: =COUNTIFS('2024 -2025-2026'!$M:$M,B304,'2024 -2025-2026'!$K:$K,"SCI",'2024 -2025-2026'!$G:$G,"2024") -> 0 | E304: =COUNTIFS('2024 -2025-2026'!$M:$M,B304,'2024 -2025-2026'!$K:$K,"Scopus/WoS Journals",'2024 -2025-2026'!$G:$G,"2024") -> 0 | F304: =COUNTIFS('2024 -2025-2026'!$M:$M,B304,'2024 -2025-2026'!$K:$K,"Scopus/WoS Conference/Book Chapter/Others", '2024 -2025-2026'!$G:$G,"2024") -> 0 | G304: =COUNTIFS('2024 -2025-2026'!$M:$M,B304,'2024 -2025-2026'!$K:$K,"Student Publication",'2024 -2025-2026'!$G:$G,"2024") -> 0 | H304: =SUM(D304:G304) -> 0 | I304: =SUM(D304:F304) -> 0
A305: 304 | B305: Dr. Sheeba Rani Gnanamalar S (T) | C305: ECE | D305: =COUNTIFS('2024 -2025-2026'!$M:$M,B305,'2024 -2025-2026'!$K:$K,"SCI",'2024 -2025-2026'!$G:$G,"2024") -> 0 | E305: =COUNTIFS('2024 -2025-2026'!$M:$M,B305,'2024 -2025-2026'!$K:$K,"Scopus/WoS Journals",'2024 -2025-2026'!$G:$G,"2024") -> 0 | F305: =COUNTIFS('2024 -2025-2026'!$M:$M,B305,'2024 -2025-2026'!$K:$K,"Scopus/WoS Conference/Book Chapter/Others", '2024 -2025-2026'!$G:$G,"2024") -> 0 | G305: =COUNTIFS('2024 -2025-2026'!$M:$M,B305,'2024 -2025-2026'!$K:$K,"Student Publication",'2024 -2025-2026'!$G:$G,"2024") -> 1 | H305: =SUM(D305:G305) -> 1 | I305: =SUM(D305:F305) -> 0
A306: 305 | B306: Dr. Mahendhiran P D | C306: CSBS | D306: =COUNTIFS('2024 -2025-2026'!$M:$M,B306,'2024 -2025-2026'!$K:$K,"SCI",'2024 -2025-2026'!$G:$G,"2024") -> 0 | E306: =COUNTIFS('2024 -2025-2026'!$M:$M,B306,'2024 -2025-2026'!$K:$K,"Scopus/WoS Journals",'2024 -2025-2026'!$G:$G,"2024") -> 0 | F306: =COUNTIFS('2024 -2025-2026'!$M:$M,B306,'2024 -2025-2026'!$K:$K,"Scopus/WoS Conference/Book Chapter/Others", '2024 -2025-2026'!$G:$G,"2024") -> 0 | G306: =COUNTIFS('2024 -2025-2026'!$M:$M,B306,'2024 -2025-2026'!$K:$K,"Student Publication",'2024 -2025-2026'!$G:$G,"2024") -> 0 | H306: =SUM(D306:G306) -> 0 | I306: =SUM(D306:F306) -> 0
A307: 306 | B307: Mr. Karthick R | C307: CSE | D307: =COUNTIFS('2024 -2025-2026'!$M:$M,B307,'2024 -2025-2026'!$K:$K,"SCI",'2024 -2025-2026'!$G:$G,"2024") -> 0 | E307: =COUNTIFS('2024 -2025-2026'!$M:$M,B307,'2024 -2025-2026'!$K:$K,"Scopus/WoS Journals",'2024 -2025-2026'!$G:$G,"2024") -> 0 | F307: =COUNTIFS('2024 -2025-2026'!$M:$M,B307,'2024 -2025-2026'!$K:$K,"Scopus/WoS Conference/Book Chapter/Others", '2024 -2025-2026'!$G:$G,"2024") -> 0 | G307: =COUNTIFS('2024 -2025-2026'!$M:$M,B307,'2024 -2025-2026'!$K:$K,"Student Publication",'2024 -2025-2026'!$G:$G,"2024") -> 0 | H307: =SUM(D307:G307) -> 0 | I307: =SUM(D307:F307) -> 0
A308: 307 | C308: AIDS, ECE | D308: =COUNTIFS('2024 -2025-2026'!$M:$M,B308,'2024 -2025-2026'!$K:$K,"SCI",'2024 -2025-2026'!$G:$G,"2024") -> 0 | E308: =COUNTIFS('2024 -2025-2026'!$M:$M,B308,'2024 -2025-2026'!$K:$K,"Scopus/WoS Journals",'2024 -2025-2026'!$G:$G,"2024") -> 0 | F308: =COUNTIFS('2024 -2025-2026'!$M:$M,B308,'2024 -2025-2026'!$K:$K,"Scopus/WoS Conference/Book Chapter/Others", '2024 -2025-2026'!$G:$G,"2024") -> 0 | G308: =COUNTIFS('2024 -2025-2026'!$M:$M,B308,'2024 -2025-2026'!$K:$K,"Student Publication",'2024 -2025-2026'!$G:$G,"2024") -> 0 | H308: =SUM(D308:G308) -> 0 | I308: =SUM(D308:F308) -> 0
A309: 308 | B309: Dr. Saranya D | D309: =COUNTIFS('2024 -2025-2026'!$M:$M,B309,'2024 -2025-2026'!$K:$K,"SCI",'2024 -2025-2026'!$G:$G,"2024") -> 0 | E309: =COUNTIFS('2024 -2025-2026'!$M:$M,B309,'2024 -2025-2026'!$K:$K,"Scopus/WoS Journals",'2024 -2025-2026'!$G:$G,"2024") -> 0 | F309: =COUNTIFS('2024 -2025-2026'!$M:$M,B309,'2024 -2025-2026'!$K:$K,"Scopus/WoS Conference/Book Chapter/Others", '2024 -2025-2026'!$G:$G,"2024") -> 0 | G309: =COUNTIFS('2024 -2025-2026'!$M:$M,B309,'2024 -2025-2026'!$K:$K,"Student Publication",'2024 -2025-2026'!$G:$G,"2024") -> 0 | H309: =SUM(D309:G309) -> 0 | I309: =SUM(D309:F309) -> 0
A310: 309 | B310: Dr. Akila A | C310: Che | D310: =COUNTIFS('2024 -2025-2026'!$M:$M,B310,'2024 -2025-2026'!$K:$K,"SCI",'2024 -2025-2026'!$G:$G,"2024") -> 0 | E310: =COUNTIFS('2024 -2025-2026'!$M:$M,B310,'2024 -2025-2026'!$K:$K,"Scopus/WoS Journals",'2024 -2025-2026'!$G:$G,"2024") -> 0 | F310: =COUNTIFS('2024 -2025-2026'!$M:$M,B310,'2024 -2025-2026'!$K:$K,"Scopus/WoS Conference/Book Chapter/Others", '2024 -2025-2026'!$G:$G,"2024") -> 0 | G310: =COUNTIFS('2024 -2025-2026'!$M:$M,B310,'2024 -2025-2026'!$K:$K,"Student Publication",'2024 -2025-2026'!$G:$G,"2024") -> 0 | H310: =SUM(D310:G310) -> 0 | I310: =SUM(D310:F310) -> 0
A311: 310 | B311: Ms. Sugunavathy S | C311: RS | D311: =COUNTIFS('2024 -2025-2026'!$M:$M,B311,'2024 -2025-2026'!$K:$K,"SCI",'2024 -2025-2026'!$G:$G,"2024") -> 0 | E311: =COUNTIFS('2024 -2025-2026'!$M:$M,B311,'2024 -2025-2026'!$K:$K,"Scopus/WoS Journals",'2024 -2025-2026'!$G:$G,"2024") -> 0 | F311: =COUNTIFS('2024 -2025-2026'!$M:$M,B311,'2024 -2025-2026'!$K:$K,"Scopus/WoS Conference/Book Chapter/Others", '2024 -2025-2026'!$G:$G,"2024") -> 0 | G311: =COUNTIFS('2024 -2025-2026'!$M:$M,B311,'2024 -2025-2026'!$K:$K,"Student Publication",'2024 -2025-2026'!$G:$G,"2024") -> 0 | H311: =SUM(D311:G311) -> 0 | I311: =SUM(D311:F311) -> 0
A312: 311 | B312: Mr. Boopathi B | C312: RS | D312: =COUNTIFS('2024 -2025-2026'!$M:$M,B312,'2024 -2025-2026'!$K:$K,"SCI",'2024 -2025-2026'!$G:$G,"2024") -> 0 | E312: =COUNTIFS('2024 -2025-2026'!$M:$M,B312,'2024 -2025-2026'!$K:$K,"Scopus/WoS Journals",'2024 -2025-2026'!$G:$G,"2024") -> 0 | F312: =COUNTIFS('2024 -2025-2026'!$M:$M,B312,'2024 -2025-2026'!$K:$K,"Scopus/WoS Conference/Book Chapter/Others", '2024 -2025-2026'!$G:$G,"2024") -> 0 | G312: =COUNTIFS('2024 -2025-2026'!$M:$M,B312,'2024 -2025-2026'!$K:$K,"Student Publication",'2024 -2025-2026'!$G:$G,"2024") -> 0 | H312: =SUM(D312:G312) -> 0 | I312: =SUM(D312:F312) -> 0
A313: 312 | B313: Ms. Divya T | C313: RS | D313: =COUNTIFS('2024 -2025-2026'!$M:$M,B313,'2024 -2025-2026'!$K:$K,"SCI",'2024 -2025-2026'!$G:$G,"2024") -> 0 | E313: =COUNTIFS('2024 -2025-2026'!$M:$M,B313,'2024 -2025-2026'!$K:$K,"Scopus/WoS Journals",'2024 -2025-2026'!$G:$G,"2024") -> 0 | F313: =COUNTIFS('2024 -2025-2026'!$M:$M,B313,'2024 -2025-2026'!$K:$K,"Scopus/WoS Conference/Book Chapter/Others", '2024 -2025-2026'!$G:$G,"2024") -> 0 | G313: =COUNTIFS('2024 -2025-2026'!$M:$M,B313,'2024 -2025-2026'!$K:$K,"Student Publication",'2024 -2025-2026'!$G:$G,"2024") -> 0 | H313: =SUM(D313:G313) -> 0 | I313: =SUM(D313:F313) -> 0
A314: 313 | B314: Mr. Neelraj E | C314: RS | D314: =COUNTIFS('2024 -2025-2026'!$M:$M,B314,'2024 -2025-2026'!$K:$K,"SCI",'2024 -2025-2026'!$G:$G,"2024") -> 0 | E314: =COUNTIFS('2024 -2025-2026'!$M:$M,B314,'2024 -2025-2026'!$K:$K,"Scopus/WoS Journals",'2024 -2025-2026'!$G:$G,"2024") -> 0 | F314: =COUNTIFS('2024 -2025-2026'!$M:$M,B314,'2024 -2025-2026'!$K:$K,"Scopus/WoS Conference/Book Chapter/Others", '2024 -2025-2026'!$G:$G,"2024") -> 0 | G314: =COUNTIFS('2024 -2025-2026'!$M:$M,B314,'2024 -2025-2026'!$K:$K,"Student Publication",'2024 -2025-2026'!$G:$G,"2024") -> 0 | H314: =SUM(D314:G314) -> 0 | I314: =SUM(D314:F314) -> 0
A315: 314 | B315: Ms. Saranya S | C315: RS | D315: =COUNTIFS('2024 -2025-2026'!$M:$M,B315,'2024 -2025-2026'!$K:$K,"SCI",'2024 -2025-2026'!$G:$G,"2024") -> 0 | E315: =COUNTIFS('2024 -2025-2026'!$M:$M,B315,'2024 -2025-2026'!$K:$K,"Scopus/WoS Journals",'2024 -2025-2026'!$G:$G,"2024") -> 0 | F315: =COUNTIFS('2024 -2025-2026'!$M:$M,B315,'2024 -2025-2026'!$K:$K,"Scopus/WoS Conference/Book Chapter/Others", '2024 -2025-2026'!$G:$G,"2024") -> 0 | G315: =COUNTIFS('2024 -2025-2026'!$M:$M,B315,'2024 -2025-2026'!$K:$K,"Student Publication",'2024 -2025-2026'!$G:$G,"2024") -> 0 | H315: =SUM(D315:G315) -> 0 | I315: =SUM(D315:F315) -> 0
A316: 315 | B316: Mr. Manoj Kumar C | C316: RS | D316: =COUNTIFS('2024 -2025-2026'!$M:$M,B316,'2024 -2025-2026'!$K:$K,"SCI",'2024 -2025-2026'!$G:$G,"2024") -> 0 | E316: =COUNTIFS('2024 -2025-2026'!$M:$M,B316,'2024 -2025-2026'!$K:$K,"Scopus/WoS Journals",'2024 -2025-2026'!$G:$G,"2024") -> 0 | F316: =COUNTIFS('2024 -2025-2026'!$M:$M,B316,'2024 -2025-2026'!$K:$K,"Scopus/WoS Conference/Book Chapter/Others", '2024 -2025-2026'!$G:$G,"2024") -> 0 | G316: =COUNTIFS('2024 -2025-2026'!$M:$M,B316,'2024 -2025-2026'!$K:$K,"Student Publication",'2024 -2025-2026'!$G:$G,"2024") -> 0 | H316: =SUM(D316:G316) -> 0 | I316: =SUM(D316:F316) -> 0
A317: 316 | B317: Dr. Vijeyakumar K N | C317: ECE | D317: =COUNTIFS('2024 -2025-2026'!$M:$M,B317,'2024 -2025-2026'!$K:$K,"SCI",'2024 -2025-2026'!$G:$G,"2024") -> 0 | E317: =COUNTIFS('2024 -2025-2026'!$M:$M,B317,'2024 -2025-2026'!$K:$K,"Scopus/WoS Journals",'2024 -2025-2026'!$G:$G,"2024") -> 0 | F317: =COUNTIFS('2024 -2025-2026'!$M:$M,B317,'2024 -2025-2026'!$K:$K,"Scopus/WoS Conference/Book Chapter/Others", '2024 -2025-2026'!$G:$G,"2024") -> 0 | G317: =COUNTIFS('2024 -2025-2026'!$M:$M,B317,'2024 -2025-2026'!$K:$K,"Student Publication",'2024 -2025-2026'!$G:$G,"2024") -> 0 | H317: =SUM(D317:G317) -> 0 | I317: =SUM(D317:F317) -> 0
A318: 317 | B318: Ms. Sushma V P | C318: AIDS | D318: =COUNTIFS('2024 -2025-2026'!$M:$M,B318,'2024 -2025-2026'!$K:$K,"SCI",'2024 -2025-2026'!$G:$G,"2024") -> 0 | E318: =COUNTIFS('2024 -2025-2026'!$M:$M,B318,'2024 -2025-2026'!$K:$K,"Scopus/WoS Journals",'2024 -2025-2026'!$G:$G,"2024") -> 0 | F318: =COUNTIFS('2024 -2025-2026'!$M:$M,B318,'2024 -2025-2026'!$K:$K,"Scopus/WoS Conference/Book Chapter/Others", '2024 -2025-2026'!$G:$G,"2024") -> 0 | G318: =COUNTIFS('2024 -2025-2026'!$M:$M,B318,'2024 -2025-2026'!$K:$K,"Student Publication",'2024 -2025-2026'!$G:$G,"2024") -> 0 | H318: =SUM(D318:G318) -> 0 | I318: =SUM(D318:F318) -> 0
A319: 318 | B319: Mr. Stephen Rufus A | C319: AIDS | D319: =COUNTIFS('2024 -2025-2026'!$M:$M,B319,'2024 -2025-2026'!$K:$K,"SCI",'2024 -2025-2026'!$G:$G,"2024") -> 0 | E319: =COUNTIFS('2024 -2025-2026'!$M:$M,B319,'2024 -2025-2026'!$K:$K,"Scopus/WoS Journals",'2024 -2025-2026'!$G:$G,"2024") -> 0 | F319: =COUNTIFS('2024 -2025-2026'!$M:$M,B319,'2024 -2025-2026'!$K:$K,"Scopus/WoS Conference/Book Chapter/Others", '2024 -2025-2026'!$G:$G,"2024") -> 0 | G319: =COUNTIFS('2024 -2025-2026'!$M:$M,B319,'2024 -2025-2026'!$K:$K,"Student Publication",'2024 -2025-2026'!$G:$G,"2024") -> 0 | H319: =SUM(D319:G319) -> 0 | I319: =SUM(D319:F319) -> 0
A320: 319 | B320: Ms. Rashmi AV | C320: AIDS | D320: =COUNTIFS('2024 -2025-2026'!$M:$M,B320,'2024 -2025-2026'!$K:$K,"SCI",'2024 -2025-2026'!$G:$G,"2024") -> 0 | E320: =COUNTIFS('2024 -2025-2026'!$M:$M,B320,'2024 -2025-2026'!$K:$K,"Scopus/WoS Journals",'2024 -2025-2026'!$G:$G,"2024") -> 0 | F320: =COUNTIFS('2024 -2025-2026'!$M:$M,B320,'2024 -2025-2026'!$K:$K,"Scopus/WoS Conference/Book Chapter/Others", '2024 -2025-2026'!$G:$G,"2024") -> 0 | G320: =COUNTIFS('2024 -2025-2026'!$M:$M,B320,'2024 -2025-2026'!$K:$K,"Student Publication",'2024 -2025-2026'!$G:$G,"2024") -> 0 | H320: =SUM(D320:G320) -> 0 | I320: =SUM(D320:F320) -> 0
A321: 320 | B321: Mr. Sarvesh Nath K | C321: AIDS | D321: =COUNTIFS('2024 -2025-2026'!$M:$M,B321,'2024 -2025-2026'!$K:$K,"SCI",'2024 -2025-2026'!$G:$G,"2024") -> 0 | E321: =COUNTIFS('2024 -2025-2026'!$M:$M,B321,'2024 -2025-2026'!$K:$K,"Scopus/WoS Journals",'2024 -2025-2026'!$G:$G,"2024") -> 0 | F321: =COUNTIFS('2024 -2025-2026'!$M:$M,B321,'2024 -2025-2026'!$K:$K,"Scopus/WoS Conference/Book Chapter/Others", '2024 -2025-2026'!$G:$G,"2024") -> 0 | G321: =COUNTIFS('2024 -2025-2026'!$M:$M,B321,'2024 -2025-2026'!$K:$K,"Student Publication",'2024 -2025-2026'!$G:$G,"2024") -> 0 | H321: =SUM(D321:G321) -> 0 | I321: =SUM(D321:F321) -> 0
... A357: 356 | B357: Dr. Subashini A | C357: Maths | D357: =COUNTIFS('2024 -2025-2026'!$M:$M,B357,'2024 -2025-2026'!$K:$K,"SCI",'2024 -2025-2026'!$G:$G,"2024") -> 0 | E357: =COUNTIFS('2024 -2025-2026'!$M:$M,B357,'2024 -2025-2026'!$K:$K,"Scopus/WoS Journals",'2024 -2025-2026'!$G:$G,"2024") -> 0 | F357: =COUNTIFS('2024 -2025-2026'!$M:$M,B357,'2024 -2025-2026'!$K:$K,"Scopus/WoS Conference/Book Chapter/Others", '2024 -2025-2026'!$G:$G,"2024") -> 0 | G357: =COUNTIFS('2024 -2025-2026'!$M:$M,B357,'2024 -2025-2026'!$K:$K,"Student Publication",'2024 -2025-2026'!$G:$G,"2024") -> 0 | H357: =SUM(D357:G357) -> 0 | I357: =SUM(D357:F357) -> 0
A358: 357 | B358: Ms. Sandhiya K | D358: =COUNTIFS('2024 -2025-2026'!$M:$M,B358,'2024 -2025-2026'!$K:$K,"SCI",'2024 -2025-2026'!$G:$G,"2024") -> 0 | E358: =COUNTIFS('2024 -2025-2026'!$M:$M,B358,'2024 -2025-2026'!$K:$K,"Scopus/WoS Journals",'2024 -2025-2026'!$G:$G,"2024") -> 0 | F358: =COUNTIFS('2024 -2025-2026'!$M:$M,B358,'2024 -2025-2026'!$K:$K,"Scopus/WoS Conference/Book Chapter/Others", '2024 -2025-2026'!$G:$G,"2024") -> 0 | G358: =COUNTIFS('2024 -2025-2026'!$M:$M,B358,'2024 -2025-2026'!$K:$K,"Student Publication",'2024 -2025-2026'!$G:$G,"2024") -> 0 | H358: =SUM(D358:G358) -> 0 | I358: =SUM(D358:F358) -> 0
A359: 358 | B359: Mr. Muthusamy M | D359: =COUNTIFS('2024 -2025-2026'!$M:$M,B359,'2024 -2025-2026'!$K:$K,"SCI",'2024 -2025-2026'!$G:$G,"2024") -> 0 | E359: =COUNTIFS('2024 -2025-2026'!$M:$M,B359,'2024 -2025-2026'!$K:$K,"Scopus/WoS Journals",'2024 -2025-2026'!$G:$G,"2024") -> 0 | F359: =COUNTIFS('2024 -2025-2026'!$M:$M,B359,'2024 -2025-2026'!$K:$K,"Scopus/WoS Conference/Book Chapter/Others", '2024 -2025-2026'!$G:$G,"2024") -> 0 | G359: =COUNTIFS('2024 -2025-2026'!$M:$M,B359,'2024 -2025-2026'!$K:$K,"Student Publication",'2024 -2025-2026'!$G:$G,"2024") -> 0 | H359: =SUM(D359:G359) -> 0 | I359: =SUM(D359:F359) -> 0
A360: 359 | B360: Dr. Poonkodi R | C360: IT | D360: =COUNTIFS('2024 -2025-2026'!$M:$M,B360,'2024 -2025-2026'!$K:$K,"SCI",'2024 -2025-2026'!$G:$G,"2024") -> 0 | E360: =COUNTIFS('2024 -2025-2026'!$M:$M,B360,'2024 -2025-2026'!$K:$K,"Scopus/WoS Journals",'2024 -2025-2026'!$G:$G,"2024") -> 0 | F360: =COUNTIFS('2024 -2025-2026'!$M:$M,B360,'2024 -2025-2026'!$K:$K,"Scopus/WoS Conference/Book Chapter/Others", '2024 -2025-2026'!$G:$G,"2024") -> 0 | G360: =COUNTIFS('2024 -2025-2026'!$M:$M,B360,'2024 -2025-2026'!$K:$K,"Student Publication",'2024 -2025-2026'!$G:$G,"2024") -> 0 | H360: =SUM(D360:G360) -> 0 | I360: =SUM(D360:F360) -> 0
A361: 360 | D361: =COUNTIFS('2024 -2025-2026'!$M:$M,B361,'2024 -2025-2026'!$K:$K,"SCI",'2024 -2025-2026'!$G:$G,"2024") -> 0 | E361: =COUNTIFS('2024 -2025-2026'!$M:$M,B361,'2024 -2025-2026'!$K:$K,"Scopus/WoS Journals",'2024 -2025-2026'!$G:$G,"2024") -> 0 | F361: =COUNTIFS('2024 -2025-2026'!$M:$M,B361,'2024 -2025-2026'!$K:$K,"Scopus/WoS Conference/Book Chapter/Others", '2024 -2025-2026'!$G:$G,"2024") -> 0 | G361: =COUNTIFS('2024 -2025-2026'!$M:$M,B361,'2024 -2025-2026'!$K:$K,"Student Publication",'2024 -2025-2026'!$G:$G,"2024") -> 0 | H361: =SUM(D361:G361) -> 0 | I361: =SUM(D361:F361) -> 0
A362: 361 | D362: =COUNTIFS('2024 -2025-2026'!$M:$M,B362,'2024 -2025-2026'!$K:$K,"SCI",'2024 -2025-2026'!$G:$G,"2024") -> 0 | E362: =COUNTIFS('2024 -2025-2026'!$M:$M,B362,'2024 -2025-2026'!$K:$K,"Scopus/WoS Journals",'2024 -2025-2026'!$G:$G,"2024") -> 0 | F362: =COUNTIFS('2024 -2025-2026'!$M:$M,B362,'2024 -2025-2026'!$K:$K,"Scopus/WoS Conference/Book Chapter/Others", '2024 -2025-2026'!$G:$G,"2024") -> 0 | G362: =COUNTIFS('2024 -2025-2026'!$M:$M,B362,'2024 -2025-2026'!$K:$K,"Student Publication",'2024 -2025-2026'!$G:$G,"2024") -> 0 | H362: =SUM(D362:G362) -> 0 | I362: =SUM(D362:F362) -> 0
A363: 362 | D363: =COUNTIFS('2024 -2025-2026'!$M:$M,B363,'2024 -2025-2026'!$K:$K,"SCI",'2024 -2025-2026'!$G:$G,"2024") -> 0 | E363: =COUNTIFS('2024 -2025-2026'!$M:$M,B363,'2024 -2025-2026'!$K:$K,"Scopus/WoS Journals",'2024 -2025-2026'!$G:$G,"2024") -> 0 | F363: =COUNTIFS('2024 -2025-2026'!$M:$M,B363,'2024 -2025-2026'!$K:$K,"Scopus/WoS Conference/Book Chapter/Others", '2024 -2025-2026'!$G:$G,"2024") -> 0 | G363: =COUNTIFS('2024 -2025-2026'!$M:$M,B363,'2024 -2025-2026'!$K:$K,"Student Publication",'2024 -2025-2026'!$G:$G,"2024") -> 0 | H363: =SUM(D363:G363) -> 0 | I363: =SUM(D363:F363) -> 0
A364: 363 | D364: =COUNTIFS('2024 -2025-2026'!$M:$M,B364,'2024 -2025-2026'!$K:$K,"SCI",'2024 -2025-2026'!$G:$G,"2024") -> 0 | E364: =COUNTIFS('2024 -2025-2026'!$M:$M,B364,'2024 -2025-2026'!$K:$K,"Scopus/WoS Journals",'2024 -2025-2026'!$G:$G,"2024") -> 0 | F364: =COUNTIFS('2024 -2025-2026'!$M:$M,B364,'2024 -2025-2026'!$K:$K,"Scopus/WoS Conference/Book Chapter/Others", '2024 -2025-2026'!$G:$G,"2024") -> 0 | G364: =COUNTIFS('2024 -2025-2026'!$M:$M,B364,'2024 -2025-2026'!$K:$K,"Student Publication",'2024 -2025-2026'!$G:$G,"2024") -> 0 | H364: =SUM(D364:G364) -> 0 | I364: =SUM(D364:F364) -> 0
A365: 364 | D365: =COUNTIFS('2024 -2025-2026'!$M:$M,B365,'2024 -2025-2026'!$K:$K,"SCI",'2024 -2025-2026'!$G:$G,"2024") -> 0 | E365: =COUNTIFS('2024 -2025-2026'!$M:$M,B365,'2024 -2025-2026'!$K:$K,"Scopus/WoS Journals",'2024 -2025-2026'!$G:$G,"2024") -> 0 | F365: =COUNTIFS('2024 -2025-2026'!$M:$M,B365,'2024 -2025-2026'!$K:$K,"Scopus/WoS Conference/Book Chapter/Others", '2024 -2025-2026'!$G:$G,"2024") -> 0 | G365: =COUNTIFS('2024 -2025-2026'!$M:$M,B365,'2024 -2025-2026'!$K:$K,"Student Publication",'2024 -2025-2026'!$G:$G,"2024") -> 0 | H365: =SUM(D365:G365) -> 0 | I365: =SUM(D365:F365) -> 0
A366: 365 | D366: =COUNTIFS('2024 -2025-2026'!$M:$M,B366,'2024 -2025-2026'!$K:$K,"SCI",'2024 -2025-2026'!$G:$G,"2024") -> 0 | E366: =COUNTIFS('2024 -2025-2026'!$M:$M,B366,'2024 -2025-2026'!$K:$K,"Scopus/WoS Journals",'2024 -2025-2026'!$G:$G,"2024") -> 0 | F366: =COUNTIFS('2024 -2025-2026'!$M:$M,B366,'2024 -2025-2026'!$K:$K,"Scopus/WoS Conference/Book Chapter/Others", '2024 -2025-2026'!$G:$G,"2024") -> 0 | G366: =COUNTIFS('2024 -2025-2026'!$M:$M,B366,'2024 -2025-2026'!$K:$K,"Student Publication",'2024 -2025-2026'!$G:$G,"2024") -> 0 | H366: =SUM(D366:G366) -> 0 | I366: =SUM(D366:F366) -> 0
A367: 366 | D367: =COUNTIFS('2024 -2025-2026'!$M:$M,B367,'2024 -2025-2026'!$K:$K,"SCI",'2024 -2025-2026'!$G:$G,"2024") -> 0 | E367: =COUNTIFS('2024 -2025-2026'!$M:$M,B367,'2024 -2025-2026'!$K:$K,"Scopus/WoS Journals",'2024 -2025-2026'!$G:$G,"2024") -> 0 | F367: =COUNTIFS('2024 -2025-2026'!$M:$M,B367,'2024 -2025-2026'!$K:$K,"Scopus/WoS Conference/Book Chapter/Others", '2024 -2025-2026'!$G:$G,"2024") -> 0 | G367: =COUNTIFS('2024 -2025-2026'!$M:$M,B367,'2024 -2025-2026'!$K:$K,"Student Publication",'2024 -2025-2026'!$G:$G,"2024") -> 0 | H367: =SUM(D367:G367) -> 0 | I367: =SUM(D367:F367) -> 0
A368: 367 | D368: =COUNTIFS('2024 -2025-2026'!$M:$M,B368,'2024 -2025-2026'!$K:$K,"SCI",'2024 -2025-2026'!$G:$G,"2024") -> 0 | E368: =COUNTIFS('2024 -2025-2026'!$M:$M,B368,'2024 -2025-2026'!$K:$K,"Scopus/WoS Journals",'2024 -2025-2026'!$G:$G,"2024") -> 0 | F368: =COUNTIFS('2024 -2025-2026'!$M:$M,B368,'2024 -2025-2026'!$K:$K,"Scopus/WoS Conference/Book Chapter/Others", '2024 -2025-2026'!$G:$G,"2024") -> 0 | G368: =COUNTIFS('2024 -2025-2026'!$M:$M,B368,'2024 -2025-2026'!$K:$K,"Student Publication",'2024 -2025-2026'!$G:$G,"2024") -> 0 | H368: =SUM(D368:G368) -> 0 | I368: =SUM(D368:F368) -> 0
A369: 368 | D369: =COUNTIFS('2024 -2025-2026'!$M:$M,B369,'2024 -2025-2026'!$K:$K,"SCI",'2024 -2025-2026'!$G:$G,"2024") -> 0 | E369: =COUNTIFS('2024 -2025-2026'!$M:$M,B369,'2024 -2025-2026'!$K:$K,"Scopus/WoS Journals",'2024 -2025-2026'!$G:$G,"2024") -> 0 | F369: =COUNTIFS('2024 -2025-2026'!$M:$M,B369,'2024 -2025-2026'!$K:$K,"Scopus/WoS Conference/Book Chapter/Others", '2024 -2025-2026'!$G:$G,"2024") -> 0 | G369: =COUNTIFS('2024 -2025-2026'!$M:$M,B369,'2024 -2025-2026'!$K:$K,"Student Publication",'2024 -2025-2026'!$G:$G,"2024") -> 0 | H369: =SUM(D369:G369) -> 0 | I369: =SUM(D369:F369) -> 0
A370: 369 | D370: =COUNTIFS('2024 -2025-2026'!$M:$M,B370,'2024 -2025-2026'!$K:$K,"SCI",'2024 -2025-2026'!$G:$G,"2024") -> 0 | E370: =COUNTIFS('2024 -2025-2026'!$M:$M,B370,'2024 -2025-2026'!$K:$K,"Scopus/WoS Journals",'2024 -2025-2026'!$G:$G,"2024") -> 0 | F370: =COUNTIFS('2024 -2025-2026'!$M:$M,B370,'2024 -2025-2026'!$K:$K,"Scopus/WoS Conference/Book Chapter/Others", '2024 -2025-2026'!$G:$G,"2024") -> 0 | G370: =COUNTIFS('2024 -2025-2026'!$M:$M,B370,'2024 -2025-2026'!$K:$K,"Student Publication",'2024 -2025-2026'!$G:$G,"2024") -> 0 | H370: =SUM(D370:G370) -> 0 | I370: =SUM(D370:F370) -> 0
A371: 370 | D371: =COUNTIFS('2024 -2025-2026'!$M:$M,B371,'2024 -2025-2026'!$K:$K,"SCI",'2024 -2025-2026'!$G:$G,"2024") -> 0 | E371: =COUNTIFS('2024 -2025-2026'!$M:$M,B371,'2024 -2025-2026'!$K:$K,"Scopus/WoS Journals",'2024 -2025-2026'!$G:$G,"2024") -> 0 | F371: =COUNTIFS('2024 -2025-2026'!$M:$M,B371,'2024 -2025-2026'!$K:$K,"Scopus/WoS Conference/Book Chapter/Others", '2024 -2025-2026'!$G:$G,"2024") -> 0 | G371: =COUNTIFS('2024 -2025-2026'!$M:$M,B371,'2024 -2025-2026'!$K:$K,"Student Publication",'2024 -2025-2026'!$G:$G,"2024") -> 0 | H371: =SUM(D371:G371) -> 0 | I371: =SUM(D371:F371) -> 0
A372: 371 | D372: =COUNTIFS('2024 -2025-2026'!$M:$M,B372,'2024 -2025-2026'!$K:$K,"SCI",'2024 -2025-2026'!$G:$G,"2024") -> 0 | E372: =COUNTIFS('2024 -2025-2026'!$M:$M,B372,'2024 -2025-2026'!$K:$K,"Scopus/WoS Journals",'2024 -2025-2026'!$G:$G,"2024") -> 0 | F372: =COUNTIFS('2024 -2025-2026'!$M:$M,B372,'2024 -2025-2026'!$K:$K,"Scopus/WoS Conference/Book Chapter/Others", '2024 -2025-2026'!$G:$G,"2024") -> 0 | G372: =COUNTIFS('2024 -2025-2026'!$M:$M,B372,'2024 -2025-2026'!$K:$K,"Student Publication",'2024 -2025-2026'!$G:$G,"2024") -> 0 | H372: =SUM(D372:G372) -> 0 | I372: =SUM(D372:F372) -> 0
D373: =COUNTIFS('2024 -2025-2026'!$M:$M,B373,'2024 -2025-2026'!$K:$K,"SCI",'2024 -2025-2026'!$G:$G,"2024") -> 0 | E373: =COUNTIFS('2024 -2025-2026'!$M:$M,B373,'2024 -2025-2026'!$K:$K,"Scopus/WoS Journals",'2024 -2025-2026'!$G:$G,"2024") -> 0 | F373: =COUNTIFS('2024 -2025-2026'!$M:$M,B373,'2024 -2025-2026'!$K:$K,"Scopus/WoS Conference/Book Chapter/Others", '2024 -2025-2026'!$G:$G,"2024") -> 0 | G373: =COUNTIFS('2024 -2025-2026'!$M:$M,B373,'2024 -2025-2026'!$K:$K,"Student Publication",'2024 -2025-2026'!$G:$G,"2024") -> 0 | H373: =SUM(D373:G373) -> 0 | I373: =SUM(D373:F373) -> 0
D374: =COUNTIFS('2024 -2025-2026'!$M:$M,B374,'2024 -2025-2026'!$K:$K,"SCI",'2024 -2025-2026'!$G:$G,"2024") -> 0 | E374: =COUNTIFS('2024 -2025-2026'!$M:$M,B374,'2024 -2025-2026'!$K:$K,"Scopus/WoS Journals",'2024 -2025-2026'!$G:$G,"2024") -> 0 | F374: =COUNTIFS('2024 -2025-2026'!$M:$M,B374,'2024 -2025-2026'!$K:$K,"Scopus/WoS Conference/Book Chapter/Others", '2024 -2025-2026'!$G:$G,"2024") -> 0 | G374: =COUNTIFS('2024 -2025-2026'!$M:$M,B374,'2024 -2025-2026'!$K:$K,"Student Publication",'2024 -2025-2026'!$G:$G,"2024") -> 0 | H374: =SUM(D374:G374) -> 0 | I374: =SUM(D374:F374) -> 0
D375: =COUNTIFS('2024 -2025-2026'!$M:$M,B375,'2024 -2025-2026'!$K:$K,"SCI",'2024 -2025-2026'!$G:$G,"2024") -> 0 | E375: =COUNTIFS('2024 -2025-2026'!$M:$M,B375,'2024 -2025-2026'!$K:$K,"Scopus/WoS Journals",'2024 -2025-2026'!$G:$G,"2024") -> 0 | F375: =COUNTIFS('2024 -2025-2026'!$M:$M,B375,'2024 -2025-2026'!$K:$K,"Scopus/WoS Conference/Book Chapter/Others", '2024 -2025-2026'!$G:$G,"2024") -> 0 | G375: =COUNTIFS('2024 -2025-2026'!$M:$M,B375,'2024 -2025-2026'!$K:$K,"Student Publication",'2024 -2025-2026'!$G:$G,"2024") -> 0 | H375: =SUM(D375:G375) -> 0 | I375: =SUM(D375:F375) -> 0
D376: =COUNTIFS('2024 -2025-2026'!$M:$M,B376,'2024 -2025-2026'!$K:$K,"SCI",'2024 -2025-2026'!$G:$G,"2024") -> 0 | E376: =COUNTIFS('2024 -2025-2026'!$M:$M,B376,'2024 -2025-2026'!$K:$K,"Scopus/WoS Journals",'2024 -2025-2026'!$G:$G,"2024") -> 0 | F376: =COUNTIFS('2024 -2025-2026'!$M:$M,B376,'2024 -2025-2026'!$K:$K,"Scopus/WoS Conference/Book Chapter/Others", '2024 -2025-2026'!$G:$G,"2024") -> 0 | G376: =COUNTIFS('2024 -2025-2026'!$M:$M,B376,'2024 -2025-2026'!$K:$K,"Student Publication",'2024 -2025-2026'!$G:$G,"2024") -> 0 | H376: =SUM(D376:G376) -> 0 | I376: =SUM(D376:F376) -> 0
D377: =COUNTIFS('2024 -2025-2026'!$M:$M,B377,'2024 -2025-2026'!$K:$K,"SCI",'2024 -2025-2026'!$G:$G,"2024") -> 0 | E377: =COUNTIFS('2024 -2025-2026'!$M:$M,B377,'2024 -2025-2026'!$K:$K,"Scopus/WoS Journals",'2024 -2025-2026'!$G:$G,"2024") -> 0 | F377: =COUNTIFS('2024 -2025-2026'!$M:$M,B377,'2024 -2025-2026'!$K:$K,"Scopus/WoS Conference/Book Chapter/Others", '2024 -2025-2026'!$G:$G,"2024") -> 0 | G377: =COUNTIFS('2024 -2025-2026'!$M:$M,B377,'2024 -2025-2026'!$K:$K,"Student Publication",'2024 -2025-2026'!$G:$G,"2024") -> 0 | H377: =SUM(D377:G377) -> 0 | I377: =SUM(D377:F377) -> 0
D378: =COUNTIFS('2024 -2025-2026'!$M:$M,B378,'2024 -2025-2026'!$K:$K,"SCI",'2024 -2025-2026'!$G:$G,"2024") -> 0 | E378: =COUNTIFS('2024 -2025-2026'!$M:$M,B378,'2024 -2025-2026'!$K:$K,"Scopus/WoS Journals",'2024 -2025-2026'!$G:$G,"2024") -> 0 | F378: =COUNTIFS('2024 -2025-2026'!$M:$M,B378,'2024 -2025-2026'!$K:$K,"Scopus/WoS Conference/Book Chapter/Others", '2024 -2025-2026'!$G:$G,"2024") -> 0 | G378: =COUNTIFS('2024 -2025-2026'!$M:$M,B378,'2024 -2025-2026'!$K:$K,"Student Publication",'2024 -2025-2026'!$G:$G,"2024") -> 0 | H378: =SUM(D378:G378) -> 0 | I378: =SUM(D378:F378) -> 0
D379: =COUNTIFS('2024 -2025-2026'!$M:$M,B379,'2024 -2025-2026'!$K:$K,"SCI",'2024 -2025-2026'!$G:$G,"2024") -> 0 | E379: =COUNTIFS('2024 -2025-2026'!$M:$M,B379,'2024 -2025-2026'!$K:$K,"Scopus/WoS Journals",'2024 -2025-2026'!$G:$G,"2024") -> 0 | F379: =COUNTIFS('2024 -2025-2026'!$M:$M,B379,'2024 -2025-2026'!$K:$K,"Scopus/WoS Conference/Book Chapter/Others", '2024 -2025-2026'!$G:$G,"2024") -> 0 | G379: =COUNTIFS('2024 -2025-2026'!$M:$M,B379,'2024 -2025-2026'!$K:$K,"Student Publication",'2024 -2025-2026'!$G:$G,"2024") -> 0 | H379: =SUM(D379:G379) -> 0 | I379: =SUM(D379:F379) -> 0
D380: =COUNTIFS('2024 -2025-2026'!$M:$M,B380,'2024 -2025-2026'!$K:$K,"SCI",'2024 -2025-2026'!$G:$G,"2024") -> 0 | E380: =COUNTIFS('2024 -2025-2026'!$M:$M,B380,'2024 -2025-2026'!$K:$K,"Scopus/WoS Journals",'2024 -2025-2026'!$G:$G,"2024") -> 0 | F380: =COUNTIFS('2024 -2025-2026'!$M:$M,B380,'2024 -2025-2026'!$K:$K,"Scopus/WoS Conference/Book Chapter/Others", '2024 -2025-2026'!$G:$G,"2024") -> 0 | G380: =COUNTIFS('2024 -2025-2026'!$M:$M,B380,'2024 -2025-2026'!$K:$K,"Student Publication",'2024 -2025-2026'!$G:$G,"2024") -> 0 | H380: =SUM(D380:G380) -> 0 | I380: =SUM(D380:F380) -> 0
D381: =COUNTIFS('2024 -2025-2026'!$M:$M,B381,'2024 -2025-2026'!$K:$K,"SCI",'2024 -2025-2026'!$G:$G,"2024") -> 0 | E381: =COUNTIFS('2024 -2025-2026'!$M:$M,B381,'2024 -2025-2026'!$K:$K,"Scopus/WoS Journals",'2024 -2025-2026'!$G:$G,"2024") -> 0 | F381: =COUNTIFS('2024 -2025-2026'!$M:$M,B381,'2024 -2025-2026'!$K:$K,"Scopus/WoS Conference/Book Chapter/Others", '2024 -2025-2026'!$G:$G,"2024") -> 0 | G381: =COUNTIFS('2024 -2025-2026'!$M:$M,B381,'2024 -2025-2026'!$K:$K,"Student Publication",'2024 -2025-2026'!$G:$G,"2024") -> 0 | H381: =SUM(D381:G381) -> 0 | I381: =SUM(D381:F381) -> 0
D382: =COUNTIFS('2024 -2025-2026'!$M:$M,B382,'2024 -2025-2026'!$K:$K,"SCI",'2024 -2025-2026'!$G:$G,"2024") -> 0 | E382: =COUNTIFS('2024 -2025-2026'!$M:$M,B382,'2024 -2025-2026'!$K:$K,"Scopus/WoS Journals",'2024 -2025-2026'!$G:$G,"2024") -> 0 | F382: =COUNTIFS('2024 -2025-2026'!$M:$M,B382,'2024 -2025-2026'!$K:$K,"Scopus/WoS Conference/Book Chapter/Others", '2024 -2025-2026'!$G:$G,"2024") -> 0 | G382: =COUNTIFS('2024 -2025-2026'!$M:$M,B382,'2024 -2025-2026'!$K:$K,"Student Publication",'2024 -2025-2026'!$G:$G,"2024") -> 0 | H382: =SUM(D382:G382) -> 0 | I382: =SUM(D382:F382) -> 0
D383: =COUNTIFS('2024 -2025-2026'!$M:$M,B383,'2024 -2025-2026'!$K:$K,"SCI",'2024 -2025-2026'!$G:$G,"2024") -> 0 | E383: =COUNTIFS('2024 -2025-2026'!$M:$M,B383,'2024 -2025-2026'!$K:$K,"Scopus/WoS Journals",'2024 -2025-2026'!$G:$G,"2024") -> 0 | F383: =COUNTIFS('2024 -2025-2026'!$M:$M,B383,'2024 -2025-2026'!$K:$K,"Scopus/WoS Conference/Book Chapter/Others", '2024 -2025-2026'!$G:$G,"2024") -> 0 | G383: =COUNTIFS('2024 -2025-2026'!$M:$M,B383,'2024 -2025-2026'!$K:$K,"Student Publication",'2024 -2025-2026'!$G:$G,"2024") -> 0 | H383: =SUM(D383:G383) -> 0 | I383: =SUM(D383:F383) -> 0
D384: =COUNTIFS('2024 -2025-2026'!$M:$M,B384,'2024 -2025-2026'!$K:$K,"SCI",'2024 -2025-2026'!$G:$G,"2024") -> 0 | E384: =COUNTIFS('2024 -2025-2026'!$M:$M,B384,'2024 -2025-2026'!$K:$K,"Scopus/WoS Journals",'2024 -2025-2026'!$G:$G,"2024") -> 0 | F384: =COUNTIFS('2024 -2025-2026'!$M:$M,B384,'2024 -2025-2026'!$K:$K,"Scopus/WoS Conference/Book Chapter/Others", '2024 -2025-2026'!$G:$G,"2024") -> 0 | G384: =COUNTIFS('2024 -2025-2026'!$M:$M,B384,'2024 -2025-2026'!$K:$K,"Student Publication",'2024 -2025-2026'!$G:$G,"2024") -> 0 | H384: =SUM(D384:G384) -> 0 | I384: =SUM(D384:F384) -> 0
... D389: =COUNTIFS('2024 -2025-2026'!$M:$M,B389,'2024 -2025-2026'!$K:$K,"SCI",'2024 -2025-2026'!$G:$G,"2024") -> 0 | E389: =COUNTIFS('2024 -2025-2026'!$M:$M,B389,'2024 -2025-2026'!$K:$K,"Scopus/WoS Journals",'2024 -2025-2026'!$G:$G,"2024") -> 0 | F389: =COUNTIFS('2024 -2025-2026'!$M:$M,B389,'2024 -2025-2026'!$K:$K,"Scopus/WoS Conference/Book Chapter/Others", '2024 -2025-2026'!$G:$G,"2024") -> 0 | G389: =COUNTIFS('2024 -2025-2026'!$M:$M,B389,'2024 -2025-2026'!$K:$K,"Student Publication",'2024 -2025-2026'!$G:$G,"2024") -> 0 | H389: =SUM(D389:G389) -> 0 | I389: =SUM(D389:F389) -> 0

Sheet Name of the Faculty 2025
A1: S.No | B1: Name of the Faculty | C1: Dept | D1: SCI - 2025 | E1: Scopus/WoS Journals - 2025 | F1: Scopus/WoS Conference/Book Chapter/Others - 2025 | G1: Student Publication 2025 | H1: Patent Published | I1: Patent Granted | J1: Total Publications without Student Publications | K1: Total | L1: Book | P1: Combined Department
A2: ='Name of the Faculty 2024'!A2 -> 1 | B2: ='Name of the Faculty 2024'!B2 -> Dr. Dinesh Kumar P | C2: ='Name of the Faculty 2024'!C2 -> AIDS | D2: =COUNTIFS('2024 -2025-2026'!$M:$M,B2,'2024 -2025-2026'!$K:$K,"SCI",'2024 -2025-2026'!$G:$G,"2025") -> 0 | E2: =COUNTIFS('2024 -2025-2026'!$M:$M,B2,'2024 -2025-2026'!$K:$K,"Scopus/WoS Journals",'2024 -2025-2026'!$G:$G,"2025") -> 0 | F2: =COUNTIFS('2024 -2025-2026'!$M:$M,B2,'2024 -2025-2026'!$K:$K,"Scopus/WoS Conference/Book Chapter/Others", '2024 -2025-2026'!$G:$G,"2025") -> 0 | G2: =COUNTIFS('2024 -2025-2026'!$M:$M,B2,'2024 -2025-2026'!$K:$K,"Student Publication", '2024 -2025-2026'!$G:$G,"2025") -> 0 | H2: =COUNTIFS('Patent - 2025'!$Q:$Q,B2,'Patent - 2025'!$D:$D,"Published") -> 1 | I2: =COUNTIFS('Patent - 2025'!$Q:$Q,B2,'Patent - 2025'!D:D,"Granted") -> 0 | J2: =SUM(D2:F2) -> 0 | K2: =SUM(D2:G2) -> 0 | L2: =COUNTIFS('2024 -2025-2026'!$M:$M,B2,'2024 -2025-2026'!$K:$K,"Book",'2024 -2025-2026'!$G:$G,"2025") -> 0 | N2: SCI | O2: =SUM(D2:D499) -> 186 | P2: AIDS
A3: ='Name of the Faculty 2024'!A3 -> 2 | B3: ='Name of the Faculty 2024'!B3 -> Dr. Geetha M P | C3: ='Name of the Faculty 2024'!C3 -> AIDS | D3: =COUNTIFS('2024 -2025-2026'!$M:$M,B3,'2024 -2025-2026'!$K:$K,"SCI",'2024 -2025-2026'!$G:$G,"2025") -> 0 | E3: =COUNTIFS('2024 -2025-2026'!$M:$M,B3,'2024 -2025-2026'!$K:$K,"Scopus/WoS Journals",'2024 -2025-2026'!$G:$G,"2025") -> 1 | F3: =COUNTIFS('2024 -2025-2026'!$M:$M,B3,'2024 -2025-2026'!$K:$K,"Scopus/WoS Conference/Book Chapter/Others", '2024 -2025-2026'!$G:$G,"2025") -> 1 | G3: =COUNTIFS('2024 -2025-2026'!$M:$M,B3,'2024 -2025-2026'!$K:$K,"Student Publication", '2024 -2025-2026'!$G:$G,"2025") -> 0 | H3: =COUNTIFS('Patent - 2025'!$Q:$Q,B3,'Patent - 2025'!$D:$D,"Published") -> 0 | I3: =COUNTIFS('Patent - 2025'!$Q:$Q,B3,'Patent - 2025'!D:D,"Granted") -> 0 | J3: =SUM(D3:F3) -> 2 | K3: =SUM(D3:G3) -> 2 | L3: =COUNTIFS('2024 -2025-2026'!$M:$M,B3,'2024 -2025-2026'!$K:$K,"Book",'2024 -2025-2026'!$G:$G,"2025") -> 0 | N3: Scopus/WoS Journals | O3: =SUM(E2:E499) -> 104 | P3: AIML
A4: ='Name of the Faculty 2024'!A4 -> 3 | B4: ='Name of the Faculty 2024'!B4 -> Dr. Kanimozhi T | C4: ='Name of the Faculty 2024'!C4 -> AIDS | D4: =COUNTIFS('2024 -2025-2026'!$M:$M,B4,'2024 -2025-2026'!$K:$K,"SCI",'2024 -2025-2026'!$G:$G,"2025") -> 1 | E4: =COUNTIFS('2024 -2025-2026'!$M:$M,B4,'2024 -2025-2026'!$K:$K,"Scopus/WoS Journals",'2024 -2025-2026'!$G:$G,"2025") -> 0 | F4: =COUNTIFS('2024 -2025-2026'!$M:$M,B4,'2024 -2025-2026'!$K:$K,"Scopus/WoS Conference/Book Chapter/Others", '2024 -2025-2026'!$G:$G,"2025") -> 4 | G4: =COUNTIFS('2024 -2025-2026'!$M:$M,B4,'2024 -2025-2026'!$K:$K,"Student Publication", '2024 -2025-2026'!$G:$G,"2025") -> 1 | H4: =COUNTIFS('Patent - 2025'!$Q:$Q,B4,'Patent - 2025'!$D:$D,"Published") -> 1 | I4: =COUNTIFS('Patent - 2025'!$Q:$Q,B4,'Patent - 2025'!D:D,"Granted") -> 0 | J4: =SUM(D4:F4) -> 5 | K4: =SUM(D4:G4) -> 6 | L4: =COUNTIFS('2024 -2025-2026'!$M:$M,B4,'2024 -2025-2026'!$K:$K,"Book",'2024 -2025-2026'!$G:$G,"2025") -> 0 | N4: Scopus/WoS Conference/Book Chapter/Others | O4: =SUM(F2:F499) -> 404 | P4: CCE
A5: ='Name of the Faculty 2024'!A5 -> 4 | B5: ='Name of the Faculty 2024'!B5 -> Dr. Lakshmi M | C5: ='Name of the Faculty 2024'!C5 -> AIDS | D5: =COUNTIFS('2024 -2025-2026'!$M:$M,B5,'2024 -2025-2026'!$K:$K,"SCI",'2024 -2025-2026'!$G:$G,"2025") -> 0 | E5: =COUNTIFS('2024 -2025-2026'!$M:$M,B5,'2024 -2025-2026'!$K:$K,"Scopus/WoS Journals",'2024 -2025-2026'!$G:$G,"2025") -> 0 | F5: =COUNTIFS('2024 -2025-2026'!$M:$M,B5,'2024 -2025-2026'!$K:$K,"Scopus/WoS Conference/Book Chapter/Others", '2024 -2025-2026'!$G:$G,"2025") -> 0 | G5: =COUNTIFS('2024 -2025-2026'!$M:$M,B5,'2024 -2025-2026'!$K:$K,"Student Publication", '2024 -2025-2026'!$G:$G,"2025") -> 0 | H5: =COUNTIFS('Patent - 2025'!$Q:$Q,B5,'Patent - 2025'!$D:$D,"Published") -> 0 | I5: =COUNTIFS('Patent - 2025'!$Q:$Q,B5,'Patent - 2025'!D:D,"Granted") -> 0 | J5: =SUM(D5:F5) -> 0 | K5: =SUM(D5:G5) -> 0 | L5: =COUNTIFS('2024 -2025-2026'!$M:$M,B5,'2024 -2025-2026'!$K:$K,"Book",'2024 -2025-2026'!$G:$G,"2025") -> 0 | N5: Student Publication | O5: =SUM(G2:G499) -> 205 | P5: CSBS
A6: ='Name of the Faculty 2024'!A6 -> 5 | B6: ='Name of the Faculty 2024'!B6 -> Dr. Mohammed Mustafa M | C6: ='Name of the Faculty 2024'!C6 -> AIDS | D6: =COUNTIFS('2024 -2025-2026'!$M:$M,B6,'2024 -2025-2026'!$K:$K,"SCI",'2024 -2025-2026'!$G:$G,"2025") -> 0 | E6: =COUNTIFS('2024 -2025-2026'!$M:$M,B6,'2024 -2025-2026'!$K:$K,"Scopus/WoS Journals",'2024 -2025-2026'!$G:$G,"2025") -> 0 | F6: =COUNTIFS('2024 -2025-2026'!$M:$M,B6,'2024 -2025-2026'!$K:$K,"Scopus/WoS Conference/Book Chapter/Others", '2024 -2025-2026'!$G:$G,"2025") -> 1 | G6: =COUNTIFS('2024 -2025-2026'!$M:$M,B6,'2024 -2025-2026'!$K:$K,"Student Publication", '2024 -2025-2026'!$G:$G,"2025") -> 0 | H6: =COUNTIFS('Patent - 2025'!$Q:$Q,B6,'Patent - 2025'!$D:$D,"Published") -> 1 | I6: =COUNTIFS('Patent - 2025'!$Q:$Q,B6,'Patent - 2025'!D:D,"Granted") -> 0 | J6: =SUM(D6:F6) -> 1 | K6: =SUM(D6:G6) -> 1 | L6: =COUNTIFS('2024 -2025-2026'!$M:$M,B6,'2024 -2025-2026'!$K:$K,"Book",'2024 -2025-2026'!$G:$G,"2025") -> 0 | N6: Book | O6: =SUM(L2:L2246) -> 6 | P6: CSE
A7: ='Name of the Faculty 2024'!A7 -> 6 | B7: ='Name of the Faculty 2024'!B7 -> Dr. Nivaashini M | C7: ='Name of the Faculty 2024'!C7 -> AIDS | D7: =COUNTIFS('2024 -2025-2026'!$M:$M,B7,'2024 -2025-2026'!$K:$K,"SCI",'2024 -2025-2026'!$G:$G,"2025") -> 0 | E7: =COUNTIFS('2024 -2025-2026'!$M:$M,B7,'2024 -2025-2026'!$K:$K,"Scopus/WoS Journals",'2024 -2025-2026'!$G:$G,"2025") -> 0 | F7: =COUNTIFS('2024 -2025-2026'!$M:$M,B7,'2024 -2025-2026'!$K:$K,"Scopus/WoS Conference/Book Chapter/Others", '2024 -2025-2026'!$G:$G,"2025") -> 7 | G7: =COUNTIFS('2024 -2025-2026'!$M:$M,B7,'2024 -2025-2026'!$K:$K,"Student Publication", '2024 -2025-2026'!$G:$G,"2025") -> 1 | H7: =COUNTIFS('Patent - 2025'!$Q:$Q,B7,'Patent - 2025'!$D:$D,"Published") -> 0 | I7: =COUNTIFS('Patent - 2025'!$Q:$Q,B7,'Patent - 2025'!D:D,"Granted") -> 0 | J7: =SUM(D7:F7) -> 7 | K7: =SUM(D7:G7) -> 8 | L7: =COUNTIFS('2024 -2025-2026'!$M:$M,B7,'2024 -2025-2026'!$K:$K,"Book",'2024 -2025-2026'!$G:$G,"2025") -> 0 | N7: Total | O7: =SUM(O2:O6) -> 905 | P7: ECE
A8: ='Name of the Faculty 2024'!A8 -> 7 | B8: ='Name of the Faculty 2024'!B8 -> Dr. Sathish Kumar G | C8: ='Name of the Faculty 2024'!C8 -> AIDS | D8: =COUNTIFS('2024 -2025-2026'!$M:$M,B8,'2024 -2025-2026'!$K:$K,"SCI",'2024 -2025-2026'!$G:$G,"2025") -> 3 | E8: =COUNTIFS('2024 -2025-2026'!$M:$M,B8,'2024 -2025-2026'!$K:$K,"Scopus/WoS Journals",'2024 -2025-2026'!$G:$G,"2025") -> 1 | F8: =COUNTIFS('2024 -2025-2026'!$M:$M,B8,'2024 -2025-2026'!$K:$K,"Scopus/WoS Conference/Book Chapter/Others", '2024 -2025-2026'!$G:$G,"2025") -> 0 | G8: =COUNTIFS('2024 -2025-2026'!$M:$M,B8,'2024 -2025-2026'!$K:$K,"Student Publication", '2024 -2025-2026'!$G:$G,"2025") -> 2 | H8: =COUNTIFS('Patent - 2025'!$Q:$Q,B8,'Patent - 2025'!$D:$D,"Published") -> 0 | I8: =COUNTIFS('Patent - 2025'!$Q:$Q,B8,'Patent - 2025'!D:D,"Granted") -> 0 | J8: =SUM(D8:F8) -> 4 | K8: =SUM(D8:G8) -> 6 | L8: =COUNTIFS('2024 -2025-2026'!$M:$M,B8,'2024 -2025-2026'!$K:$K,"Book",'2024 -2025-2026'!$G:$G,"2025") -> 0 | P8: MECH
A9: ='Name of the Faculty 2024'!A9 -> 8 | B9: ='Name of the Faculty 2024'!B9 -> Dr. Thenmozhi M | C9: ='Name of the Faculty 2024'!C9 -> AIDS | D9: =COUNTIFS('2024 -2025-2026'!$M:$M,B9,'2024 -2025-2026'!$K:$K,"SCI",'2024 -2025-2026'!$G:$G,"2025") -> 0 | E9: =COUNTIFS('2024 -2025-2026'!$M:$M,B9,'2024 -2025-2026'!$K:$K,"Scopus/WoS Journals",'2024 -2025-2026'!$G:$G,"2025") -> 1 | F9: =COUNTIFS('2024 -2025-2026'!$M:$M,B9,'2024 -2025-2026'!$K:$K,"Scopus/WoS Conference/Book Chapter/Others", '2024 -2025-2026'!$G:$G,"2025") -> 4 | G9: =COUNTIFS('2024 -2025-2026'!$M:$M,B9,'2024 -2025-2026'!$K:$K,"Student Publication", '2024 -2025-2026'!$G:$G,"2025") -> 0 | H9: =COUNTIFS('Patent - 2025'!$Q:$Q,B9,'Patent - 2025'!$D:$D,"Published") -> 1 | I9: =COUNTIFS('Patent - 2025'!$Q:$Q,B9,'Patent - 2025'!D:D,"Granted") -> 0 | J9: =SUM(D9:F9) -> 5 | K9: =SUM(D9:G9) -> 5 | L9: =COUNTIFS('2024 -2025-2026'!$M:$M,B9,'2024 -2025-2026'!$K:$K,"Book",'2024 -2025-2026'!$G:$G,"2025") -> 0 | P9: EEE
A10: ='Name of the Faculty 2024'!A10 -> 9 | B10: ='Name of the Faculty 2024'!B10 -> Dr. Vimal S | C10: ='Name of the Faculty 2024'!C10 -> AIDS | D10: =COUNTIFS('2024 -2025-2026'!$M:$M,B10,'2024 -2025-2026'!$K:$K,"SCI",'2024 -2025-2026'!$G:$G,"2025") -> 0 | E10: =COUNTIFS('2024 -2025-2026'!$M:$M,B10,'2024 -2025-2026'!$K:$K,"Scopus/WoS Journals",'2024 -2025-2026'!$G:$G,"2025") -> 0 | F10: =COUNTIFS('2024 -2025-2026'!$M:$M,B10,'2024 -2025-2026'!$K:$K,"Scopus/WoS Conference/Book Chapter/Others", '2024 -2025-2026'!$G:$G,"2025") -> 0 | G10: =COUNTIFS('2024 -2025-2026'!$M:$M,B10,'2024 -2025-2026'!$K:$K,"Student Publication", '2024 -2025-2026'!$G:$G,"2025") -> 0 | H10: =COUNTIFS('Patent - 2025'!$Q:$Q,B10,'Patent - 2025'!$D:$D,"Published") -> 0 | I10: =COUNTIFS('Patent - 2025'!$Q:$Q,B10,'Patent - 2025'!D:D,"Granted") -> 0 | J10: =SUM(D10:F10) -> 0 | K10: =SUM(D10:G10) -> 0 | L10: =COUNTIFS('2024 -2025-2026'!$M:$M,B10,'2024 -2025-2026'!$K:$K,"Book",'2024 -2025-2026'!$G:$G,"2025") -> 0 | P10: IT
A11: ='Name of the Faculty 2024'!A11 -> 10 | B11: ='Name of the Faculty 2024'!B11 -> Mr. Sridharan S | C11: ='Name of the Faculty 2024'!C11 -> AIDS | D11: =COUNTIFS('2024 -2025-2026'!$M:$M,B11,'2024 -2025-2026'!$K:$K,"SCI",'2024 -2025-2026'!$G:$G,"2025") -> 0 | E11: =COUNTIFS('2024 -2025-2026'!$M:$M,B11,'2024 -2025-2026'!$K:$K,"Scopus/WoS Journals",'2024 -2025-2026'!$G:$G,"2025") -> 0 | F11: =COUNTIFS('2024 -2025-2026'!$M:$M,B11,'2024 -2025-2026'!$K:$K,"Scopus/WoS Conference/Book Chapter/Others", '2024 -2025-2026'!$G:$G,"2025") -> 0 | G11: =COUNTIFS('2024 -2025-2026'!$M:$M,B11,'2024 -2025-2026'!$K:$K,"Student Publication", '2024 -2025-2026'!$G:$G,"2025") -> 0 | H11: =COUNTIFS('Patent - 2025'!$Q:$Q,B11,'Patent - 2025'!$D:$D,"Published") -> 0 | I11: =COUNTIFS('Patent - 2025'!$Q:$Q,B11,'Patent - 2025'!D:D,"Granted") -> 0 | J11: =SUM(D11:F11) -> 0 | K11: =SUM(D11:G11) -> 0 | L11: =COUNTIFS('2024 -2025-2026'!$M:$M,B11,'2024 -2025-2026'!$K:$K,"Book",'2024 -2025-2026'!$G:$G,"2025") -> 0 | P11: S&H (Eng)
A12: ='Name of the Faculty 2024'!A12 -> 11 | B12: ='Name of the Faculty 2024'!B12 -> Ms. Anitha E | C12: ='Name of the Faculty 2024'!C12 -> AIDS | D12: =COUNTIFS('2024 -2025-2026'!$M:$M,B12,'2024 -2025-2026'!$K:$K,"SCI",'2024 -2025-2026'!$G:$G,"2025") -> 0 | E12: =COUNTIFS('2024 -2025-2026'!$M:$M,B12,'2024 -2025-2026'!$K:$K,"Scopus/WoS Journals",'2024 -2025-2026'!$G:$G,"2025") -> 1 | F12: =COUNTIFS('2024 -2025-2026'!$M:$M,B12,'2024 -2025-2026'!$K:$K,"Scopus/WoS Conference/Book Chapter/Others", '2024 -2025-2026'!$G:$G,"2025") -> 0 | G12: =COUNTIFS('2024 -2025-2026'!$M:$M,B12,'2024 -2025-2026'!$K:$K,"Student Publication", '2024 -2025-2026'!$G:$G,"2025") -> 0 | H12: =COUNTIFS('Patent - 2025'!$Q:$Q,B12,'Patent - 2025'!$D:$D,"Published") -> 0 | I12: =COUNTIFS('Patent - 2025'!$Q:$Q,B12,'Patent - 2025'!D:D,"Granted") -> 0 | J12: =SUM(D12:F12) -> 1 | K12: =SUM(D12:G12) -> 1 | L12: =COUNTIFS('2024 -2025-2026'!$M:$M,B12,'2024 -2025-2026'!$K:$K,"Book",'2024 -2025-2026'!$G:$G,"2025") -> 0 | P12: CSE, IT, CCE
A13: ='Name of the Faculty 2024'!A13 -> 12 | B13: ='Name of the Faculty 2024'!B13 -> Ms. Divyaprabha R | C13: ='Name of the Faculty 2024'!C13 -> AIDS | D13: =COUNTIFS('2024 -2025-2026'!$M:$M,B13,'2024 -2025-2026'!$K:$K,"SCI",'2024 -2025-2026'!$G:$G,"2025") -> 0 | E13: =COUNTIFS('2024 -2025-2026'!$M:$M,B13,'2024 -2025-2026'!$K:$K,"Scopus/WoS Journals",'2024 -2025-2026'!$G:$G,"2025") -> 0 | F13: =COUNTIFS('2024 -2025-2026'!$M:$M,B13,'2024 -2025-2026'!$K:$K,"Scopus/WoS Conference/Book Chapter/Others", '2024 -2025-2026'!$G:$G,"2025") -> 0 | G13: =COUNTIFS('2024 -2025-2026'!$M:$M,B13,'2024 -2025-2026'!$K:$K,"Student Publication", '2024 -2025-2026'!$G:$G,"2025") -> 0 | H13: =COUNTIFS('Patent - 2025'!$Q:$Q,B13,'Patent - 2025'!$D:$D,"Published") -> 0 | I13: =COUNTIFS('Patent - 2025'!$Q:$Q,B13,'Patent - 2025'!D:D,"Granted") -> 0 | J13: =SUM(D13:F13) -> 0 | K13: =SUM(D13:G13) -> 0 | L13: =COUNTIFS('2024 -2025-2026'!$M:$M,B13,'2024 -2025-2026'!$K:$K,"Book",'2024 -2025-2026'!$G:$G,"2025") -> 0 | P13: MECH, S&H (Eng)
A14: ='Name of the Faculty 2024'!A14 -> 13 | B14: ='Name of the Faculty 2024'!B14 -> Ms. Esther Pushpam | C14: ='Name of the Faculty 2024'!C14 -> AIDS | D14: =COUNTIFS('2024 -2025-2026'!$M:$M,B14,'2024 -2025-2026'!$K:$K,"SCI",'2024 -2025-2026'!$G:$G,"2025") -> 0 | E14: =COUNTIFS('2024 -2025-2026'!$M:$M,B14,'2024 -2025-2026'!$K:$K,"Scopus/WoS Journals",'2024 -2025-2026'!$G:$G,"2025") -> 0 | F14: =COUNTIFS('2024 -2025-2026'!$M:$M,B14,'2024 -2025-2026'!$K:$K,"Scopus/WoS Conference/Book Chapter/Others", '2024 -2025-2026'!$G:$G,"2025") -> 0 | G14: =COUNTIFS('2024 -2025-2026'!$M:$M,B14,'2024 -2025-2026'!$K:$K,"Student Publication", '2024 -2025-2026'!$G:$G,"2025") -> 0 | H14: =COUNTIFS('Patent - 2025'!$Q:$Q,B14,'Patent - 2025'!$D:$D,"Published") -> 0 | I14: =COUNTIFS('Patent - 2025'!$Q:$Q,B14,'Patent - 2025'!D:D,"Granted") -> 0 | J14: =SUM(D14:F14) -> 0 | K14: =SUM(D14:G14) -> 0 | L14: =COUNTIFS('2024 -2025-2026'!$M:$M,B14,'2024 -2025-2026'!$K:$K,"Book",'2024 -2025-2026'!$G:$G,"2025") -> 0 | P14: S&H (Che)
A15: ='Name of the Faculty 2024'!A15 -> 14 | B15: ='Name of the Faculty 2024'!B15 -> Ms. Geetha Rajakumari R | C15: ='Name of the Faculty 2024'!C15 -> AIDS | D15: =COUNTIFS('2024 -2025-2026'!$M:$M,B15,'2024 -2025-2026'!$K:$K,"SCI",'2024 -2025-2026'!$G:$G,"2025") -> 0 | E15: =COUNTIFS('2024 -2025-2026'!$M:$M,B15,'2024 -2025-2026'!$K:$K,"Scopus/WoS Journals",'2024 -2025-2026'!$G:$G,"2025") -> 1 | F15: =COUNTIFS('2024 -2025-2026'!$M:$M,B15,'2024 -2025-2026'!$K:$K,"Scopus/WoS Conference/Book Chapter/Others", '2024 -2025-2026'!$G:$G,"2025") -> 1 | G15: =COUNTIFS('2024 -2025-2026'!$M:$M,B15,'2024 -2025-2026'!$K:$K,"Student Publication", '2024 -2025-2026'!$G:$G,"2025") -> 2 | H15: =COUNTIFS('Patent - 2025'!$Q:$Q,B15,'Patent - 2025'!$D:$D,"Published") -> 1 | I15: =COUNTIFS('Patent - 2025'!$Q:$Q,B15,'Patent - 2025'!D:D,"Granted") -> 0 | J15: =SUM(D15:F15) -> 2 | K15: =SUM(D15:G15) -> 4 | L15: =COUNTIFS('2024 -2025-2026'!$M:$M,B15,'2024 -2025-2026'!$K:$K,"Book",'2024 -2025-2026'!$G:$G,"2025") -> 0 | P15: S&H (Maths)
A16: ='Name of the Faculty 2024'!A16 -> 15 | B16: ='Name of the Faculty 2024'!B16 -> Ms. Gowri S | C16: ='Name of the Faculty 2024'!C16 -> AIDS | D16: =COUNTIFS('2024 -2025-2026'!$M:$M,B16,'2024 -2025-2026'!$K:$K,"SCI",'2024 -2025-2026'!$G:$G,"2025") -> 0 | E16: =COUNTIFS('2024 -2025-2026'!$M:$M,B16,'2024 -2025-2026'!$K:$K,"Scopus/WoS Journals",'2024 -2025-2026'!$G:$G,"2025") -> 0 | F16: =COUNTIFS('2024 -2025-2026'!$M:$M,B16,'2024 -2025-2026'!$K:$K,"Scopus/WoS Conference/Book Chapter/Others", '2024 -2025-2026'!$G:$G,"2025") -> 1 | G16: =COUNTIFS('2024 -2025-2026'!$M:$M,B16,'2024 -2025-2026'!$K:$K,"Student Publication", '2024 -2025-2026'!$G:$G,"2025") -> 0 | H16: =COUNTIFS('Patent - 2025'!$Q:$Q,B16,'Patent - 2025'!$D:$D,"Published") -> 2 | I16: =COUNTIFS('Patent - 2025'!$Q:$Q,B16,'Patent - 2025'!D:D,"Granted") -> 0 | J16: =SUM(D16:F16) -> 1 | K16: =SUM(D16:G16) -> 1 | L16: =COUNTIFS('2024 -2025-2026'!$M:$M,B16,'2024 -2025-2026'!$K:$K,"Book",'2024 -2025-2026'!$G:$G,"2025") -> 0 | P16: S&H (Phy)
A17: ='Name of the Faculty 2024'!A17 -> 16 | B17: ='Name of the Faculty 2024'!B17 -> Ms. Parvathy K | C17: ='Name of the Faculty 2024'!C17 -> AIDS | D17: =COUNTIFS('2024 -2025-2026'!$M:$M,B17,'2024 -2025-2026'!$K:$K,"SCI",'2024 -2025-2026'!$G:$G,"2025") -> 0 | E17: =COUNTIFS('2024 -2025-2026'!$M:$M,B17,'2024 -2025-2026'!$K:$K,"Scopus/WoS Journals",'2024 -2025-2026'!$G:$G,"2025") -> 0 | F17: =COUNTIFS('2024 -2025-2026'!$M:$M,B17,'2024 -2025-2026'!$K:$K,"Scopus/WoS Conference/Book Chapter/Others", '2024 -2025-2026'!$G:$G,"2025") -> 15 | G17: =COUNTIFS('2024 -2025-2026'!$M:$M,B17,'2024 -2025-2026'!$K:$K,"Student Publication", '2024 -2025-2026'!$G:$G,"2025") -> 0 | H17: =COUNTIFS('Patent - 2025'!$Q:$Q,B17,'Patent - 2025'!$D:$D,"Published") -> 1 | I17: =COUNTIFS('Patent - 2025'!$Q:$Q,B17,'Patent - 2025'!D:D,"Granted") -> 0 | J17: =SUM(D17:F17) -> 15 | K17: =SUM(D17:G17) -> 15 | L17: =COUNTIFS('2024 -2025-2026'!$M:$M,B17,'2024 -2025-2026'!$K:$K,"Book",'2024 -2025-2026'!$G:$G,"2025") -> 0 | P17: Student Publication AIDS
A18: ='Name of the Faculty 2024'!A18 -> 17 | B18: ='Name of the Faculty 2024'!B18 -> Ms. Rajalakshmi S | C18: ='Name of the Faculty 2024'!C18 -> AIDS | D18: =COUNTIFS('2024 -2025-2026'!$M:$M,B18,'2024 -2025-2026'!$K:$K,"SCI",'2024 -2025-2026'!$G:$G,"2025") -> 0 | E18: =COUNTIFS('2024 -2025-2026'!$M:$M,B18,'2024 -2025-2026'!$K:$K,"Scopus/WoS Journals",'2024 -2025-2026'!$G:$G,"2025") -> 0 | F18: =COUNTIFS('2024 -2025-2026'!$M:$M,B18,'2024 -2025-2026'!$K:$K,"Scopus/WoS Conference/Book Chapter/Others", '2024 -2025-2026'!$G:$G,"2025") -> 1 | G18: =COUNTIFS('2024 -2025-2026'!$M:$M,B18,'2024 -2025-2026'!$K:$K,"Student Publication", '2024 -2025-2026'!$G:$G,"2025") -> 0 | H18: =COUNTIFS('Patent - 2025'!$Q:$Q,B18,'Patent - 2025'!$D:$D,"Published") -> 1 | I18: =COUNTIFS('Patent - 2025'!$Q:$Q,B18,'Patent - 2025'!D:D,"Granted") -> 0 | J18: =SUM(D18:F18) -> 1 | K18: =SUM(D18:G18) -> 1 | L18: =COUNTIFS('2024 -2025-2026'!$M:$M,B18,'2024 -2025-2026'!$K:$K,"Book",'2024 -2025-2026'!$G:$G,"2025") -> 0 | P18: Student Publication CCE
A19: ='Name of the Faculty 2024'!A19 -> 18 | B19: ='Name of the Faculty 2024'!B19 -> Ms. Sangavi V | C19: ='Name of the Faculty 2024'!C19 -> AIDS | D19: =COUNTIFS('2024 -2025-2026'!$M:$M,B19,'2024 -2025-2026'!$K:$K,"SCI",'2024 -2025-2026'!$G:$G,"2025") -> 0 | E19: =COUNTIFS('2024 -2025-2026'!$M:$M,B19,'2024 -2025-2026'!$K:$K,"Scopus/WoS Journals",'2024 -2025-2026'!$G:$G,"2025") -> 0 | F19: =COUNTIFS('2024 -2025-2026'!$M:$M,B19,'2024 -2025-2026'!$K:$K,"Scopus/WoS Conference/Book Chapter/Others", '2024 -2025-2026'!$G:$G,"2025") -> 2 | G19: =COUNTIFS('2024 -2025-2026'!$M:$M,B19,'2024 -2025-2026'!$K:$K,"Student Publication", '2024 -2025-2026'!$G:$G,"2025") -> 0 | H19: =COUNTIFS('Patent - 2025'!$Q:$Q,B19,'Patent - 2025'!$D:$D,"Published") -> 1 | I19: =COUNTIFS('Patent - 2025'!$Q:$Q,B19,'Patent - 2025'!D:D,"Granted") -> 0 | J19: =SUM(D19:F19) -> 2 | K19: =SUM(D19:G19) -> 2 | L19: =COUNTIFS('2024 -2025-2026'!$M:$M,B19,'2024 -2025-2026'!$K:$K,"Book",'2024 -2025-2026'!$G:$G,"2025") -> 0 | P19: Student Publication CSBS
... A25: ='Name of the Faculty 2024'!A25 -> 24 | B25: ='Name of the Faculty 2024'!B25 -> Dr. Sumathi S | C25: ='Name of the Faculty 2024'!C25 -> AIML | D25: =COUNTIFS('2024 -2025-2026'!$M:$M,B25,'2024 -2025-2026'!$K:$K,"SCI",'2024 -2025-2026'!$G:$G,"2025") -> 0 | E25: =COUNTIFS('2024 -2025-2026'!$M:$M,B25,'2024 -2025-2026'!$K:$K,"Scopus/WoS Journals",'2024 -2025-2026'!$G:$G,"2025") -> 1 | F25: =COUNTIFS('2024 -2025-2026'!$M:$M,B25,'2024 -2025-2026'!$K:$K,"Scopus/WoS Conference/Book Chapter/Others", '2024 -2025-2026'!$G:$G,"2025") -> 2 | G25: =COUNTIFS('2024 -2025-2026'!$M:$M,B25,'2024 -2025-2026'!$K:$K,"Student Publication", '2024 -2025-2026'!$G:$G,"2025") -> 3 | H25: =COUNTIFS('Patent - 2025'!$Q:$Q,B25,'Patent - 2025'!$D:$D,"Published") -> 1 | I25: =COUNTIFS('Patent - 2025'!$Q:$Q,B25,'Patent - 2025'!D:D,"Granted") -> 0 | J25: =SUM(D25:F25) -> 3 | K25: =SUM(D25:G25) -> 6 | L25: =COUNTIFS('2024 -2025-2026'!$M:$M,B25,'2024 -2025-2026'!$K:$K,"Book",'2024 -2025-2026'!$G:$G,"2025") -> 0 | P25: S&H
A26: ='Name of the Faculty 2024'!A26 -> 25 | B26: ='Name of the Faculty 2024'!B26 -> Dr. Kathiresan K | C26: ='Name of the Faculty 2024'!C26 -> AIML | D26: =COUNTIFS('2024 -2025-2026'!$M:$M,B26,'2024 -2025-2026'!$K:$K,"SCI",'2024 -2025-2026'!$G:$G,"2025") -> 0 | E26: =COUNTIFS('2024 -2025-2026'!$M:$M,B26,'2024 -2025-2026'!$K:$K,"Scopus/WoS Journals",'2024 -2025-2026'!$G:$G,"2025") -> 0 | F26: =COUNTIFS('2024 -2025-2026'!$M:$M,B26,'2024 -2025-2026'!$K:$K,"Scopus/WoS Conference/Book Chapter/Others", '2024 -2025-2026'!$G:$G,"2025") -> 0 | G26: =COUNTIFS('2024 -2025-2026'!$M:$M,B26,'2024 -2025-2026'!$K:$K,"Student Publication", '2024 -2025-2026'!$G:$G,"2025") -> 0 | H26: =COUNTIFS('Patent - 2025'!$Q:$Q,B26,'Patent - 2025'!$D:$D,"Published") -> 1 | I26: =COUNTIFS('Patent - 2025'!$Q:$Q,B26,'Patent - 2025'!D:D,"Granted") -> 0 | J26: =SUM(D26:F26) -> 0 | K26: =SUM(D26:G26) -> 0 | L26: =COUNTIFS('2024 -2025-2026'!$M:$M,B26,'2024 -2025-2026'!$K:$K,"Book",'2024 -2025-2026'!$G:$G,"2025") -> 0
A27: ='Name of the Faculty 2024'!A27 -> 26 | B27: ='Name of the Faculty 2024'!B27 -> Ms. Preethi P | C27: ='Name of the Faculty 2024'!C27 -> AIML | D27: =COUNTIFS('2024 -2025-2026'!$M:$M,B27,'2024 -2025-2026'!$K:$K,"SCI",'2024 -2025-2026'!$G:$G,"2025") -> 0 | E27: =COUNTIFS('2024 -2025-2026'!$M:$M,B27,'2024 -2025-2026'!$K:$K,"Scopus/WoS Journals",'2024 -2025-2026'!$G:$G,"2025") -> 0 | F27: =COUNTIFS('2024 -2025-2026'!$M:$M,B27,'2024 -2025-2026'!$K:$K,"Scopus/WoS Conference/Book Chapter/Others", '2024 -2025-2026'!$G:$G,"2025") -> 1 | G27: =COUNTIFS('2024 -2025-2026'!$M:$M,B27,'2024 -2025-2026'!$K:$K,"Student Publication", '2024 -2025-2026'!$G:$G,"2025") -> 0 | H27: =COUNTIFS('Patent - 2025'!$Q:$Q,B27,'Patent - 2025'!$D:$D,"Published") -> 1 | I27: =COUNTIFS('Patent - 2025'!$Q:$Q,B27,'Patent - 2025'!D:D,"Granted") -> 0 | J27: =SUM(D27:F27) -> 1 | K27: =SUM(D27:G27) -> 1 | L27: =COUNTIFS('2024 -2025-2026'!$M:$M,B27,'2024 -2025-2026'!$K:$K,"Book",'2024 -2025-2026'!$G:$G,"2025") -> 0
A28: ='Name of the Faculty 2024'!A28 -> 27 | B28: ='Name of the Faculty 2024'!B28 -> Ms. Sindhuja S | C28: ='Name of the Faculty 2024'!C28 -> AIML | D28: =COUNTIFS('2024 -2025-2026'!$M:$M,B28,'2024 -2025-2026'!$K:$K,"SCI",'2024 -2025-2026'!$G:$G,"2025") -> 0 | E28: =COUNTIFS('2024 -2025-2026'!$M:$M,B28,'2024 -2025-2026'!$K:$K,"Scopus/WoS Journals",'2024 -2025-2026'!$G:$G,"2025") -> 1 | F28: =COUNTIFS('2024 -2025-2026'!$M:$M,B28,'2024 -2025-2026'!$K:$K,"Scopus/WoS Conference/Book Chapter/Others", '2024 -2025-2026'!$G:$G,"2025") -> 1 | G28: =COUNTIFS('2024 -2025-2026'!$M:$M,B28,'2024 -2025-2026'!$K:$K,"Student Publication", '2024 -2025-2026'!$G:$G,"2025") -> 0 | H28: =COUNTIFS('Patent - 2025'!$Q:$Q,B28,'Patent - 2025'!$D:$D,"Published") -> 1 | I28: =COUNTIFS('Patent - 2025'!$Q:$Q,B28,'Patent - 2025'!D:D,"Granted") -> 0 | J28: =SUM(D28:F28) -> 2 | K28: =SUM(D28:G28) -> 2 | L28: =COUNTIFS('2024 -2025-2026'!$M:$M,B28,'2024 -2025-2026'!$K:$K,"Book",'2024 -2025-2026'!$G:$G,"2025") -> 0
A29: ='Name of the Faculty 2024'!A29 -> 28 | B29: ='Name of the Faculty 2024'!B29 -> Ms. Kalaivani T | C29: ='Name of the Faculty 2024'!C29 -> AIML | D29: =COUNTIFS('2024 -2025-2026'!$M:$M,B29,'2024 -2025-2026'!$K:$K,"SCI",'2024 -2025-2026'!$G:$G,"2025") -> 1 | E29: =COUNTIFS('2024 -2025-2026'!$M:$M,B29,'2024 -2025-2026'!$K:$K,"Scopus/WoS Journals",'2024 -2025-2026'!$G:$G,"2025") -> 0 | F29: =COUNTIFS('2024 -2025-2026'!$M:$M,B29,'2024 -2025-2026'!$K:$K,"Scopus/WoS Conference/Book Chapter/Others", '2024 -2025-2026'!$G:$G,"2025") -> 4 | G29: =COUNTIFS('2024 -2025-2026'!$M:$M,B29,'2024 -2025-2026'!$K:$K,"Student Publication", '2024 -2025-2026'!$G:$G,"2025") -> 1 | H29: =COUNTIFS('Patent - 2025'!$Q:$Q,B29,'Patent - 2025'!$D:$D,"Published") -> 3 | I29: =COUNTIFS('Patent - 2025'!$Q:$Q,B29,'Patent - 2025'!D:D,"Granted") -> 0 | J29: =SUM(D29:F29) -> 5 | K29: =SUM(D29:G29) -> 6 | L29: =COUNTIFS('2024 -2025-2026'!$M:$M,B29,'2024 -2025-2026'!$K:$K,"Book",'2024 -2025-2026'!$G:$G,"2025") -> 0
A30: ='Name of the Faculty 2024'!A30 -> 29 | B30: ='Name of the Faculty 2024'!B30 -> Ms. Charanya P | C30: ='Name of the Faculty 2024'!C30 -> AIML | D30: =COUNTIFS('2024 -2025-2026'!$M:$M,B30,'2024 -2025-2026'!$K:$K,"SCI",'2024 -2025-2026'!$G:$G,"2025") -> 0 | E30: =COUNTIFS('2024 -2025-2026'!$M:$M,B30,'2024 -2025-2026'!$K:$K,"Scopus/WoS Journals",'2024 -2025-2026'!$G:$G,"2025") -> 0 | F30: =COUNTIFS('2024 -2025-2026'!$M:$M,B30,'2024 -2025-2026'!$K:$K,"Scopus/WoS Conference/Book Chapter/Others", '2024 -2025-2026'!$G:$G,"2025") -> 2 | G30: =COUNTIFS('2024 -2025-2026'!$M:$M,B30,'2024 -2025-2026'!$K:$K,"Student Publication", '2024 -2025-2026'!$G:$G,"2025") -> 2 | H30: =COUNTIFS('Patent - 2025'!$Q:$Q,B30,'Patent - 2025'!$D:$D,"Published") -> 0 | I30: =COUNTIFS('Patent - 2025'!$Q:$Q,B30,'Patent - 2025'!D:D,"Granted") -> 0 | J30: =SUM(D30:F30) -> 2 | K30: =SUM(D30:G30) -> 4 | L30: =COUNTIFS('2024 -2025-2026'!$M:$M,B30,'2024 -2025-2026'!$K:$K,"Book",'2024 -2025-2026'!$G:$G,"2025") -> 0
A31: ='Name of the Faculty 2024'!A31 -> 30 | B31: ='Name of the Faculty 2024'!B31 -> Dr. Babitha Lincy R | C31: ='Name of the Faculty 2024'!C31 -> CCE | D31: =COUNTIFS('2024 -2025-2026'!$M:$M,B31,'2024 -2025-2026'!$K:$K,"SCI",'2024 -2025-2026'!$G:$G,"2025") -> 1 | E31: =COUNTIFS('2024 -2025-2026'!$M:$M,B31,'2024 -2025-2026'!$K:$K,"Scopus/WoS Journals",'2024 -2025-2026'!$G:$G,"2025") -> 0 | F31: =COUNTIFS('2024 -2025-2026'!$M:$M,B31,'2024 -2025-2026'!$K:$K,"Scopus/WoS Conference/Book Chapter/Others", '2024 -2025-2026'!$G:$G,"2025") -> 14 | G31: =COUNTIFS('2024 -2025-2026'!$M:$M,B31,'2024 -2025-2026'!$K:$K,"Student Publication", '2024 -2025-2026'!$G:$G,"2025") -> 1 | H31: =COUNTIFS('Patent - 2025'!$Q:$Q,B31,'Patent - 2025'!$D:$D,"Published") -> 1 | I31: =COUNTIFS('Patent - 2025'!$Q:$Q,B31,'Patent - 2025'!D:D,"Granted") -> 0 | J31: =SUM(D31:F31) -> 15 | K31: =SUM(D31:G31) -> 16 | L31: =COUNTIFS('2024 -2025-2026'!$M:$M,B31,'2024 -2025-2026'!$K:$K,"Book",'2024 -2025-2026'!$G:$G,"2025") -> 0
A32: ='Name of the Faculty 2024'!A32 -> 31 | B32: ='Name of the Faculty 2024'!B32 -> Dr. Dhamodharan S | C32: ='Name of the Faculty 2024'!C32 -> CCE | D32: =COUNTIFS('2024 -2025-2026'!$M:$M,B32,'2024 -2025-2026'!$K:$K,"SCI",'2024 -2025-2026'!$G:$G,"2025") -> 3 | E32: =COUNTIFS('2024 -2025-2026'!$M:$M,B32,'2024 -2025-2026'!$K:$K,"Scopus/WoS Journals",'2024 -2025-2026'!$G:$G,"2025") -> 0 | F32: =COUNTIFS('2024 -2025-2026'!$M:$M,B32,'2024 -2025-2026'!$K:$K,"Scopus/WoS Conference/Book Chapter/Others", '2024 -2025-2026'!$G:$G,"2025") -> 3 | G32: =COUNTIFS('2024 -2025-2026'!$M:$M,B32,'2024 -2025-2026'!$K:$K,"Student Publication", '2024 -2025-2026'!$G:$G,"2025") -> 3 | H32: =COUNTIFS('Patent - 2025'!$Q:$Q,B32,'Patent - 2025'!$D:$D,"Published") -> 0 | I32: =COUNTIFS('Patent - 2025'!$Q:$Q,B32,'Patent - 2025'!D:D,"Granted") -> 0 | J32: =SUM(D32:F32) -> 6 | K32: =SUM(D32:G32) -> 9 | L32: =COUNTIFS('2024 -2025-2026'!$M:$M,B32,'2024 -2025-2026'!$K:$K,"Book",'2024 -2025-2026'!$G:$G,"2025") -> 0
A33: ='Name of the Faculty 2024'!A33 -> 32 | B33: ='Name of the Faculty 2024'!B33 -> Dr. Ganesh C | C33: ='Name of the Faculty 2024'!C33 -> CCE | D33: =COUNTIFS('2024 -2025-2026'!$M:$M,B33,'2024 -2025-2026'!$K:$K,"SCI",'2024 -2025-2026'!$G:$G,"2025") -> 4 | E33: =COUNTIFS('2024 -2025-2026'!$M:$M,B33,'2024 -2025-2026'!$K:$K,"Scopus/WoS Journals",'2024 -2025-2026'!$G:$G,"2025") -> 1 | F33: =COUNTIFS('2024 -2025-2026'!$M:$M,B33,'2024 -2025-2026'!$K:$K,"Scopus/WoS Conference/Book Chapter/Others", '2024 -2025-2026'!$G:$G,"2025") -> 3 | G33: =COUNTIFS('2024 -2025-2026'!$M:$M,B33,'2024 -2025-2026'!$K:$K,"Student Publication", '2024 -2025-2026'!$G:$G,"2025") -> 2 | H33: =COUNTIFS('Patent - 2025'!$Q:$Q,B33,'Patent - 2025'!$D:$D,"Published") -> 1 | I33: =COUNTIFS('Patent - 2025'!$Q:$Q,B33,'Patent - 2025'!D:D,"Granted") -> 0 | J33: =SUM(D33:F33) -> 8 | K33: =SUM(D33:G33) -> 10 | L33: =COUNTIFS('2024 -2025-2026'!$M:$M,B33,'2024 -2025-2026'!$K:$K,"Book",'2024 -2025-2026'!$G:$G,"2025") -> 0
A34: ='Name of the Faculty 2024'!A34 -> 33 | B34: ='Name of the Faculty 2024'!B34 -> Dr. Thirrunavukkarasu R R | C34: ='Name of the Faculty 2024'!C34 -> CCE | D34: =COUNTIFS('2024 -2025-2026'!$M:$M,B34,'2024 -2025-2026'!$K:$K,"SCI",'2024 -2025-2026'!$G:$G,"2025") -> 0 | E34: =COUNTIFS('2024 -2025-2026'!$M:$M,B34,'2024 -2025-2026'!$K:$K,"Scopus/WoS Journals",'2024 -2025-2026'!$G:$G,"2025") -> 0 | F34: =COUNTIFS('2024 -2025-2026'!$M:$M,B34,'2024 -2025-2026'!$K:$K,"Scopus/WoS Conference/Book Chapter/Others", '2024 -2025-2026'!$G:$G,"2025") -> 1 | G34: =COUNTIFS('2024 -2025-2026'!$M:$M,B34,'2024 -2025-2026'!$K:$K,"Student Publication", '2024 -2025-2026'!$G:$G,"2025") -> 1 | H34: =COUNTIFS('Patent - 2025'!$Q:$Q,B34,'Patent - 2025'!$D:$D,"Published") -> 0 | I34: =COUNTIFS('Patent - 2025'!$Q:$Q,B34,'Patent - 2025'!D:D,"Granted") -> 0 | J34: =SUM(D34:F34) -> 1 | K34: =SUM(D34:G34) -> 2 | L34: =COUNTIFS('2024 -2025-2026'!$M:$M,B34,'2024 -2025-2026'!$K:$K,"Book",'2024 -2025-2026'!$G:$G,"2025") -> 0
A35: ='Name of the Faculty 2024'!A35 -> 34 | B35: ='Name of the Faculty 2024'!B35 -> Dr. Vivek C | C35: ='Name of the Faculty 2024'!C35 -> CCE | D35: =COUNTIFS('2024 -2025-2026'!$M:$M,B35,'2024 -2025-2026'!$K:$K,"SCI",'2024 -2025-2026'!$G:$G,"2025") -> 1 | E35: =COUNTIFS('2024 -2025-2026'!$M:$M,B35,'2024 -2025-2026'!$K:$K,"Scopus/WoS Journals",'2024 -2025-2026'!$G:$G,"2025") -> 0 | F35: =COUNTIFS('2024 -2025-2026'!$M:$M,B35,'2024 -2025-2026'!$K:$K,"Scopus/WoS Conference/Book Chapter/Others", '2024 -2025-2026'!$G:$G,"2025") -> 0 | G35: =COUNTIFS('2024 -2025-2026'!$M:$M,B35,'2024 -2025-2026'!$K:$K,"Student Publication", '2024 -2025-2026'!$G:$G,"2025") -> 0 | H35: =COUNTIFS('Patent - 2025'!$Q:$Q,B35,'Patent - 2025'!$D:$D,"Published") -> 0 | I35: =COUNTIFS('Patent - 2025'!$Q:$Q,B35,'Patent - 2025'!D:D,"Granted") -> 0 | J35: =SUM(D35:F35) -> 1 | K35: =SUM(D35:G35) -> 1 | L35: =COUNTIFS('2024 -2025-2026'!$M:$M,B35,'2024 -2025-2026'!$K:$K,"Book",'2024 -2025-2026'!$G:$G,"2025") -> 0
A36: ='Name of the Faculty 2024'!A36 -> 35 | B36: ='Name of the Faculty 2024'!B36 -> Mr. Arun R | C36: ='Name of the Faculty 2024'!C36 -> CCE | D36: =COUNTIFS('2024 -2025-2026'!$M:$M,B36,'2024 -2025-2026'!$K:$K,"SCI",'2024 -2025-2026'!$G:$G,"2025") -> 0 | E36: =COUNTIFS('2024 -2025-2026'!$M:$M,B36,'2024 -2025-2026'!$K:$K,"Scopus/WoS Journals",'2024 -2025-2026'!$G:$G,"2025") -> 0 | F36: =COUNTIFS('2024 -2025-2026'!$M:$M,B36,'2024 -2025-2026'!$K:$K,"Scopus/WoS Conference/Book Chapter/Others", '2024 -2025-2026'!$G:$G,"2025") -> 2 | G36: =COUNTIFS('2024 -2025-2026'!$M:$M,B36,'2024 -2025-2026'!$K:$K,"Student Publication", '2024 -2025-2026'!$G:$G,"2025") -> 0 | H36: =COUNTIFS('Patent - 2025'!$Q:$Q,B36,'Patent - 2025'!$D:$D,"Published") -> 0 | I36: =COUNTIFS('Patent - 2025'!$Q:$Q,B36,'Patent - 2025'!D:D,"Granted") -> 0 | J36: =SUM(D36:F36) -> 2 | K36: =SUM(D36:G36) -> 2 | L36: =COUNTIFS('2024 -2025-2026'!$M:$M,B36,'2024 -2025-2026'!$K:$K,"Book",'2024 -2025-2026'!$G:$G,"2025") -> 0
A37: ='Name of the Faculty 2024'!A37 -> 36 | B37: ='Name of the Faculty 2024'!B37 -> Ms. Banu Priya N | C37: ='Name of the Faculty 2024'!C37 -> CCE | D37: =COUNTIFS('2024 -2025-2026'!$M:$M,B37,'2024 -2025-2026'!$K:$K,"SCI",'2024 -2025-2026'!$G:$G,"2025") -> 0 | E37: =COUNTIFS('2024 -2025-2026'!$M:$M,B37,'2024 -2025-2026'!$K:$K,"Scopus/WoS Journals",'2024 -2025-2026'!$G:$G,"2025") -> 0 | F37: =COUNTIFS('2024 -2025-2026'!$M:$M,B37,'2024 -2025-2026'!$K:$K,"Scopus/WoS Conference/Book Chapter/Others", '2024 -2025-2026'!$G:$G,"2025") -> 5 | G37: =COUNTIFS('2024 -2025-2026'!$M:$M,B37,'2024 -2025-2026'!$K:$K,"Student Publication", '2024 -2025-2026'!$G:$G,"2025") -> 2 | H37: =COUNTIFS('Patent - 2025'!$Q:$Q,B37,'Patent - 2025'!$D:$D,"Published") -> 1 | I37: =COUNTIFS('Patent - 2025'!$Q:$Q,B37,'Patent - 2025'!D:D,"Granted") -> 0 | J37: =SUM(D37:F37) -> 5 | K37: =SUM(D37:G37) -> 7 | L37: =COUNTIFS('2024 -2025-2026'!$M:$M,B37,'2024 -2025-2026'!$K:$K,"Book",'2024 -2025-2026'!$G:$G,"2025") -> 0
... A141: ='Name of the Faculty 2024'!A141 -> 140 | B141: ='Name of the Faculty 2024'!B141 -> Ms. Shanmuga Priya A | C141: ='Name of the Faculty 2024'!C141 -> ECE | D141: =COUNTIFS('2024 -2025-2026'!$M:$M,B141,'2024 -2025-2026'!$K:$K,"SCI",'2024 -2025-2026'!$G:$G,"2025") -> 1 | E141: =COUNTIFS('2024 -2025-2026'!$M:$M,B141,'2024 -2025-2026'!$K:$K,"Scopus/WoS Journals",'2024 -2025-2026'!$G:$G,"2025") -> 0 | F141: =COUNTIFS('2024 -2025-2026'!$M:$M,B141,'2024 -2025-2026'!$K:$K,"Scopus/WoS Conference/Book Chapter/Others", '2024 -2025-2026'!$G:$G,"2025") -> 2 | G141: =COUNTIFS('2024 -2025-2026'!$M:$M,B141,'2024 -2025-2026'!$K:$K,"Student Publication", '2024 -2025-2026'!$G:$G,"2025") -> 3 | H141: =COUNTIFS('Patent - 2025'!$Q:$Q,B141,'Patent - 2025'!$D:$D,"Published") -> 1 | I141: =COUNTIFS('Patent - 2025'!$Q:$Q,B141,'Patent - 2025'!D:D,"Granted") -> 0 | J141: =SUM(D141:F141) -> 3 | K141: =SUM(D141:G141) -> 6 | L141: =COUNTIFS('2024 -2025-2026'!$M:$M,B141,'2024 -2025-2026'!$K:$K,"Book",'2024 -2025-2026'!$G:$G,"2025") -> 0
